Workbook

Sheet grouping by
A1: ValidRule | B1: Long Text | C1: Field name | D1: Lookup | E1: Key
B2: Intermediate DE Val.: ZIP Accounts only | C2: /1FB/CURKEY_GC | D2: =VLOOKUP(C2,'lookup table'!$A$2:$B$19,2,FALSE) -> #N/A | E2: =IF(ISNA(D2),"",IF(A2="","",A2) & "|" & D2)
B3: Intermediate DE Val.: ZIP LOB: PN02-PN09 | C3: /1FB/CURKEY_GC | D3: =VLOOKUP(C3,'lookup table'!$A$2:$B$19,2,FALSE) -> #N/A | E3: =IF(ISNA(D3),"",IF(A3="","",A3) & "|" & D3)
B4: Intermediate DE Val.: IFRS MAT only ZZZ / blank - Segm. | C4: /1FB/CURKEY_GC | D4: =VLOOKUP(C4,'lookup table'!$A$2:$B$19,2,FALSE) -> #N/A | E4: =IF(ISNA(D4),"",IF(A4="","",A4) & "|" & D4)
B5: Intermediate DE Val.: ZIP Accounts only | C5: /1FB/CURKEY_LC | D5: =VLOOKUP(C5,'lookup table'!$A$2:$B$19,2,FALSE) -> #N/A | E5: =IF(ISNA(D5),"",IF(A5="","",A5) & "|" & D5)
B6: Intermediate DE Val.: ZIP LOB: PN02-PN09 | C6: /1FB/CURKEY_LC | D6: =VLOOKUP(C6,'lookup table'!$A$2:$B$19,2,FALSE) -> #N/A | E6: =IF(ISNA(D6),"",IF(A6="","",A6) & "|" & D6)
B7: Intermediate DE Val.: IFRS MAT only ZZZ / blank - Segm. | C7: /1FB/CURKEY_LC | D7: =VLOOKUP(C7,'lookup table'!$A$2:$B$19,2,FALSE) -> #N/A | E7: =IF(ISNA(D7),"",IF(A7="","",A7) & "|" & D7)
B8: Intermediate DE Val.: ZIP Accounts only | C8: /1FB/CURKEY_TC | D8: =VLOOKUP(C8,'lookup table'!$A$2:$B$19,2,FALSE) -> #N/A | E8: =IF(ISNA(D8),"",IF(A8="","",A8) & "|" & D8)
B9: Intermediate DE Val.: ZIP LOB: PN02-PN09 | C9: /1FB/CURKEY_TC | D9: =VLOOKUP(C9,'lookup table'!$A$2:$B$19,2,FALSE) -> #N/A | E9: =IF(ISNA(D9),"",IF(A9="","",A9) & "|" & D9)
B10: Blocked combinations of accounts and maturity | C10: /1FB/CURKEY_TC | D10: =VLOOKUP(C10,'lookup table'!$A$2:$B$19,2,FALSE) -> #N/A | E10: =IF(ISNA(D10),"",IF(A10="","",A10) & "|" & D10)
B11: Blocked combinations of accounts and maturity | C11: /1FB/CURKEY_TC | D11: =VLOOKUP(C11,'lookup table'!$A$2:$B$19,2,FALSE) -> #N/A | E11: =IF(ISNA(D11),"",IF(A11="","",A11) & "|" & D11)
B12: Intermediate DE Val.: IFRS MAT only ZZZ / blank - Segm. | C12: /1FB/CURKEY_TC | D12: =VLOOKUP(C12,'lookup table'!$A$2:$B$19,2,FALSE) -> #N/A | E12: =IF(ISNA(D12),"",IF(A12="","",A12) & "|" & D12)
B13: Blocked combinations of accounts and Asset/Liability | C13: /1FB/CURKEY_TC | D13: =VLOOKUP(C13,'lookup table'!$A$2:$B$19,2,FALSE) -> #N/A | E13: =IF(ISNA(D13),"",IF(A13="","",A13) & "|" & D13)
... B1687: Blocked combinations of accounts and Asset/Liability | C1687: UNIT | D1687: =VLOOKUP(C1687,'lookup table'!$A$2:$B$19,2,FALSE) -> #N/A | E1687: =IF(ISNA(D1687),"",IF(A1687="","",A1687) & "|" & D1687)
A1688: A004_70 | B1688: A004_70 No gains&losses to equity - Derivatives | C1688: /BIC/ZZF_FSACC | D1688: =VLOOKUP(C1688,'lookup table'!$A$2:$B$19,2,FALSE) -> FS Item | E1688: =IF(ISNA(D1688),"",IF(A1688="","",A1688) & "|" & D1688) -> A004_70|FS Item
A1689: A004_70 | B1689: A004_70 No gains&losses to equity - Derivatives | C1689: /BIC/ZZF_MOVTY | D1689: =VLOOKUP(C1689,'lookup table'!$A$2:$B$19,2,FALSE) -> ToM | E1689: =IF(ISNA(D1689),"",IF(A1689="","",A1689) & "|" & D1689) -> A004_70|ToM
A1690: A021_00 | B1690: A021_00: Block ToMs 406/407 for FVOCI Eq. securities FV Opt. | C1690: /BIC/ZZF_FSACC | D1690: =VLOOKUP(C1690,'lookup table'!$A$2:$B$19,2,FALSE) -> FS Item | E1690: =IF(ISNA(D1690),"",IF(A1690="","",A1690) & "|" & D1690) -> A021_00|FS Item
A1691: A021_00 | B1691: A021_00: Block ToMs 406/407 for FVOCI Eq. securities FV Opt. | C1691: /BIC/ZZF_GCOA | D1691: =VLOOKUP(C1691,'lookup table'!$A$2:$B$19,2,FALSE) -> ignore | E1691: =IF(ISNA(D1691),"",IF(A1691="","",A1691) & "|" & D1691) -> A021_00|ignore
A1692: A043_00 | B1692: A043_00: Pos. Impairm due to EGP chges FAS 97&120 contract | C1692: /BIC/ZZF_FSACC | D1692: =VLOOKUP(C1692,'lookup table'!$A$2:$B$19,2,FALSE) -> FS Item | E1692: =IF(ISNA(D1692),"",IF(A1692="","",A1692) & "|" & D1692) -> A043_00|FS Item
A1693: A043_00 | B1693: A043_00: Pos. Impairm due to EGP chges FAS 97&120 contract | C1693: /BIC/ZZF_GCOA | D1693: =VLOOKUP(C1693,'lookup table'!$A$2:$B$19,2,FALSE) -> ignore | E1693: =IF(ISNA(D1693),"",IF(A1693="","",A1693) & "|" & D1693) -> A043_00|ignore
A1694: A043_00 | B1694: A043_00: Pos. Impairm due to EGP chges FAS 97&120 contract | C1694: /BIC/ZZF_MOVTY | D1694: =VLOOKUP(C1694,'lookup table'!$A$2:$B$19,2,FALSE) -> ToM | E1694: =IF(ISNA(D1694),"",IF(A1694="","",A1694) & "|" & D1694) -> A043_00|ToM
A1695: A043_60 | B1695: A043_60: Pos.Impairm due to EGP changes | C1695: /BIC/ZZF_FSACC | D1695: =VLOOKUP(C1695,'lookup table'!$A$2:$B$19,2,FALSE) -> FS Item | E1695: =IF(ISNA(D1695),"",IF(A1695="","",A1695) & "|" & D1695) -> A043_60|FS Item
A1696: A043_60 | B1696: A043_60: Pos.Impairm due to EGP changes | C1696: /BIC/ZZF_GCOA | D1696: =VLOOKUP(C1696,'lookup table'!$A$2:$B$19,2,FALSE) -> ignore | E1696: =IF(ISNA(D1696),"",IF(A1696="","",A1696) & "|" & D1696) -> A043_60|ignore
A1697: A043_60 | B1697: A043_60: Pos.Impairm due to EGP changes | C1697: /BIC/ZZF_MOVTY | D1697: =VLOOKUP(C1697,'lookup table'!$A$2:$B$19,2,FALSE) -> ToM | E1697: =IF(ISNA(D1697),"",IF(A1697="","",A1697) & "|" & D1697) -> A043_60|ToM
A1698: A045_00 | B1698: A045_00: No Amort./Impairm on Land held for Inv at FV | C1698: /BIC/ZZF_FSACC | D1698: =VLOOKUP(C1698,'lookup table'!$A$2:$B$19,2,FALSE) -> FS Item | E1698: =IF(ISNA(D1698),"",IF(A1698="","",A1698) & "|" & D1698) -> A045_00|FS Item
A1699: A045_00 | B1699: A045_00: No Amort./Impairm on Land held for Inv at FV | C1699: /BIC/ZZF_GCOA | D1699: =VLOOKUP(C1699,'lookup table'!$A$2:$B$19,2,FALSE) -> ignore | E1699: =IF(ISNA(D1699),"",IF(A1699="","",A1699) & "|" & D1699) -> A045_00|ignore
... A12349: TR320_17 | B12349: TR020_17: FPR 2022 YTD IFRS 4 equals IFRS 17 - SF stat acc | C12349: CS_PLEVEL | D12349: =VLOOKUP(C12349,'lookup table'!$A$2:$B$19,2,FALSE) -> Posting Level | E12349: =IF(ISNA(D12349),"",IF(A12349="","",A12349) & "|" & D12349) -> TR320_17|Posting Level

Sheet lookup table
A1: FIP Data | B1: EBS item
A2: /BIC/ZZF_ASSLI | B2: ALC
A3: /BIC/ZZF_AYEAR | B3: AY
A4: /BIC/ZZF_BBACA | B4: BBA Set
A5: /BIC/ZZF_FSACC | B5: FS Item
A6: /BIC/ZZF_GRCED | B6: GRC
A7: /BIC/ZZF_GCOA | B7: ignore
A8: /BIC/ZZF_INVSE | B8: Investee Segment
A9: /BIC/ZZF_INVUN | B9: Investee Unit
A10: /BIC/ZZF_LOB | B10: LoB
A11: /BIC/ZZF_MATUR | B11: MAT
A12: /BIC/ZZF_PSEGM | B12: Partner Segment
... A19: /BIC/ZZF_VALUE | B19: VLT

Sheet cross checks all
A1: Type of change | B1: Status | C1: Category | D1: Sense Check | E1: X-Check No. | F1: Grouping By | G1: Grouping By
A2: Changed | B2: ACTIVE | C2: Fixed Assets | E2: A450_00 | F2: FS Item, ToM | G2: FS Item | H2: ToM | I2: =$E2 &"|" & G2 -> A450_00|FS Item | J2: =$E2 &"|" & H2 -> A450_00|ToM
A3: New xcheck or association | B3: ACTIVE | C3: Stammhaus / SLST | E3: AL602_60 | F3: FS Item | G3: FS Item | I3: =$E3 &"|" & G3 -> AL602_60|FS Item

Sheet comparison
A1: EBX | B1: FIP | C1: Comparison
A2: A450_00|FS Item | B2: =VLOOKUP(A2,'grouping by'!$E:$E,1,FALSE) -> A450_00|FS Item | C2: =A2=B2 -> TRUE
A3: A450_00|ToM | B3: =VLOOKUP(A3,'grouping by'!$E:$E,1,FALSE) -> A450_00|ToM | C3: =A3=B3 -> TRUE
A4: AL602_60|FS Item | B4: =VLOOKUP(A4,'grouping by'!$E:$E,1,FALSE) -> AL602_60|FS Item | C4: =A4=B4 -> TRUE
