Workbook

Sheet cross checks all
A1: Type of change | B1: Status | C1: Category | D1: Sense Check | E1: X-Check No. | F1: Inscope | G1: Reference X-Check (Condition) | H1: Applicable Quarters | I1: Included RUs | J1: Excluded RUs | K1: Reference X-Check (Limit, %) | L1: Description | M1: Version Spanning Validation | N1: Absolute (result) | O1: Account No. | P1: Account description | Q1: Exclude Account Type | R1: SubA No. | S1: SubA Description | T1: SST account category | U1: SII account category | V1: Operator (X-Check Term) | W1: Ending Balance Prior Year | X1: Operator 1 | Y1: Limit 1 | Z1: Operator 2 | AA1: Limit 2 | AB1: Absolute (Account/SubA) | AC1: % | AD1: Grouping By | AE1: Deactivation due to Hyperinflation (FIP) | AF1: Exclude Z-Core | AG1: IFRS New RFD | AH1: IFRS New SFD | AI1: IFRS New CFD | AJ1: Actual IFRS RFD | AK1: Actual IFRS SFD | AL1: Actual IFRS CFD | AM1: MHC RFD | AN1: MHC SFD | AO1: MHC CFD | AP1: Curr. Simulation Versions RFD | AQ1: Curr. Simulation Versions SFD | AR1: Curr. Simulation Versions CFD | AS1: Stammhaus SLST RFD | AT1: Stammhaus SLST SFD | AU1: Stammhaus SLST CFD | AV1: Stammhaus IFRS RFD | AW1: Stammhaus IFRS SFD | AX1: Stammhaus IFRS CFD | AY1: Plan/ Forecast (SU) RFD | AZ1: Plan/ Forecast (SU) SFD | BA1: Plan/ Forecast (SU) CFD | BB1: RI Assets RFD | BC1: RI Assets SFD | BD1: RI Assets CFD | BE1: Tax RFD | BF1: Tax SFD | BG1: Tax CFD | BH1: Equity RFD | BI1: Equity SFD | BJ1: Equity CFD | BK1: I/C RFD | BL1: I/C SFD | BM1: I/C CFD | BN1: IE GAAP RFD | BO1: IE GAAP SFD | BP1: IE GAAP CFD | BQ1: SST RFD | BR1: SST SFD | BS1: SST CFD | BT1: ZIC & ZLIC FINMA information RFD | BU1: ZIC & ZLIC FINMA information SFD | BV1: ZIC & ZLIC FINMA information CFD | BW1: SII RFD | BX1: SII SFD | BY1: SII CFD | BZ1: ZIP IFRS RFD | CA1: ZIP IFRS SFD | CB1: ZIP IFRS CFD | CC1: RI Assets IFRSN RFD | CD1: RI Assets IFRSN SFD | CE1: RI Assets IFRSN CFD | CF1: Equity IFRSN RFD | CG1: Equity IFRSN SFD | CH1: Equity IFRSN CFD | CI1: I/C IFRSN RFD | CJ1: I/C IFRSN SFD | CK1: I/C IFRSN CFD | CL1: Tax IFRSN RFD | CM1: Tax IFRSN SFD | CN1: Tax IFRSN CFD | CO1: DE GAAP RFD | CP1: DE GAAP SFD | CQ1: DE GAAP CFD
A2: Changed | B2: ACTIVE | C2: Loss allowance | E2: A011_09 | F2: =VLOOKUP(E2,Sheet2!$A:$A,1,FALSE) -> A011_09 | L2: A011_09 Transfer to 12-month ECL ToM should be total 0 | O2: 10891 | P2: Loss allow.stage1 -Am.Cost CDO/CLO | R2: 602 | S2: Transfer to 12-month ECL(S1) | V2: + | X2: >= | Y2: -5 | Z2: <= | AA2: 5 | AG2: e | AH2: e
A3: Changed | B3: ACTIVE | C3: Loss allowance | E3: A011_09 | F3: =VLOOKUP(E3,Sheet2!$A:$A,1,FALSE) -> A011_09 | L3: A011_09 Transfer to 12-month ECL ToM should be total 0 | O3: 10931 | P3: Loss allow.stage2 -Am.Cost CDO/CLO | R3: 602 | S3: Transfer to 12-month ECL(S1) | V3: + | X3: >= | Y3: -5 | Z3: <= | AA3: 5 | AG3: e | AH3: e
A4: Changed | B4: ACTIVE | C4: Loss allowance | E4: A029_09 | F4: =VLOOKUP(E4,Sheet2!$A:$A,1,FALSE) -> A029_09 | L4: A029_09 Transfer to lifetime ECL ToM should be total 0 | O4: 10891 | P4: Loss allow.stage1 -Am.Cost CDO/CLO | R4: 603 | S4: Transfer to lifetime ECL(S2) | V4: + | X4: >= | Y4: -5 | Z4: <= | AA4: 5 | AG4: e | AH4: e
A5: Changed | B5: ACTIVE | C5: Loss allowance | E5: A029_09 | F5: =VLOOKUP(E5,Sheet2!$A:$A,1,FALSE) -> A029_09 | L5: A029_09 Transfer to lifetime ECL ToM should be total 0 | O5: 10931 | P5: Loss allow.stage2 -Am.Cost CDO/CLO | R5: 603 | S5: Transfer to lifetime ECL(S2) | V5: + | X5: >= | Y5: -5 | Z5: <= | AA5: 5 | AG5: e | AH5: e
A6: Changed | B6: ACTIVE | C6: Equity Securities - Common Stock | E6: A079_00 | F6: =VLOOKUP(E6,Sheet2!$A:$A,1,FALSE) -> A079_00 | L6: A079_00 No pos. or neg. Diff. FV - to FVPL Equity sec. | O6: 12311 | P6: FVPL Comm.stocks-Publ.util.(SLST FV,LCM) | R6: 880 | S6: Inc m. val.chg in ex lifeFVOCI-bk. to eq | V6: + | X6: >= | Y6: -5 | Z6: <= | AA6: 5 | AD6: FS Item, ToM | AG6: e | AH6: e | AS6: e | CO6: w | CP6: w
A7: Changed | B7: ACTIVE | C7: Equity Securities - Common Stock | E7: A079_00 | F7: =VLOOKUP(E7,Sheet2!$A:$A,1,FALSE) -> A079_00 | L7: A079_00 No pos. or neg. Diff. FV - to FVPL Equity sec. | O7: 12311 | P7: FVPL Comm.stocks-Publ.util.(SLST FV,LCM) | R7: 882 | S7: Decr m. val/chg in exp life FVOCI bk t q | V7: + | X7: >= | Y7: -5 | Z7: <= | AA7: 5 | AD7: FS Item, ToM | AG7: e | AH7: e | AS7: e | CO7: w | CP7: w
A8: Changed | B8: ACTIVE | C8: Equity Securities - Common Stock | E8: A079_00 | F8: =VLOOKUP(E8,Sheet2!$A:$A,1,FALSE) -> A079_00 | L8: A079_00 No pos. or neg. Diff. FV - to FVPL Equity sec. | O8: 12321 | P8: FVPL Comm.st.-Banks,Ins&oth(SLST FV,LCM) | R8: 880 | S8: Inc m. val.chg in ex lifeFVOCI-bk. to eq | V8: + | X8: >= | Y8: -5 | Z8: <= | AA8: 5 | AD8: FS Item, ToM | AG8: e | AH8: e | AS8: e | CO8: w | CP8: w
A9: Changed | B9: ACTIVE | C9: Equity Securities - Common Stock | E9: A079_00 | F9: =VLOOKUP(E9,Sheet2!$A:$A,1,FALSE) -> A079_00 | L9: A079_00 No pos. or neg. Diff. FV - to FVPL Equity sec. | O9: 12321 | P9: FVPL Comm.st.-Banks,Ins&oth(SLST FV,LCM) | R9: 882 | S9: Decr m. val/chg in exp life FVOCI bk t q | V9: + | X9: >= | Y9: -5 | Z9: <= | AA9: 5 | AD9: FS Item, ToM | AG9: e | AH9: e | AS9: e | CO9: w | CP9: w
A10: Changed | B10: ACTIVE | C10: Equity Securities - Common Stock | E10: A079_00 | F10: =VLOOKUP(E10,Sheet2!$A:$A,1,FALSE) -> A079_00 | L10: A079_00 No pos. or neg. Diff. FV - to FVPL Equity sec. | O10: 12341 | P10: FVPL Com.stocks-ZIG(own shares,SLST FV) | R10: 880 | S10: Inc m. val.chg in ex lifeFVOCI-bk. to eq | V10: + | X10: >= | Y10: -5 | Z10: <= | AA10: 5 | AD10: FS Item, ToM | AG10: e | AH10: e | AS10: e | CO10: w | CP10: w
A11: Changed | B11: ACTIVE | C11: Equity Securities - Common Stock | E11: A079_00 | F11: =VLOOKUP(E11,Sheet2!$A:$A,1,FALSE) -> A079_00 | L11: A079_00 No pos. or neg. Diff. FV - to FVPL Equity sec. | O11: 12341 | P11: FVPL Com.stocks-ZIG(own shares,SLST FV) | R11: 882 | S11: Decr m. val/chg in exp life FVOCI bk t q | V11: + | X11: >= | Y11: -5 | Z11: <= | AA11: 5 | AD11: FS Item, ToM | AG11: e | AH11: e | AS11: e | CO11: w | CP11: w
A12: Changed | B12: ACTIVE | C12: Equity Securities - Common Stock | E12: A079_00 | F12: =VLOOKUP(E12,Sheet2!$A:$A,1,FALSE) -> A079_00 | L12: A079_00 No pos. or neg. Diff. FV - to FVPL Equity sec. | O12: 12361 | P12: FVPL Comm.st.-Industr&Misc(SLST FV,LCM) | R12: 880 | S12: Inc m. val.chg in ex lifeFVOCI-bk. to eq | V12: + | X12: >= | Y12: -5 | Z12: <= | AA12: 5 | AD12: FS Item, ToM | AG12: e | AH12: e | AS12: e | CO12: w | CP12: w
A13: Changed | B13: ACTIVE | C13: Equity Securities - Common Stock | E13: A079_00 | F13: =VLOOKUP(E13,Sheet2!$A:$A,1,FALSE) -> A079_00 | L13: A079_00 No pos. or neg. Diff. FV - to FVPL Equity sec. | O13: 12361 | P13: FVPL Comm.st.-Industr&Misc(SLST FV,LCM) | R13: 882 | S13: Decr m. val/chg in exp life FVOCI bk t q | V13: + | X13: >= | Y13: -5 | Z13: <= | AA13: 5 | AD13: FS Item, ToM | AG13: e | AH13: e | AS13: e | CO13: w | CP13: w
A14: Changed | B14: ACTIVE | C14: Equity Securities - Common Stock | E14: A079_00 | F14: =VLOOKUP(E14,Sheet2!$A:$A,1,FALSE) -> A079_00 | L14: A079_00 No pos. or neg. Diff. FV - to FVPL Equity sec. | O14: 12366 | P14: UL Common Stocks FVPL (SLST FV) | R14: 880 | S14: Inc m. val.chg in ex lifeFVOCI-bk. to eq | V14: + | X14: >= | Y14: -5 | Z14: <= | AA14: 5 | AD14: FS Item, ToM | AG14: e | AH14: e | AS14: e | CO14: w | CP14: w
A15: Changed | B15: ACTIVE | C15: Equity Securities - Common Stock | E15: A079_00 | F15: =VLOOKUP(E15,Sheet2!$A:$A,1,FALSE) -> A079_00 | L15: A079_00 No pos. or neg. Diff. FV - to FVPL Equity sec. | O15: 12366 | P15: UL Common Stocks FVPL (SLST FV) | R15: 882 | S15: Decr m. val/chg in exp life FVOCI bk t q | V15: + | X15: >= | Y15: -5 | Z15: <= | AA15: 5 | AD15: FS Item, ToM | AG15: e | AH15: e | AS15: e | CO15: w | CP15: w
A16: Changed | B16: ACTIVE | C16: Equity Securities - Common Stock | E16: A079_00 | F16: =VLOOKUP(E16,Sheet2!$A:$A,1,FALSE) -> A079_00 | L16: A079_00 No pos. or neg. Diff. FV - to FVPL Equity sec. | O16: 12371 | P16: FVPL Unlisted stocks (SLST LoCoM) | R16: 882 | S16: Decr m. val/chg in exp life FVOCI bk t q | V16: + | X16: >= | Y16: -5 | Z16: <= | AA16: 5 | AD16: FS Item, ToM | AG16: e | AH16: e | AS16: e | CO16: w | CP16: w
A17: Changed | B17: ACTIVE | C17: Equity Securities - Common Stock | E17: A079_00 | F17: =VLOOKUP(E17,Sheet2!$A:$A,1,FALSE) -> A079_00 | L17: A079_00 No pos. or neg. Diff. FV - to FVPL Equity sec. | O17: 12371 | P17: FVPL Unlisted stocks (SLST LoCoM) | R17: 880 | S17: Inc m. val.chg in ex lifeFVOCI-bk. to eq | V17: + | X17: >= | Y17: -5 | Z17: <= | AA17: 5 | AD17: FS Item, ToM | AG17: e | AH17: e | AS17: e | CO17: w | CP17: w
... A67: Changed | B67: ACTIVE | C67: Equity Securities - Open-end investment funds | E67: A091_00 | F67: =VLOOKUP(E67,Sheet2!$A:$A,1,FALSE) -> A091_00 | L67: A091_00 No neg Diff. FV on EQ for FVPL Open-end inv. funds | O67: 14386 | P67: UL OE inv.funds-Mixed-FVPL(SLST FV) | R67: 882 | S67: Decr m. val/chg in exp life FVOCI bk t q | V67: + | X67: >= | Y67: -5 | Z67: <= | AA67: 5 | AD67: FS Item | AG67: e | AH67: e | AS67: e | CO67: w | CP67: w
B68: ACTIVE | C68: Debt Securities - Amortized cost | E68: A102_00 | F68: =VLOOKUP(E68,Sheet2!$A:$A,1,FALSE) -> A102_00 | L68: A102_00 Transfers betw Investm. Classes - Amortized Cost - 3rd part | O68: 10151 | P68: Amortized Cost Bonds-Swiss Gov(SLST AC) | R68: 272 | S68: Transfers between types of instrum -Ded | V68: + | X68: >= | Y68: -5 | Z68: <= | AA68: 5 | AG68: e | AH68: e | AS68: e | CO68: w | CP68: w
B69: ACTIVE | C69: Debt Securities - Amortized cost | E69: A102_00 | F69: =VLOOKUP(E69,Sheet2!$A:$A,1,FALSE) -> A102_00 | L69: A102_00 Transfers betw Investm. Classes - Amortized Cost - 3rd part | O69: 10151 | P69: Amortized Cost Bonds-Swiss Gov(SLST AC) | R69: 270 | S69: Transfers between types of instrum - Add | V69: + | X69: >= | Y69: -5 | Z69: <= | AA69: 5 | AG69: e | AH69: e | AS69: e | CO69: w | CP69: w
B70: ACTIVE | C70: Debt Securities - Amortized cost | E70: A102_00 | F70: =VLOOKUP(E70,Sheet2!$A:$A,1,FALSE) -> A102_00 | L70: A102_00 Transfers betw Investm. Classes - Amortized Cost - 3rd part | O70: 10161 | P70: Amortized Cost Bonds-U.S. Gov(SLST AC) | R70: 270 | S70: Transfers between types of instrum - Add | V70: + | X70: >= | Y70: -5 | Z70: <= | AA70: 5 | AG70: e | AH70: e | AS70: e | CO70: w | CP70: w
B71: ACTIVE | C71: Debt Securities - Amortized cost | E71: A102_00 | F71: =VLOOKUP(E71,Sheet2!$A:$A,1,FALSE) -> A102_00 | L71: A102_00 Transfers betw Investm. Classes - Amortized Cost - 3rd part | O71: 10161 | P71: Amortized Cost Bonds-U.S. Gov(SLST AC) | R71: 272 | S71: Transfers between types of instrum -Ded | V71: + | X71: >= | Y71: -5 | Z71: <= | AA71: 5 | AG71: e | AH71: e | AS71: e | CO71: w | CP71: w
B72: ACTIVE | C72: Debt Securities - Amortized cost | E72: A102_00 | F72: =VLOOKUP(E72,Sheet2!$A:$A,1,FALSE) -> A102_00 | L72: A102_00 Transfers betw Investm. Classes - Amortized Cost - 3rd part | O72: 10171 | P72: Amortized Cost Bonds-Other Govs(SLST AC) | R72: 270 | S72: Transfers between types of instrum - Add | V72: + | X72: >= | Y72: -5 | Z72: <= | AA72: 5 | AG72: e | AH72: e | AS72: e | CO72: w | CP72: w
B73: ACTIVE | C73: Debt Securities - Amortized cost | E73: A102_00 | F73: =VLOOKUP(E73,Sheet2!$A:$A,1,FALSE) -> A102_00 | L73: A102_00 Transfers betw Investm. Classes - Amortized Cost - 3rd part | O73: 10171 | P73: Amortized Cost Bonds-Other Govs(SLST AC) | R73: 272 | S73: Transfers between types of instrum -Ded | V73: + | X73: >= | Y73: -5 | Z73: <= | AA73: 5 | AG73: e | AH73: e | AS73: e | CO73: w | CP73: w
B74: ACTIVE | C74: Debt Securities - Amortized cost | E74: A102_00 | F74: =VLOOKUP(E74,Sheet2!$A:$A,1,FALSE) -> A102_00 | L74: A102_00 Transfers betw Investm. Classes - Amortized Cost - 3rd part | O74: 10181 | P74: Amortized Cost Bonds-U.K. Gov(SLST AC) | R74: 270 | S74: Transfers between types of instrum - Add | V74: + | X74: >= | Y74: -5 | Z74: <= | AA74: 5 | AG74: e | AH74: e | AS74: e | CO74: w | CP74: w
B75: ACTIVE | C75: Debt Securities - Amortized cost | E75: A102_00 | F75: =VLOOKUP(E75,Sheet2!$A:$A,1,FALSE) -> A102_00 | L75: A102_00 Transfers betw Investm. Classes - Amortized Cost - 3rd part | O75: 10181 | P75: Amortized Cost Bonds-U.K. Gov(SLST AC) | R75: 272 | S75: Transfers between types of instrum -Ded | V75: + | X75: >= | Y75: -5 | Z75: <= | AA75: 5 | AG75: e | AH75: e | AS75: e | CO75: w | CP75: w
B76: ACTIVE | C76: Debt Securities - Amortized cost | E76: A102_00 | F76: =VLOOKUP(E76,Sheet2!$A:$A,1,FALSE) -> A102_00 | L76: A102_00 Transfers betw Investm. Classes - Amortized Cost - 3rd part | O76: 10191 | P76: Amort.Cost Bonds-Public Utilit.(SLST AC) | R76: 272 | S76: Transfers between types of instrum -Ded | V76: + | X76: >= | Y76: -5 | Z76: <= | AA76: 5 | AG76: e | AH76: e | AS76: e | CO76: w | CP76: w
B77: ACTIVE | C77: Debt Securities - Amortized cost | E77: A102_00 | F77: =VLOOKUP(E77,Sheet2!$A:$A,1,FALSE) -> A102_00 | L77: A102_00 Transfers betw Investm. Classes - Amortized Cost - 3rd part | O77: 10191 | P77: Amort.Cost Bonds-Public Utilit.(SLST AC) | R77: 270 | S77: Transfers between types of instrum - Add | V77: + | X77: >= | Y77: -5 | Z77: <= | AA77: 5 | AG77: e | AH77: e | AS77: e | CO77: w | CP77: w
B78: ACTIVE | C78: Debt Securities - Amortized cost | E78: A102_00 | F78: =VLOOKUP(E78,Sheet2!$A:$A,1,FALSE) -> A102_00 | L78: A102_00 Transfers betw Investm. Classes - Amortized Cost - 3rd part | O78: 10221 | P78: Amortized Cost Bonds-Corporates(SLST AC) | R78: 270 | S78: Transfers between types of instrum - Add | V78: + | X78: >= | Y78: -5 | Z78: <= | AA78: 5 | AG78: e | AH78: e | AS78: e | CO78: w | CP78: w
B79: ACTIVE | C79: Debt Securities - Amortized cost | E79: A102_00 | F79: =VLOOKUP(E79,Sheet2!$A:$A,1,FALSE) -> A102_00 | L79: A102_00 Transfers betw Investm. Classes - Amortized Cost - 3rd part | O79: 10221 | P79: Amortized Cost Bonds-Corporates(SLST AC) | R79: 272 | S79: Transfers between types of instrum -Ded | V79: + | X79: >= | Y79: -5 | Z79: <= | AA79: 5 | AG79: e | AH79: e | AS79: e | CO79: w | CP79: w
... B85: ACTIVE | C85: Debt Securities - Amortized cost | E85: A102_00 | F85: =VLOOKUP(E85,Sheet2!$A:$A,1,FALSE) -> A102_00 | L85: A102_00 Transfers betw Investm. Classes - Amortized Cost - 3rd part | O85: 10461 | P85: Amort.Cost Bonds-Private Debt(SLST AC) | R85: 270 | S85: Transfers between types of instrum - Add | V85: + | X85: >= | Y85: -5 | Z85: <= | AA85: 5 | AG85: e | AH85: e | AS85: e | CO85: w | CP85: w
B86: ACTIVE | C86: FVPL debts | D86: yes | E86: A114_00 | F86: =VLOOKUP(E86,Sheet2!$A:$A,1,FALSE) -> A114_00 | L86: A114_00 Transfers betw Investm. Classes-FVPL-3rd part | O86: 10251 | P86: FVPL Bonds-Swiss Gov FV Option(SLST AC) | R86: 270 | S86: Transfers between types of instrum - Add | V86: + | X86: >= | Y86: -5 | Z86: <= | AA86: 5 | AG86: w | AH86: w | AS86: w | CO86: w | CP86: w
B87: ACTIVE | C87: FVPL debts | D87: yes | E87: A114_00 | F87: =VLOOKUP(E87,Sheet2!$A:$A,1,FALSE) -> A114_00 | L87: A114_00 Transfers betw Investm. Classes-FVPL-3rd part | O87: 10251 | P87: FVPL Bonds-Swiss Gov FV Option(SLST AC) | R87: 272 | S87: Transfers between types of instrum -Ded | V87: + | X87: >= | Y87: -5 | Z87: <= | AA87: 5 | AG87: w | AH87: w | AS87: w | CO87: w | CP87: w
B88: ACTIVE | C88: FVPL debts | D88: yes | E88: A114_00 | F88: =VLOOKUP(E88,Sheet2!$A:$A,1,FALSE) -> A114_00 | L88: A114_00 Transfers betw Investm. Classes-FVPL-3rd part | O88: 10261 | P88: FVPL Bonds-U.S. Gov FV Option(SLST AC) | R88: 272 | S88: Transfers between types of instrum -Ded | V88: + | X88: >= | Y88: -5 | Z88: <= | AA88: 5 | AG88: w | AH88: w | AS88: w | CO88: w | CP88: w
B89: ACTIVE | C89: FVPL debts | D89: yes | E89: A114_00 | F89: =VLOOKUP(E89,Sheet2!$A:$A,1,FALSE) -> A114_00 | L89: A114_00 Transfers betw Investm. Classes-FVPL-3rd part | O89: 10261 | P89: FVPL Bonds-U.S. Gov FV Option(SLST AC) | R89: 270 | S89: Transfers between types of instrum - Add | V89: + | X89: >= | Y89: -5 | Z89: <= | AA89: 5 | AG89: w | AH89: w | AS89: w | CO89: w | CP89: w
B90: ACTIVE | C90: FVPL debts | D90: yes | E90: A114_00 | F90: =VLOOKUP(E90,Sheet2!$A:$A,1,FALSE) -> A114_00 | L90: A114_00 Transfers betw Investm. Classes-FVPL-3rd part | O90: 10271 | P90: FVPL Bonds-Other Gov. FV Option(SLST AC) | R90: 272 | S90: Transfers between types of instrum -Ded | V90: + | X90: >= | Y90: -5 | Z90: <= | AA90: 5 | AG90: w | AH90: w | AS90: w | CO90: w | CP90: w
B91: ACTIVE | C91: FVPL debts | D91: yes | E91: A114_00 | F91: =VLOOKUP(E91,Sheet2!$A:$A,1,FALSE) -> A114_00 | L91: A114_00 Transfers betw Investm. Classes-FVPL-3rd part | O91: 10271 | P91: FVPL Bonds-Other Gov. FV Option(SLST AC) | R91: 270 | S91: Transfers between types of instrum - Add | V91: + | X91: >= | Y91: -5 | Z91: <= | AA91: 5 | AG91: w | AH91: w | AS91: w | CO91: w | CP91: w
B92: ACTIVE | C92: FVPL debts | D92: yes | E92: A114_00 | F92: =VLOOKUP(E92,Sheet2!$A:$A,1,FALSE) -> A114_00 | L92: A114_00 Transfers betw Investm. Classes-FVPL-3rd part | O92: 10281 | P92: FVPL Bonds-U.K. Gov FV Option(SLST AC) | R92: 272 | S92: Transfers between types of instrum -Ded | V92: + | X92: >= | Y92: -5 | Z92: <= | AA92: 5 | AG92: w | AH92: w | AS92: w | CO92: w | CP92: w
B93: ACTIVE | C93: FVPL debts | D93: yes | E93: A114_00 | F93: =VLOOKUP(E93,Sheet2!$A:$A,1,FALSE) -> A114_00 | L93: A114_00 Transfers betw Investm. Classes-FVPL-3rd part | O93: 10281 | P93: FVPL Bonds-U.K. Gov FV Option(SLST AC) | R93: 270 | S93: Transfers between types of instrum - Add | V93: + | X93: >= | Y93: -5 | Z93: <= | AA93: 5 | AG93: w | AH93: w | AS93: w | CO93: w | CP93: w
B94: ACTIVE | C94: FVPL debts | D94: yes | E94: A114_00 | F94: =VLOOKUP(E94,Sheet2!$A:$A,1,FALSE) -> A114_00 | L94: A114_00 Transfers betw Investm. Classes-FVPL-3rd part | O94: 10291 | P94: FVPL Bonds-Public Utilit FV Opt(SLST AC) | R94: 270 | S94: Transfers between types of instrum - Add | V94: + | X94: >= | Y94: -5 | Z94: <= | AA94: 5 | AG94: w | AH94: w | AS94: w | CO94: w | CP94: w
B95: ACTIVE | C95: FVPL debts | D95: yes | E95: A114_00 | F95: =VLOOKUP(E95,Sheet2!$A:$A,1,FALSE) -> A114_00 | L95: A114_00 Transfers betw Investm. Classes-FVPL-3rd part | O95: 10291 | P95: FVPL Bonds-Public Utilit FV Opt(SLST AC) | R95: 272 | S95: Transfers between types of instrum -Ded | V95: + | X95: >= | Y95: -5 | Z95: <= | AA95: 5 | AG95: w | AH95: w | AS95: w | CO95: w | CP95: w
B96: ACTIVE | C96: FVPL debts | D96: yes | E96: A114_00 | F96: =VLOOKUP(E96,Sheet2!$A:$A,1,FALSE) -> A114_00 | L96: A114_00 Transfers betw Investm. Classes-FVPL-3rd part | O96: 10311 | P96: FVPL Convertibles (SLST AC) | R96: 272 | S96: Transfers between types of instrum -Ded | V96: + | X96: >= | Y96: -5 | Z96: <= | AA96: 5 | AG96: w | AH96: w | AS96: w | CO96: w | CP96: w
B97: ACTIVE | C97: FVPL debts | D97: yes | E97: A114_00 | F97: =VLOOKUP(E97,Sheet2!$A:$A,1,FALSE) -> A114_00 | L97: A114_00 Transfers betw Investm. Classes-FVPL-3rd part | O97: 10311 | P97: FVPL Convertibles (SLST AC) | R97: 270 | S97: Transfers between types of instrum - Add | V97: + | X97: >= | Y97: -5 | Z97: <= | AA97: 5 | AG97: w | AH97: w | AS97: w | CO97: w | CP97: w
... B125: ACTIVE | C125: FVPL debts | D125: yes | E125: A114_00 | F125: =VLOOKUP(E125,Sheet2!$A:$A,1,FALSE) -> A114_00 | L125: A114_00 Transfers betw Investm. Classes-FVPL-3rd part | O125: 10611 | P125: FVPL Hybrids with debt feat(SLST AC) | R125: 270 | S125: Transfers between types of instrum - Add | V125: + | X125: >= | Y125: -5 | Z125: <= | AA125: 5 | AG125: w | AH125: w | AS125: w | CO125: w | CP125: w
A126: New xcheck or association | B126: ACTIVE | C126: FVPL debts | D126: yes | E126: A114_00 | F126: =VLOOKUP(E126,Sheet2!$A:$A,1,FALSE) -> A114_00 | L126: A114_00 Transfers betw Investm. Classes-FVPL-3rd part | O126: 10771 | P126: FVPL Hybr.with debt feat.FV opt(SLST AC) | R126: 272 | S126: Transfers between types of instrum -Ded | V126: + | X126: >= | Y126: -5 | Z126: <= | AA126: 5 | AG126: w | AH126: w | AS126: w | CO126: w | CP126: w
A127: New xcheck or association | B127: ACTIVE | C127: FVPL debts | D127: yes | E127: A114_00 | F127: =VLOOKUP(E127,Sheet2!$A:$A,1,FALSE) -> A114_00 | L127: A114_00 Transfers betw Investm. Classes-FVPL-3rd part | O127: 10771 | P127: FVPL Hybr.with debt feat.FV opt(SLST AC) | R127: 270 | S127: Transfers between types of instrum - Add | V127: + | X127: >= | Y127: -5 | Z127: <= | AA127: 5 | AG127: w | AH127: w | AS127: w | CO127: w | CP127: w
B128: ACTIVE | C128: FVPL debts | D128: yes | E128: A114_00 | F128: =VLOOKUP(E128,Sheet2!$A:$A,1,FALSE) -> A114_00 | L128: A114_00 Transfers betw Investm. Classes-FVPL-3rd part | O128: 24481 | P128: Fin.liab.for non-deriv.fix-to-fix swaps | R128: 270 | S128: Transfers between types of instrum - Add | V128: + | X128: >= | Y128: -5 | Z128: <= | AA128: 5 | AG128: w | AH128: w | AS128: w | CO128: w | CP128: w
B129: ACTIVE | C129: FVPL debts | D129: yes | E129: A114_00 | F129: =VLOOKUP(E129,Sheet2!$A:$A,1,FALSE) -> A114_00 | L129: A114_00 Transfers betw Investm. Classes-FVPL-3rd part | O129: 24481 | P129: Fin.liab.for non-deriv.fix-to-fix swaps | R129: 272 | S129: Transfers between types of instrum -Ded | V129: + | X129: >= | Y129: -5 | Z129: <= | AA129: 5 | AG129: w | AH129: w | AS129: w | CO129: w | CP129: w
A130: Changed | B130: ACTIVE | C130: Real Estate held for Investment | E130: A137_00 | F130: =VLOOKUP(E130,Sheet2!$A:$A,1,FALSE) -> A137_00 | L130: A137_00 No FV adjustm to Equity f Inv property: Buildings | O130: 13901 | P130: Buildings Held for Investment at FV | R130: 882 | S130: Decr m. val/chg in exp life FVOCI bk t q | V130: + | X130: >= | Y130: -5 | Z130: <= | AA130: 5 | AD130: FS Item, ToM | AG130: e | AH130: e | AS130: e | CO130: w | CP130: w
A131: Changed | B131: ACTIVE | C131: Real Estate held for Investment | E131: A137_00 | F131: =VLOOKUP(E131,Sheet2!$A:$A,1,FALSE) -> A137_00 | L131: A137_00 No FV adjustm to Equity f Inv property: Buildings | O131: 13906 | P131: UL Buildings Held for Inv. at FV | R131: 882 | S131: Decr m. val/chg in exp life FVOCI bk t q | V131: + | X131: >= | Y131: -5 | Z131: <= | AA131: 5 | AD131: FS Item, ToM | AG131: e | AH131: e | AS131: e | CO131: w | CP131: w
A132: Changed | B132: ACTIVE | C132: Fixed Assets | E132: A147_00 | F132: =VLOOKUP(E132,Sheet2!$A:$A,1,FALSE) -> A147_00 | L132: A147_00 Depreciation on own use non-IT Equipment | O132: 18708 | P132: Furniture&Fixtures Owned- Acc. Depr/Imp | R132: 402 | S132: Write-Offs (Regular Amortization/Deprec) | V132: + | X132: >= | Y132: -5 | Z132: <= | AA132: 5 | AE132: X | AG132: e | AH132: e | AS132: w | CO132: w | CP132: w
A133: Changed | B133: ACTIVE | C133: Fixed Assets | E133: A147_00 | F133: =VLOOKUP(E133,Sheet2!$A:$A,1,FALSE) -> A147_00 | L133: A147_00 Depreciation on own use non-IT Equipment | O133: 19008 | P133: Other equipment - Acc. Dep/Imp | R133: 402 | S133: Write-Offs (Regular Amortization/Deprec) | V133: + | X133: >= | Y133: -5 | Z133: <= | AA133: 5 | AE133: X | AG133: e | AH133: e | AS133: w | CO133: w | CP133: w
A134: Changed | B134: ACTIVE | C134: Fixed Assets | E134: A147_00 | F134: =VLOOKUP(E134,Sheet2!$A:$A,1,FALSE) -> A147_00 | L134: A147_00 Depreciation on own use non-IT Equipment | O134: 19028 | P134: Leaseh.Improv.(excl Inv. Prop.)-acc depr | R134: 402 | S134: Write-Offs (Regular Amortization/Deprec) | V134: + | X134: >= | Y134: -5 | Z134: <= | AA134: 5 | AE134: X | AG134: e | AH134: e | AS134: w | CO134: w | CP134: w
A135: Changed | B135: ACTIVE | C135: Fixed Assets | E135: A147_00 | F135: =VLOOKUP(E135,Sheet2!$A:$A,1,FALSE) -> A147_00 | L135: A147_00 Depreciation on own use non-IT Equipment | O135: 48451 | P135: Depreciation of non-IT equipment | V135: + | X135: >= | Y135: -5 | Z135: <= | AA135: 5 | AE135: X | AG135: e | AH135: e | AS135: w | CO135: w | CP135: w
A136: Changed | B136: ACTIVE | C136: Equity Securities - Non-redeemable Pref. Shares | E136: A152_00 | F136: =VLOOKUP(E136,Sheet2!$A:$A,1,FALSE) -> A152_00 | L136: A152_00 No pos Diff FV-to Equ.-Nred Pref.Stocks FVPL | O136: 12506 | P136: UL Nonred.Pref.Stocks-FVPL (SLST FV) | R136: 880 | S136: Inc m. val.chg in ex lifeFVOCI-bk. to eq | V136: + | X136: >= | Y136: -5 | Z136: <= | AA136: 5 | AD136: FS Item, ToM | AG136: e | AH136: e | AS136: e | CO136: w | CP136: w
A137: Changed | B137: ACTIVE | C137: Equity Securities - Non-redeemable Pref. Shares | E137: A152_00 | F137: =VLOOKUP(E137,Sheet2!$A:$A,1,FALSE) -> A152_00 | L137: A152_00 No pos Diff FV-to Equ.-Nred Pref.Stocks FVPL | O137: 12521 | P137: FVPL Non redeem Pref Shares(SLST FV,LCM) | R137: 880 | S137: Inc m. val.chg in ex lifeFVOCI-bk. to eq | V137: + | X137: >= | Y137: -5 | Z137: <= | AA137: 5 | AD137: FS Item, ToM | AG137: e | AH137: e | AS137: e | CO137: w | CP137: w
A138: Changed | B138: ACTIVE | C138: Equity Securities - Non-redeemable Pref. Shares | E138: A153_00 | F138: =VLOOKUP(E138,Sheet2!$A:$A,1,FALSE) -> A153_00 | L138: A153_00 No neg Diff FV-to Equ.-Nred Pref.Stocks FVPL | O138: 12506 | P138: UL Nonred.Pref.Stocks-FVPL (SLST FV) | R138: 882 | S138: Decr m. val/chg in exp life FVOCI bk t q | V138: + | X138: >= | Y138: -5 | Z138: <= | AA138: 5 | AD138: FS Item, ToM | AG138: e | AH138: e | AS138: e | CO138: w | CP138: w
A139: Changed | B139: ACTIVE | C139: Equity Securities - Non-redeemable Pref. Shares | E139: A153_00 | F139: =VLOOKUP(E139,Sheet2!$A:$A,1,FALSE) -> A153_00 | L139: A153_00 No neg Diff FV-to Equ.-Nred Pref.Stocks FVPL | O139: 12521 | P139: FVPL Non redeem Pref Shares(SLST FV,LCM) | R139: 882 | S139: Decr m. val/chg in exp life FVOCI bk t q | V139: + | X139: >= | Y139: -5 | Z139: <= | AA139: 5 | AD139: FS Item, ToM | AG139: e | AH139: e | AS139: e | CO139: w | CP139: w
B140: ACTIVE | C140: Derivatives | E140: A159_09 | F140: =VLOOKUP(E140,Sheet2!$A:$A,1,FALSE) -> A159_09 | L140: A159_09 No gains&losses to equity - Derivatives | O140: OAN_00277 | P140: Unit-Linked Derivatives | Q140: 2 - Affiliated | R140: 660 | S140: Transfer b/c of New Account (88A) | V140: + | X140: >= | Y140: -5 | Z140: <= | AA140: 5 | AD140: FS Item, ToM | AG140: e | AH140: e
B141: ACTIVE | C141: Derivatives | E141: A159_09 | F141: =VLOOKUP(E141,Sheet2!$A:$A,1,FALSE) -> A159_09 | L141: A159_09 No gains&losses to equity - Derivatives | O141: OAN_00277 | P141: Unit-Linked Derivatives | Q141: 2 - Affiliated | R141: 964 | S141: Corrections BB Negative difference (88C) | V141: + | X141: >= | Y141: -5 | Z141: <= | AA141: 5 | AD141: FS Item, ToM | AG141: e | AH141: e
B142: ACTIVE | C142: Derivatives | E142: A159_09 | F142: =VLOOKUP(E142,Sheet2!$A:$A,1,FALSE) -> A159_09 | L142: A159_09 No gains&losses to equity - Derivatives | O142: OAN_00277 | P142: Unit-Linked Derivatives | Q142: 2 - Affiliated | R142: 665 | S142: Transfer b/c of Internal Merger (88A) | V142: + | X142: >= | Y142: -5 | Z142: <= | AA142: 5 | AD142: FS Item, ToM | AG142: e | AH142: e
B143: ACTIVE | C143: Derivatives | E143: A159_09 | F143: =VLOOKUP(E143,Sheet2!$A:$A,1,FALSE) -> A159_09 | L143: A159_09 No gains&losses to equity - Derivatives | O143: OAN_00277 | P143: Unit-Linked Derivatives | Q143: 2 - Affiliated | R143: 963 | S143: Corrections BB Positive difference (88A) | V143: + | X143: >= | Y143: -5 | Z143: <= | AA143: 5 | AD143: FS Item, ToM | AG143: e | AH143: e
A144: Changed | B144: ACTIVE | C144: Derivatives | E144: A159_09 | F144: =VLOOKUP(E144,Sheet2!$A:$A,1,FALSE) -> A159_09 | L144: A159_09 No gains&losses to equity - Derivatives | O144: OAN_00277 | P144: Unit-Linked Derivatives | Q144: 2 - Affiliated | R144: 882 | S144: Decr m. val/chg in exp life FVOCI bk t q | V144: + | X144: >= | Y144: -5 | Z144: <= | AA144: 5 | AD144: FS Item, ToM | AG144: e | AH144: e
B145: ACTIVE | C145: Derivatives | E145: A159_09 | F145: =VLOOKUP(E145,Sheet2!$A:$A,1,FALSE) -> A159_09 | L145: A159_09 No gains&losses to equity - Derivatives | O145: OAN_00277 | P145: Unit-Linked Derivatives | Q145: 2 - Affiliated | R145: 675 | S145: Transfer b/c of Internal Merger (88C) | V145: + | X145: >= | Y145: -5 | Z145: <= | AA145: 5 | AD145: FS Item, ToM | AG145: e | AH145: e
A146: Changed | B146: ACTIVE | C146: Derivatives | E146: A159_09 | F146: =VLOOKUP(E146,Sheet2!$A:$A,1,FALSE) -> A159_09 | L146: A159_09 No gains&losses to equity - Derivatives | O146: OAN_00277 | P146: Unit-Linked Derivatives | Q146: 2 - Affiliated | R146: 880 | S146: Inc m. val.chg in ex lifeFVOCI-bk. to eq | V146: + | X146: >= | Y146: -5 | Z146: <= | AA146: 5 | AD146: FS Item, ToM | AG146: e | AH146: e
B147: ACTIVE | C147: Derivatives | E147: A159_09 | F147: =VLOOKUP(E147,Sheet2!$A:$A,1,FALSE) -> A159_09 | L147: A159_09 No gains&losses to equity - Derivatives | O147: OAN_00277 | P147: Unit-Linked Derivatives | Q147: 2 - Affiliated | R147: 670 | S147: Transfer b/c of New Account (88C) | V147: + | X147: >= | Y147: -5 | Z147: <= | AA147: 5 | AD147: FS Item, ToM | AG147: e | AH147: e
A148: Changed | B148: ACTIVE | C148: Derivatives | E148: A159_09 | F148: =VLOOKUP(E148,Sheet2!$A:$A,1,FALSE) -> A159_09 | L148: A159_09 No gains&losses to equity - Derivatives | O148: SN_12865 | P148: Interest Risk Derivatives - Trading | Q148: 2 - Affiliated | R148: 882 | S148: Decr m. val/chg in exp life FVOCI bk t q | V148: + | X148: >= | Y148: -5 | Z148: <= | AA148: 5 | AD148: FS Item, ToM | AG148: e | AH148: e
B149: ACTIVE | C149: Derivatives | E149: A159_09 | F149: =VLOOKUP(E149,Sheet2!$A:$A,1,FALSE) -> A159_09 | L149: A159_09 No gains&losses to equity - Derivatives | O149: SN_12865 | P149: Interest Risk Derivatives - Trading | Q149: 2 - Affiliated | R149: 964 | S149: Corrections BB Negative difference (88C) | V149: + | X149: >= | Y149: -5 | Z149: <= | AA149: 5 | AD149: FS Item, ToM | AG149: e | AH149: e
B150: ACTIVE | C150: Derivatives | E150: A159_09 | F150: =VLOOKUP(E150,Sheet2!$A:$A,1,FALSE) -> A159_09 | L150: A159_09 No gains&losses to equity - Derivatives | O150: SN_12865 | P150: Interest Risk Derivatives - Trading | Q150: 2 - Affiliated | R150: 670 | S150: Transfer b/c of New Account (88C) | V150: + | X150: >= | Y150: -5 | Z150: <= | AA150: 5 | AD150: FS Item, ToM | AG150: e | AH150: e
B151: ACTIVE | C151: Derivatives | E151: A159_09 | F151: =VLOOKUP(E151,Sheet2!$A:$A,1,FALSE) -> A159_09 | L151: A159_09 No gains&losses to equity - Derivatives | O151: SN_12865 | P151: Interest Risk Derivatives - Trading | Q151: 2 - Affiliated | R151: 660 | S151: Transfer b/c of New Account (88A) | V151: + | X151: >= | Y151: -5 | Z151: <= | AA151: 5 | AD151: FS Item, ToM | AG151: e | AH151: e
B152: ACTIVE | C152: Derivatives | E152: A159_09 | F152: =VLOOKUP(E152,Sheet2!$A:$A,1,FALSE) -> A159_09 | L152: A159_09 No gains&losses to equity - Derivatives | O152: SN_12865 | P152: Interest Risk Derivatives - Trading | Q152: 2 - Affiliated | R152: 665 | S152: Transfer b/c of Internal Merger (88A) | V152: + | X152: >= | Y152: -5 | Z152: <= | AA152: 5 | AD152: FS Item, ToM | AG152: e | AH152: e
B153: ACTIVE | C153: Derivatives | E153: A159_09 | F153: =VLOOKUP(E153,Sheet2!$A:$A,1,FALSE) -> A159_09 | L153: A159_09 No gains&losses to equity - Derivatives | O153: SN_12865 | P153: Interest Risk Derivatives - Trading | Q153: 2 - Affiliated | R153: 963 | S153: Corrections BB Positive difference (88A) | V153: + | X153: >= | Y153: -5 | Z153: <= | AA153: 5 | AD153: FS Item, ToM | AG153: e | AH153: e
A154: Changed | B154: ACTIVE | C154: Derivatives | E154: A159_09 | F154: =VLOOKUP(E154,Sheet2!$A:$A,1,FALSE) -> A159_09 | L154: A159_09 No gains&losses to equity - Derivatives | O154: SN_12865 | P154: Interest Risk Derivatives - Trading | Q154: 2 - Affiliated | R154: 880 | S154: Inc m. val.chg in ex lifeFVOCI-bk. to eq | V154: + | X154: >= | Y154: -5 | Z154: <= | AA154: 5 | AD154: FS Item, ToM | AG154: e | AH154: e
B155: ACTIVE | C155: Derivatives | E155: A159_09 | F155: =VLOOKUP(E155,Sheet2!$A:$A,1,FALSE) -> A159_09 | L155: A159_09 No gains&losses to equity - Derivatives | O155: SN_12865 | P155: Interest Risk Derivatives - Trading | Q155: 2 - Affiliated | R155: 675 | S155: Transfer b/c of Internal Merger (88C) | V155: + | X155: >= | Y155: -5 | Z155: <= | AA155: 5 | AD155: FS Item, ToM | AG155: e | AH155: e
B156: ACTIVE | C156: Derivatives | E156: A159_09 | F156: =VLOOKUP(E156,Sheet2!$A:$A,1,FALSE) -> A159_09 | L156: A159_09 No gains&losses to equity - Derivatives | O156: SN_12880 | P156: Currency Risk Derivatives - Trading | Q156: 2 - Affiliated | R156: 670 | S156: Transfer b/c of New Account (88C) | V156: + | X156: >= | Y156: -5 | Z156: <= | AA156: 5 | AD156: FS Item, ToM | AG156: e | AH156: e
B157: ACTIVE | C157: Derivatives | E157: A159_09 | F157: =VLOOKUP(E157,Sheet2!$A:$A,1,FALSE) -> A159_09 | L157: A159_09 No gains&losses to equity - Derivatives | O157: SN_12880 | P157: Currency Risk Derivatives - Trading | Q157: 2 - Affiliated | R157: 675 | S157: Transfer b/c of Internal Merger (88C) | V157: + | X157: >= | Y157: -5 | Z157: <= | AA157: 5 | AD157: FS Item, ToM | AG157: e | AH157: e
A158: Changed | B158: ACTIVE | C158: Derivatives | E158: A159_09 | F158: =VLOOKUP(E158,Sheet2!$A:$A,1,FALSE) -> A159_09 | L158: A159_09 No gains&losses to equity - Derivatives | O158: SN_12880 | P158: Currency Risk Derivatives - Trading | Q158: 2 - Affiliated | R158: 882 | S158: Decr m. val/chg in exp life FVOCI bk t q | V158: + | X158: >= | Y158: -5 | Z158: <= | AA158: 5 | AD158: FS Item, ToM | AG158: e | AH158: e
B159: ACTIVE | C159: Derivatives | E159: A159_09 | F159: =VLOOKUP(E159,Sheet2!$A:$A,1,FALSE) -> A159_09 | L159: A159_09 No gains&losses to equity - Derivatives | O159: SN_12880 | P159: Currency Risk Derivatives - Trading | Q159: 2 - Affiliated | R159: 665 | S159: Transfer b/c of Internal Merger (88A) | V159: + | X159: >= | Y159: -5 | Z159: <= | AA159: 5 | AD159: FS Item, ToM | AG159: e | AH159: e
B160: ACTIVE | C160: Derivatives | E160: A159_09 | F160: =VLOOKUP(E160,Sheet2!$A:$A,1,FALSE) -> A159_09 | L160: A159_09 No gains&losses to equity - Derivatives | O160: SN_12880 | P160: Currency Risk Derivatives - Trading | Q160: 2 - Affiliated | R160: 963 | S160: Corrections BB Positive difference (88A) | V160: + | X160: >= | Y160: -5 | Z160: <= | AA160: 5 | AD160: FS Item, ToM | AG160: e | AH160: e
B161: ACTIVE | C161: Derivatives | E161: A159_09 | F161: =VLOOKUP(E161,Sheet2!$A:$A,1,FALSE) -> A159_09 | L161: A159_09 No gains&losses to equity - Derivatives | O161: SN_12880 | P161: Currency Risk Derivatives - Trading | Q161: 2 - Affiliated | R161: 964 | S161: Corrections BB Negative difference (88C) | V161: + | X161: >= | Y161: -5 | Z161: <= | AA161: 5 | AD161: FS Item, ToM | AG161: e | AH161: e
A162: Changed | B162: ACTIVE | C162: Derivatives | E162: A159_09 | F162: =VLOOKUP(E162,Sheet2!$A:$A,1,FALSE) -> A159_09 | L162: A159_09 No gains&losses to equity - Derivatives | O162: SN_12880 | P162: Currency Risk Derivatives - Trading | Q162: 2 - Affiliated | R162: 880 | S162: Inc m. val.chg in ex lifeFVOCI-bk. to eq | V162: + | X162: >= | Y162: -5 | Z162: <= | AA162: 5 | AD162: FS Item, ToM | AG162: e | AH162: e
B163: ACTIVE | C163: Derivatives | E163: A159_09 | F163: =VLOOKUP(E163,Sheet2!$A:$A,1,FALSE) -> A159_09 | L163: A159_09 No gains&losses to equity - Derivatives | O163: SN_12880 | P163: Currency Risk Derivatives - Trading | Q163: 2 - Affiliated | R163: 660 | S163: Transfer b/c of New Account (88A) | V163: + | X163: >= | Y163: -5 | Z163: <= | AA163: 5 | AD163: FS Item, ToM | AG163: e | AH163: e
B164: ACTIVE | C164: Derivatives | E164: A159_09 | F164: =VLOOKUP(E164,Sheet2!$A:$A,1,FALSE) -> A159_09 | L164: A159_09 No gains&losses to equity - Derivatives | O164: SN_12900 | P164: Eq Risk (Market Risk) Derivat. -Trading | Q164: 2 - Affiliated | R164: 670 | S164: Transfer b/c of New Account (88C) | V164: + | X164: >= | Y164: -5 | Z164: <= | AA164: 5 | AD164: FS Item, ToM | AG164: e | AH164: e
B165: ACTIVE | C165: Derivatives | E165: A159_09 | F165: =VLOOKUP(E165,Sheet2!$A:$A,1,FALSE) -> A159_09 | L165: A159_09 No gains&losses to equity - Derivatives | O165: SN_12900 | P165: Eq Risk (Market Risk) Derivat. -Trading | Q165: 2 - Affiliated | R165: 675 | S165: Transfer b/c of Internal Merger (88C) | V165: + | X165: >= | Y165: -5 | Z165: <= | AA165: 5 | AD165: FS Item, ToM | AG165: e | AH165: e
B166: ACTIVE | C166: Derivatives | E166: A159_09 | F166: =VLOOKUP(E166,Sheet2!$A:$A,1,FALSE) -> A159_09 | L166: A159_09 No gains&losses to equity - Derivatives | O166: SN_12900 | P166: Eq Risk (Market Risk) Derivat. -Trading | Q166: 2 - Affiliated | R166: 665 | S166: Transfer b/c of Internal Merger (88A) | V166: + | X166: >= | Y166: -5 | Z166: <= | AA166: 5 | AD166: FS Item, ToM | AG166: e | AH166: e
B167: ACTIVE | C167: Derivatives | E167: A159_09 | F167: =VLOOKUP(E167,Sheet2!$A:$A,1,FALSE) -> A159_09 | L167: A159_09 No gains&losses to equity - Derivatives | O167: SN_12900 | P167: Eq Risk (Market Risk) Derivat. -Trading | Q167: 2 - Affiliated | R167: 660 | S167: Transfer b/c of New Account (88A) | V167: + | X167: >= | Y167: -5 | Z167: <= | AA167: 5 | AD167: FS Item, ToM | AG167: e | AH167: e
A168: Changed | B168: ACTIVE | C168: Derivatives | E168: A159_09 | F168: =VLOOKUP(E168,Sheet2!$A:$A,1,FALSE) -> A159_09 | L168: A159_09 No gains&losses to equity - Derivatives | O168: SN_12900 | P168: Eq Risk (Market Risk) Derivat. -Trading | Q168: 2 - Affiliated | R168: 880 | S168: Inc m. val.chg in ex lifeFVOCI-bk. to eq | V168: + | X168: >= | Y168: -5 | Z168: <= | AA168: 5 | AD168: FS Item, ToM | AG168: e | AH168: e
B169: ACTIVE | C169: Derivatives | E169: A159_09 | F169: =VLOOKUP(E169,Sheet2!$A:$A,1,FALSE) -> A159_09 | L169: A159_09 No gains&losses to equity - Derivatives | O169: SN_12900 | P169: Eq Risk (Market Risk) Derivat. -Trading | Q169: 2 - Affiliated | R169: 963 | S169: Corrections BB Positive difference (88A) | V169: + | X169: >= | Y169: -5 | Z169: <= | AA169: 5 | AD169: FS Item, ToM | AG169: e | AH169: e
A170: Changed | B170: ACTIVE | C170: Derivatives | E170: A159_09 | F170: =VLOOKUP(E170,Sheet2!$A:$A,1,FALSE) -> A159_09 | L170: A159_09 No gains&losses to equity - Derivatives | O170: SN_12900 | P170: Eq Risk (Market Risk) Derivat. -Trading | Q170: 2 - Affiliated | R170: 882 | S170: Decr m. val/chg in exp life FVOCI bk t q | V170: + | X170: >= | Y170: -5 | Z170: <= | AA170: 5 | AD170: FS Item, ToM | AG170: e | AH170: e
B171: ACTIVE | C171: Derivatives | E171: A159_09 | F171: =VLOOKUP(E171,Sheet2!$A:$A,1,FALSE) -> A159_09 | L171: A159_09 No gains&losses to equity - Derivatives | O171: SN_12900 | P171: Eq Risk (Market Risk) Derivat. -Trading | Q171: 2 - Affiliated | R171: 964 | S171: Corrections BB Negative difference (88C) | V171: + | X171: >= | Y171: -5 | Z171: <= | AA171: 5 | AD171: FS Item, ToM | AG171: e | AH171: e
B172: ACTIVE | C172: Derivatives | E172: A159_09 | F172: =VLOOKUP(E172,Sheet2!$A:$A,1,FALSE) -> A159_09 | L172: A159_09 No gains&losses to equity - Derivatives | O172: SN_12905 | P172: Credit Risk Derivatives - Trading | Q172: 2 - Affiliated | R172: 670 | S172: Transfer b/c of New Account (88C) | V172: + | X172: >= | Y172: -5 | Z172: <= | AA172: 5 | AD172: FS Item, ToM | AG172: e | AH172: e
B173: ACTIVE | C173: Derivatives | E173: A159_09 | F173: =VLOOKUP(E173,Sheet2!$A:$A,1,FALSE) -> A159_09 | L173: A159_09 No gains&losses to equity - Derivatives | O173: SN_12905 | P173: Credit Risk Derivatives - Trading | Q173: 2 - Affiliated | R173: 660 | S173: Transfer b/c of New Account (88A) | V173: + | X173: >= | Y173: -5 | Z173: <= | AA173: 5 | AD173: FS Item, ToM | AG173: e | AH173: e
A174: Changed | B174: ACTIVE | C174: Derivatives | E174: A159_09 | F174: =VLOOKUP(E174,Sheet2!$A:$A,1,FALSE) -> A159_09 | L174: A159_09 No gains&losses to equity - Derivatives | O174: SN_12905 | P174: Credit Risk Derivatives - Trading | Q174: 2 - Affiliated | R174: 882 | S174: Decr m. val/chg in exp life FVOCI bk t q | V174: + | X174: >= | Y174: -5 | Z174: <= | AA174: 5 | AD174: FS Item, ToM | AG174: e | AH174: e
B175: ACTIVE | C175: Derivatives | E175: A159_09 | F175: =VLOOKUP(E175,Sheet2!$A:$A,1,FALSE) -> A159_09 | L175: A159_09 No gains&losses to equity - Derivatives | O175: SN_12905 | P175: Credit Risk Derivatives - Trading | Q175: 2 - Affiliated | R175: 963 | S175: Corrections BB Positive difference (88A) | V175: + | X175: >= | Y175: -5 | Z175: <= | AA175: 5 | AD175: FS Item, ToM | AG175: e | AH175: e
B176: ACTIVE | C176: Derivatives | E176: A159_09 | F176: =VLOOKUP(E176,Sheet2!$A:$A,1,FALSE) -> A159_09 | L176: A159_09 No gains&losses to equity - Derivatives | O176: SN_12905 | P176: Credit Risk Derivatives - Trading | Q176: 2 - Affiliated | R176: 964 | S176: Corrections BB Negative difference (88C) | V176: + | X176: >= | Y176: -5 | Z176: <= | AA176: 5 | AD176: FS Item, ToM | AG176: e | AH176: e
A177: Changed | B177: ACTIVE | C177: Derivatives | E177: A159_09 | F177: =VLOOKUP(E177,Sheet2!$A:$A,1,FALSE) -> A159_09 | L177: A159_09 No gains&losses to equity - Derivatives | O177: SN_12905 | P177: Credit Risk Derivatives - Trading | Q177: 2 - Affiliated | R177: 880 | S177: Inc m. val.chg in ex lifeFVOCI-bk. to eq | V177: + | X177: >= | Y177: -5 | Z177: <= | AA177: 5 | AD177: FS Item, ToM | AG177: e | AH177: e
B178: ACTIVE | C178: Derivatives | E178: A159_09 | F178: =VLOOKUP(E178,Sheet2!$A:$A,1,FALSE) -> A159_09 | L178: A159_09 No gains&losses to equity - Derivatives | O178: SN_12905 | P178: Credit Risk Derivatives - Trading | Q178: 2 - Affiliated | R178: 675 | S178: Transfer b/c of Internal Merger (88C) | V178: + | X178: >= | Y178: -5 | Z178: <= | AA178: 5 | AD178: FS Item, ToM | AG178: e | AH178: e
B179: ACTIVE | C179: Derivatives | E179: A159_09 | F179: =VLOOKUP(E179,Sheet2!$A:$A,1,FALSE) -> A159_09 | L179: A159_09 No gains&losses to equity - Derivatives | O179: SN_12905 | P179: Credit Risk Derivatives - Trading | Q179: 2 - Affiliated | R179: 665 | S179: Transfer b/c of Internal Merger (88A) | V179: + | X179: >= | Y179: -5 | Z179: <= | AA179: 5 | AD179: FS Item, ToM | AG179: e | AH179: e
B180: ACTIVE | C180: Derivatives | E180: A159_09 | F180: =VLOOKUP(E180,Sheet2!$A:$A,1,FALSE) -> A159_09 | L180: A159_09 No gains&losses to equity - Derivatives | O180: SN_12910 | P180: Other Risk Derivatives - Trading | Q180: 2 - Affiliated | R180: 964 | S180: Corrections BB Negative difference (88C) | V180: + | X180: >= | Y180: -5 | Z180: <= | AA180: 5 | AD180: FS Item, ToM | AG180: e | AH180: e
B181: ACTIVE | C181: Derivatives | E181: A159_09 | F181: =VLOOKUP(E181,Sheet2!$A:$A,1,FALSE) -> A159_09 | L181: A159_09 No gains&losses to equity - Derivatives | O181: SN_12910 | P181: Other Risk Derivatives - Trading | Q181: 2 - Affiliated | R181: 675 | S181: Transfer b/c of Internal Merger (88C) | V181: + | X181: >= | Y181: -5 | Z181: <= | AA181: 5 | AD181: FS Item, ToM | AG181: e | AH181: e
...

Sheet Sheet2
A1: X-Check No.
A2: A011_09
A3: A029_09
A4: A079_00
A5: A090_00
A6: A091_00
A7: A114_00
A8: A137_00
A9: A147_00
A10: A152_00
A11: A153_00
A12: A159_09
... A203: AR033_00
