Workbook

Sheet cross checks all
A1: Type of change | B1: Status | C1: Category | D1: Sense Check | E1: X-Check No. | F1: Reference X-Check (Condition) | G1: Applicable Quarters | H1: Included RUs | I1: Excluded RUs | J1: Reference X-Check (Limit, %) | Q1: =SUM(Q2:Q1893) -> 0 | R1: =SUM(R2:R1893) -> 19 | S1: =SUM(S2:S1893) -> 0 | T1: =SUM(T2:T1893) -> 0 | U1: =SUM(U2:U1893) -> 0
A2: Changed | B2: ACTIVE | C2: Real Estate held for Investment | E2: A047_00 | K2: =IFERROR(VLOOKUP($E2 & "|" & F2,comparison!$A$2:$A$19,1,FALSE),"") | L2: =IFERROR(VLOOKUP($E2 & "|" & G2,comparison!$A$2:$A$19,1,FALSE),"") | M2: =IFERROR(VLOOKUP($E2 & "|" & H2,comparison!$A$2:$A$19,1,FALSE),"") | N2: =IFERROR(VLOOKUP($E2 & "|" & I2,comparison!$A$2:$A$19,1,FALSE),"") | O2: =IFERROR(VLOOKUP($E2 & "|" & J2,comparison!$A$2:$A$19,1,FALSE),"") | Q2: =IF(LEN(K2)>0,1,0) -> 0 | R2: =IF(LEN(L2)>0,1,0) -> 0 | S2: =IF(LEN(M2)>0,1,0) -> 0 | T2: =IF(LEN(N2)>0,1,0) -> 0 | U2: =IF(LEN(O2)>0,1,0) -> 0
A3: Changed | B3: ACTIVE | C3: Equity Securities - Common Stock | D3: yes | E3: A074_00 | K3: =IFERROR(VLOOKUP($E3 & "|" & F3,comparison!$A$2:$A$19,1,FALSE),"") | L3: =IFERROR(VLOOKUP($E3 & "|" & G3,comparison!$A$2:$A$19,1,FALSE),"") | M3: =IFERROR(VLOOKUP($E3 & "|" & H3,comparison!$A$2:$A$19,1,FALSE),"") | N3: =IFERROR(VLOOKUP($E3 & "|" & I3,comparison!$A$2:$A$19,1,FALSE),"") | O3: =IFERROR(VLOOKUP($E3 & "|" & J3,comparison!$A$2:$A$19,1,FALSE),"") | Q3: =IF(LEN(K3)>0,1,0) -> 0 | R3: =IF(LEN(L3)>0,1,0) -> 0 | S3: =IF(LEN(M3)>0,1,0) -> 0 | T3: =IF(LEN(N3)>0,1,0) -> 0 | U3: =IF(LEN(O3)>0,1,0) -> 0
A4: Changed | B4: ACTIVE | C4: Equity Securities - Common Stock | E4: A079_00 | K4: =IFERROR(VLOOKUP($E4 & "|" & F4,comparison!$A$2:$A$19,1,FALSE),"") | L4: =IFERROR(VLOOKUP($E4 & "|" & G4,comparison!$A$2:$A$19,1,FALSE),"") | M4: =IFERROR(VLOOKUP($E4 & "|" & H4,comparison!$A$2:$A$19,1,FALSE),"") | N4: =IFERROR(VLOOKUP($E4 & "|" & I4,comparison!$A$2:$A$19,1,FALSE),"") | O4: =IFERROR(VLOOKUP($E4 & "|" & J4,comparison!$A$2:$A$19,1,FALSE),"") | Q4: =IF(LEN(K4)>0,1,0) -> 0 | R4: =IF(LEN(L4)>0,1,0) -> 0 | S4: =IF(LEN(M4)>0,1,0) -> 0 | T4: =IF(LEN(N4)>0,1,0) -> 0 | U4: =IF(LEN(O4)>0,1,0) -> 0
A5: Changed | B5: ACTIVE | C5: Equity Securities - Common Stock | E5: A081_00 | K5: =IFERROR(VLOOKUP($E5 & "|" & F5,comparison!$A$2:$A$19,1,FALSE),"") | L5: =IFERROR(VLOOKUP($E5 & "|" & G5,comparison!$A$2:$A$19,1,FALSE),"") | M5: =IFERROR(VLOOKUP($E5 & "|" & H5,comparison!$A$2:$A$19,1,FALSE),"") | N5: =IFERROR(VLOOKUP($E5 & "|" & I5,comparison!$A$2:$A$19,1,FALSE),"") | O5: =IFERROR(VLOOKUP($E5 & "|" & J5,comparison!$A$2:$A$19,1,FALSE),"") | Q5: =IF(LEN(K5)>0,1,0) -> 0 | R5: =IF(LEN(L5)>0,1,0) -> 0 | S5: =IF(LEN(M5)>0,1,0) -> 0 | T5: =IF(LEN(N5)>0,1,0) -> 0 | U5: =IF(LEN(O5)>0,1,0) -> 0
A6: Changed | B6: ACTIVE | C6: Equity Securities - Common Stock | D6: yes | E6: A082_00 | K6: =IFERROR(VLOOKUP($E6 & "|" & F6,comparison!$A$2:$A$19,1,FALSE),"") | L6: =IFERROR(VLOOKUP($E6 & "|" & G6,comparison!$A$2:$A$19,1,FALSE),"") | M6: =IFERROR(VLOOKUP($E6 & "|" & H6,comparison!$A$2:$A$19,1,FALSE),"") | N6: =IFERROR(VLOOKUP($E6 & "|" & I6,comparison!$A$2:$A$19,1,FALSE),"") | O6: =IFERROR(VLOOKUP($E6 & "|" & J6,comparison!$A$2:$A$19,1,FALSE),"") | Q6: =IF(LEN(K6)>0,1,0) -> 0 | R6: =IF(LEN(L6)>0,1,0) -> 0 | S6: =IF(LEN(M6)>0,1,0) -> 0 | T6: =IF(LEN(N6)>0,1,0) -> 0 | U6: =IF(LEN(O6)>0,1,0) -> 0
A7: Changed | B7: ACTIVE | C7: Equity Securities - Open-end investment funds | E7: A090_00 | K7: =IFERROR(VLOOKUP($E7 & "|" & F7,comparison!$A$2:$A$19,1,FALSE),"") | L7: =IFERROR(VLOOKUP($E7 & "|" & G7,comparison!$A$2:$A$19,1,FALSE),"") | M7: =IFERROR(VLOOKUP($E7 & "|" & H7,comparison!$A$2:$A$19,1,FALSE),"") | N7: =IFERROR(VLOOKUP($E7 & "|" & I7,comparison!$A$2:$A$19,1,FALSE),"") | O7: =IFERROR(VLOOKUP($E7 & "|" & J7,comparison!$A$2:$A$19,1,FALSE),"") | Q7: =IF(LEN(K7)>0,1,0) -> 0 | R7: =IF(LEN(L7)>0,1,0) -> 0 | S7: =IF(LEN(M7)>0,1,0) -> 0 | T7: =IF(LEN(N7)>0,1,0) -> 0 | U7: =IF(LEN(O7)>0,1,0) -> 0
A8: Changed | B8: ACTIVE | C8: Equity Securities - Open-end investment funds | E8: A091_00 | K8: =IFERROR(VLOOKUP($E8 & "|" & F8,comparison!$A$2:$A$19,1,FALSE),"") | L8: =IFERROR(VLOOKUP($E8 & "|" & G8,comparison!$A$2:$A$19,1,FALSE),"") | M8: =IFERROR(VLOOKUP($E8 & "|" & H8,comparison!$A$2:$A$19,1,FALSE),"") | N8: =IFERROR(VLOOKUP($E8 & "|" & I8,comparison!$A$2:$A$19,1,FALSE),"") | O8: =IFERROR(VLOOKUP($E8 & "|" & J8,comparison!$A$2:$A$19,1,FALSE),"") | Q8: =IF(LEN(K8)>0,1,0) -> 0 | R8: =IF(LEN(L8)>0,1,0) -> 0 | S8: =IF(LEN(M8)>0,1,0) -> 0 | T8: =IF(LEN(N8)>0,1,0) -> 0 | U8: =IF(LEN(O8)>0,1,0) -> 0
A9: Changed | B9: ACTIVE | C9: Equity Securities - Open-end investment funds | D9: yes | E9: A094_00 | K9: =IFERROR(VLOOKUP($E9 & "|" & F9,comparison!$A$2:$A$19,1,FALSE),"") | L9: =IFERROR(VLOOKUP($E9 & "|" & G9,comparison!$A$2:$A$19,1,FALSE),"") | M9: =IFERROR(VLOOKUP($E9 & "|" & H9,comparison!$A$2:$A$19,1,FALSE),"") | N9: =IFERROR(VLOOKUP($E9 & "|" & I9,comparison!$A$2:$A$19,1,FALSE),"") | O9: =IFERROR(VLOOKUP($E9 & "|" & J9,comparison!$A$2:$A$19,1,FALSE),"") | Q9: =IF(LEN(K9)>0,1,0) -> 0 | R9: =IF(LEN(L9)>0,1,0) -> 0 | S9: =IF(LEN(M9)>0,1,0) -> 0 | T9: =IF(LEN(N9)>0,1,0) -> 0 | U9: =IF(LEN(O9)>0,1,0) -> 0
A10: Changed | B10: ACTIVE | C10: Equity Securities - Open-end investment funds | E10: A096_00 | K10: =IFERROR(VLOOKUP($E10 & "|" & F10,comparison!$A$2:$A$19,1,FALSE),"") | L10: =IFERROR(VLOOKUP($E10 & "|" & G10,comparison!$A$2:$A$19,1,FALSE),"") | M10: =IFERROR(VLOOKUP($E10 & "|" & H10,comparison!$A$2:$A$19,1,FALSE),"") | N10: =IFERROR(VLOOKUP($E10 & "|" & I10,comparison!$A$2:$A$19,1,FALSE),"") | O10: =IFERROR(VLOOKUP($E10 & "|" & J10,comparison!$A$2:$A$19,1,FALSE),"") | Q10: =IF(LEN(K10)>0,1,0) -> 0 | R10: =IF(LEN(L10)>0,1,0) -> 0 | S10: =IF(LEN(M10)>0,1,0) -> 0 | T10: =IF(LEN(N10)>0,1,0) -> 0 | U10: =IF(LEN(O10)>0,1,0) -> 0
A11: Changed | B11: ACTIVE | C11: Debt Securities - FVOCI | E11: A101_00 | K11: =IFERROR(VLOOKUP($E11 & "|" & F11,comparison!$A$2:$A$19,1,FALSE),"") | L11: =IFERROR(VLOOKUP($E11 & "|" & G11,comparison!$A$2:$A$19,1,FALSE),"") | M11: =IFERROR(VLOOKUP($E11 & "|" & H11,comparison!$A$2:$A$19,1,FALSE),"") | N11: =IFERROR(VLOOKUP($E11 & "|" & I11,comparison!$A$2:$A$19,1,FALSE),"") | O11: =IFERROR(VLOOKUP($E11 & "|" & J11,comparison!$A$2:$A$19,1,FALSE),"") | Q11: =IF(LEN(K11)>0,1,0) -> 0 | R11: =IF(LEN(L11)>0,1,0) -> 0 | S11: =IF(LEN(M11)>0,1,0) -> 0 | T11: =IF(LEN(N11)>0,1,0) -> 0 | U11: =IF(LEN(O11)>0,1,0) -> 0
A12: Changed | B12: ACTIVE | C12: Debt Securities - Amortized cost | E12: A102_00 | K12: =IFERROR(VLOOKUP($E12 & "|" & F12,comparison!$A$2:$A$19,1,FALSE),"") | L12: =IFERROR(VLOOKUP($E12 & "|" & G12,comparison!$A$2:$A$19,1,FALSE),"") | M12: =IFERROR(VLOOKUP($E12 & "|" & H12,comparison!$A$2:$A$19,1,FALSE),"") | N12: =IFERROR(VLOOKUP($E12 & "|" & I12,comparison!$A$2:$A$19,1,FALSE),"") | O12: =IFERROR(VLOOKUP($E12 & "|" & J12,comparison!$A$2:$A$19,1,FALSE),"") | Q12: =IF(LEN(K12)>0,1,0) -> 0 | R12: =IF(LEN(L12)>0,1,0) -> 0 | S12: =IF(LEN(M12)>0,1,0) -> 0 | T12: =IF(LEN(N12)>0,1,0) -> 0 | U12: =IF(LEN(O12)>0,1,0) -> 0
A13: Changed | B13: ACTIVE | C13: FVPL debts | D13: yes | E13: A114_00 | K13: =IFERROR(VLOOKUP($E13 & "|" & F13,comparison!$A$2:$A$19,1,FALSE),"") | L13: =IFERROR(VLOOKUP($E13 & "|" & G13,comparison!$A$2:$A$19,1,FALSE),"") | M13: =IFERROR(VLOOKUP($E13 & "|" & H13,comparison!$A$2:$A$19,1,FALSE),"") | N13: =IFERROR(VLOOKUP($E13 & "|" & I13,comparison!$A$2:$A$19,1,FALSE),"") | O13: =IFERROR(VLOOKUP($E13 & "|" & J13,comparison!$A$2:$A$19,1,FALSE),"") | Q13: =IF(LEN(K13)>0,1,0) -> 0 | R13: =IF(LEN(L13)>0,1,0) -> 0 | S13: =IF(LEN(M13)>0,1,0) -> 0 | T13: =IF(LEN(N13)>0,1,0) -> 0 | U13: =IF(LEN(O13)>0,1,0) -> 0
A14: Changed | B14: ACTIVE | C14: Real Estate held for Investment | E14: A137_00 | K14: =IFERROR(VLOOKUP($E14 & "|" & F14,comparison!$A$2:$A$19,1,FALSE),"") | L14: =IFERROR(VLOOKUP($E14 & "|" & G14,comparison!$A$2:$A$19,1,FALSE),"") | M14: =IFERROR(VLOOKUP($E14 & "|" & H14,comparison!$A$2:$A$19,1,FALSE),"") | N14: =IFERROR(VLOOKUP($E14 & "|" & I14,comparison!$A$2:$A$19,1,FALSE),"") | O14: =IFERROR(VLOOKUP($E14 & "|" & J14,comparison!$A$2:$A$19,1,FALSE),"") | Q14: =IF(LEN(K14)>0,1,0) -> 0 | R14: =IF(LEN(L14)>0,1,0) -> 0 | S14: =IF(LEN(M14)>0,1,0) -> 0 | T14: =IF(LEN(N14)>0,1,0) -> 0 | U14: =IF(LEN(O14)>0,1,0) -> 0
A15: Changed | B15: ACTIVE | C15: Real Estate held for Investment | E15: A138_00 | K15: =IFERROR(VLOOKUP($E15 & "|" & F15,comparison!$A$2:$A$19,1,FALSE),"") | L15: =IFERROR(VLOOKUP($E15 & "|" & G15,comparison!$A$2:$A$19,1,FALSE),"") | M15: =IFERROR(VLOOKUP($E15 & "|" & H15,comparison!$A$2:$A$19,1,FALSE),"") | N15: =IFERROR(VLOOKUP($E15 & "|" & I15,comparison!$A$2:$A$19,1,FALSE),"") | O15: =IFERROR(VLOOKUP($E15 & "|" & J15,comparison!$A$2:$A$19,1,FALSE),"") | Q15: =IF(LEN(K15)>0,1,0) -> 0 | R15: =IF(LEN(L15)>0,1,0) -> 0 | S15: =IF(LEN(M15)>0,1,0) -> 0 | T15: =IF(LEN(N15)>0,1,0) -> 0 | U15: =IF(LEN(O15)>0,1,0) -> 0
A16: Changed | B16: ACTIVE | C16: Real Estate held for Investment | E16: A139_00 | K16: =IFERROR(VLOOKUP($E16 & "|" & F16,comparison!$A$2:$A$19,1,FALSE),"") | L16: =IFERROR(VLOOKUP($E16 & "|" & G16,comparison!$A$2:$A$19,1,FALSE),"") | M16: =IFERROR(VLOOKUP($E16 & "|" & H16,comparison!$A$2:$A$19,1,FALSE),"") | N16: =IFERROR(VLOOKUP($E16 & "|" & I16,comparison!$A$2:$A$19,1,FALSE),"") | O16: =IFERROR(VLOOKUP($E16 & "|" & J16,comparison!$A$2:$A$19,1,FALSE),"") | Q16: =IF(LEN(K16)>0,1,0) -> 0 | R16: =IF(LEN(L16)>0,1,0) -> 0 | S16: =IF(LEN(M16)>0,1,0) -> 0 | T16: =IF(LEN(N16)>0,1,0) -> 0 | U16: =IF(LEN(O16)>0,1,0) -> 0
A17: Changed | B17: ACTIVE | C17: Equity Securities - Non-redeemable Pref. Shares | E17: A152_00 | K17: =IFERROR(VLOOKUP($E17 & "|" & F17,comparison!$A$2:$A$19,1,FALSE),"") | L17: =IFERROR(VLOOKUP($E17 & "|" & G17,comparison!$A$2:$A$19,1,FALSE),"") | M17: =IFERROR(VLOOKUP($E17 & "|" & H17,comparison!$A$2:$A$19,1,FALSE),"") | N17: =IFERROR(VLOOKUP($E17 & "|" & I17,comparison!$A$2:$A$19,1,FALSE),"") | O17: =IFERROR(VLOOKUP($E17 & "|" & J17,comparison!$A$2:$A$19,1,FALSE),"") | Q17: =IF(LEN(K17)>0,1,0) -> 0 | R17: =IF(LEN(L17)>0,1,0) -> 0 | S17: =IF(LEN(M17)>0,1,0) -> 0 | T17: =IF(LEN(N17)>0,1,0) -> 0 | U17: =IF(LEN(O17)>0,1,0) -> 0
A18: Changed | B18: ACTIVE | C18: Equity Securities - Non-redeemable Pref. Shares | E18: A153_00 | K18: =IFERROR(VLOOKUP($E18 & "|" & F18,comparison!$A$2:$A$19,1,FALSE),"") | L18: =IFERROR(VLOOKUP($E18 & "|" & G18,comparison!$A$2:$A$19,1,FALSE),"") | M18: =IFERROR(VLOOKUP($E18 & "|" & H18,comparison!$A$2:$A$19,1,FALSE),"") | N18: =IFERROR(VLOOKUP($E18 & "|" & I18,comparison!$A$2:$A$19,1,FALSE),"") | O18: =IFERROR(VLOOKUP($E18 & "|" & J18,comparison!$A$2:$A$19,1,FALSE),"") | Q18: =IF(LEN(K18)>0,1,0) -> 0 | R18: =IF(LEN(L18)>0,1,0) -> 0 | S18: =IF(LEN(M18)>0,1,0) -> 0 | T18: =IF(LEN(N18)>0,1,0) -> 0 | U18: =IF(LEN(O18)>0,1,0) -> 0
A19: Changed | B19: ACTIVE | C19: Equity Securities - Non-redeemable Pref. Shares | E19: A158_00 | K19: =IFERROR(VLOOKUP($E19 & "|" & F19,comparison!$A$2:$A$19,1,FALSE),"") | L19: =IFERROR(VLOOKUP($E19 & "|" & G19,comparison!$A$2:$A$19,1,FALSE),"") | M19: =IFERROR(VLOOKUP($E19 & "|" & H19,comparison!$A$2:$A$19,1,FALSE),"") | N19: =IFERROR(VLOOKUP($E19 & "|" & I19,comparison!$A$2:$A$19,1,FALSE),"") | O19: =IFERROR(VLOOKUP($E19 & "|" & J19,comparison!$A$2:$A$19,1,FALSE),"") | Q19: =IF(LEN(K19)>0,1,0) -> 0 | R19: =IF(LEN(L19)>0,1,0) -> 0 | S19: =IF(LEN(M19)>0,1,0) -> 0 | T19: =IF(LEN(N19)>0,1,0) -> 0 | U19: =IF(LEN(O19)>0,1,0) -> 0
A20: Changed | B20: ACTIVE | C20: Loans and Receivables | D20: yes | E20: A171_00 | K20: =IFERROR(VLOOKUP($E20 & "|" & F20,comparison!$A$2:$A$19,1,FALSE),"") | L20: =IFERROR(VLOOKUP($E20 & "|" & G20,comparison!$A$2:$A$19,1,FALSE),"") | M20: =IFERROR(VLOOKUP($E20 & "|" & H20,comparison!$A$2:$A$19,1,FALSE),"") | N20: =IFERROR(VLOOKUP($E20 & "|" & I20,comparison!$A$2:$A$19,1,FALSE),"") | O20: =IFERROR(VLOOKUP($E20 & "|" & J20,comparison!$A$2:$A$19,1,FALSE),"") | Q20: =IF(LEN(K20)>0,1,0) -> 0 | R20: =IF(LEN(L20)>0,1,0) -> 0 | S20: =IF(LEN(M20)>0,1,0) -> 0 | T20: =IF(LEN(N20)>0,1,0) -> 0 | U20: =IF(LEN(O20)>0,1,0) -> 0
A21: Changed | B21: ACTIVE | C21: Holdings in affiliates | E21: A336_00 | K21: =IFERROR(VLOOKUP($E21 & "|" & F21,comparison!$A$2:$A$19,1,FALSE),"") | L21: =IFERROR(VLOOKUP($E21 & "|" & G21,comparison!$A$2:$A$19,1,FALSE),"") | M21: =IFERROR(VLOOKUP($E21 & "|" & H21,comparison!$A$2:$A$19,1,FALSE),"") | N21: =IFERROR(VLOOKUP($E21 & "|" & I21,comparison!$A$2:$A$19,1,FALSE),"") | O21: =IFERROR(VLOOKUP($E21 & "|" & J21,comparison!$A$2:$A$19,1,FALSE),"") | Q21: =IF(LEN(K21)>0,1,0) -> 0 | R21: =IF(LEN(L21)>0,1,0) -> 0 | S21: =IF(LEN(M21)>0,1,0) -> 0 | T21: =IF(LEN(N21)>0,1,0) -> 0 | U21: =IF(LEN(O21)>0,1,0) -> 0
A22: Changed | B22: ACTIVE | C22: IFRS 16 | E22: A369_00 | K22: =IFERROR(VLOOKUP($E22 & "|" & F22,comparison!$A$2:$A$19,1,FALSE),"") | L22: =IFERROR(VLOOKUP($E22 & "|" & G22,comparison!$A$2:$A$19,1,FALSE),"") | M22: =IFERROR(VLOOKUP($E22 & "|" & H22,comparison!$A$2:$A$19,1,FALSE),"") | N22: =IFERROR(VLOOKUP($E22 & "|" & I22,comparison!$A$2:$A$19,1,FALSE),"") | O22: =IFERROR(VLOOKUP($E22 & "|" & J22,comparison!$A$2:$A$19,1,FALSE),"") | Q22: =IF(LEN(K22)>0,1,0) -> 0 | R22: =IF(LEN(L22)>0,1,0) -> 0 | S22: =IF(LEN(M22)>0,1,0) -> 0 | T22: =IF(LEN(N22)>0,1,0) -> 0 | U22: =IF(LEN(O22)>0,1,0) -> 0
A23: Changed | B23: ACTIVE | C23: IFRS 16 | E23: A370_00 | K23: =IFERROR(VLOOKUP($E23 & "|" & F23,comparison!$A$2:$A$19,1,FALSE),"") | L23: =IFERROR(VLOOKUP($E23 & "|" & G23,comparison!$A$2:$A$19,1,FALSE),"") | M23: =IFERROR(VLOOKUP($E23 & "|" & H23,comparison!$A$2:$A$19,1,FALSE),"") | N23: =IFERROR(VLOOKUP($E23 & "|" & I23,comparison!$A$2:$A$19,1,FALSE),"") | O23: =IFERROR(VLOOKUP($E23 & "|" & J23,comparison!$A$2:$A$19,1,FALSE),"") | Q23: =IF(LEN(K23)>0,1,0) -> 0 | R23: =IF(LEN(L23)>0,1,0) -> 0 | S23: =IF(LEN(M23)>0,1,0) -> 0 | T23: =IF(LEN(N23)>0,1,0) -> 0 | U23: =IF(LEN(O23)>0,1,0) -> 0
A24: Changed | B24: ACTIVE | C24: IFRS 16 | E24: A371_00 | K24: =IFERROR(VLOOKUP($E24 & "|" & F24,comparison!$A$2:$A$19,1,FALSE),"") | L24: =IFERROR(VLOOKUP($E24 & "|" & G24,comparison!$A$2:$A$19,1,FALSE),"") | M24: =IFERROR(VLOOKUP($E24 & "|" & H24,comparison!$A$2:$A$19,1,FALSE),"") | N24: =IFERROR(VLOOKUP($E24 & "|" & I24,comparison!$A$2:$A$19,1,FALSE),"") | O24: =IFERROR(VLOOKUP($E24 & "|" & J24,comparison!$A$2:$A$19,1,FALSE),"") | Q24: =IF(LEN(K24)>0,1,0) -> 0 | R24: =IF(LEN(L24)>0,1,0) -> 0 | S24: =IF(LEN(M24)>0,1,0) -> 0 | T24: =IF(LEN(N24)>0,1,0) -> 0 | U24: =IF(LEN(O24)>0,1,0) -> 0
A25: Changed | B25: ACTIVE | C25: Fixed Assets | E25: A400_00 | K25: =IFERROR(VLOOKUP($E25 & "|" & F25,comparison!$A$2:$A$19,1,FALSE),"") | L25: =IFERROR(VLOOKUP($E25 & "|" & G25,comparison!$A$2:$A$19,1,FALSE),"") | M25: =IFERROR(VLOOKUP($E25 & "|" & H25,comparison!$A$2:$A$19,1,FALSE),"") | N25: =IFERROR(VLOOKUP($E25 & "|" & I25,comparison!$A$2:$A$19,1,FALSE),"") | O25: =IFERROR(VLOOKUP($E25 & "|" & J25,comparison!$A$2:$A$19,1,FALSE),"") | Q25: =IF(LEN(K25)>0,1,0) -> 0 | R25: =IF(LEN(L25)>0,1,0) -> 0 | S25: =IF(LEN(M25)>0,1,0) -> 0 | T25: =IF(LEN(N25)>0,1,0) -> 0 | U25: =IF(LEN(O25)>0,1,0) -> 0
A26: Changed | B26: ACTIVE | C26: Fixed Assets | E26: A436_00 | K26: =IFERROR(VLOOKUP($E26 & "|" & F26,comparison!$A$2:$A$19,1,FALSE),"") | L26: =IFERROR(VLOOKUP($E26 & "|" & G26,comparison!$A$2:$A$19,1,FALSE),"") | M26: =IFERROR(VLOOKUP($E26 & "|" & H26,comparison!$A$2:$A$19,1,FALSE),"") | N26: =IFERROR(VLOOKUP($E26 & "|" & I26,comparison!$A$2:$A$19,1,FALSE),"") | O26: =IFERROR(VLOOKUP($E26 & "|" & J26,comparison!$A$2:$A$19,1,FALSE),"") | Q26: =IF(LEN(K26)>0,1,0) -> 0 | R26: =IF(LEN(L26)>0,1,0) -> 0 | S26: =IF(LEN(M26)>0,1,0) -> 0 | T26: =IF(LEN(N26)>0,1,0) -> 0 | U26: =IF(LEN(O26)>0,1,0) -> 0
A27: Changed | B27: ACTIVE | C27: Other Intangible Assets | E27: A437_00 | K27: =IFERROR(VLOOKUP($E27 & "|" & F27,comparison!$A$2:$A$19,1,FALSE),"") | L27: =IFERROR(VLOOKUP($E27 & "|" & G27,comparison!$A$2:$A$19,1,FALSE),"") | M27: =IFERROR(VLOOKUP($E27 & "|" & H27,comparison!$A$2:$A$19,1,FALSE),"") | N27: =IFERROR(VLOOKUP($E27 & "|" & I27,comparison!$A$2:$A$19,1,FALSE),"") | O27: =IFERROR(VLOOKUP($E27 & "|" & J27,comparison!$A$2:$A$19,1,FALSE),"") | Q27: =IF(LEN(K27)>0,1,0) -> 0 | R27: =IF(LEN(L27)>0,1,0) -> 0 | S27: =IF(LEN(M27)>0,1,0) -> 0 | T27: =IF(LEN(N27)>0,1,0) -> 0 | U27: =IF(LEN(O27)>0,1,0) -> 0
A28: Changed | B28: ACTIVE | C28: Fixed Assets | E28: A450_00 | K28: =IFERROR(VLOOKUP($E28 & "|" & F28,comparison!$A$2:$A$19,1,FALSE),"") | L28: =IFERROR(VLOOKUP($E28 & "|" & G28,comparison!$A$2:$A$19,1,FALSE),"") | M28: =IFERROR(VLOOKUP($E28 & "|" & H28,comparison!$A$2:$A$19,1,FALSE),"") | N28: =IFERROR(VLOOKUP($E28 & "|" & I28,comparison!$A$2:$A$19,1,FALSE),"") | O28: =IFERROR(VLOOKUP($E28 & "|" & J28,comparison!$A$2:$A$19,1,FALSE),"") | Q28: =IF(LEN(K28)>0,1,0) -> 0 | R28: =IF(LEN(L28)>0,1,0) -> 0 | S28: =IF(LEN(M28)>0,1,0) -> 0 | T28: =IF(LEN(N28)>0,1,0) -> 0 | U28: =IF(LEN(O28)>0,1,0) -> 0
A29: Changed | B29: ACTIVE | C29: Fixed Assets | E29: A469_00 | K29: =IFERROR(VLOOKUP($E29 & "|" & F29,comparison!$A$2:$A$19,1,FALSE),"") | L29: =IFERROR(VLOOKUP($E29 & "|" & G29,comparison!$A$2:$A$19,1,FALSE),"") | M29: =IFERROR(VLOOKUP($E29 & "|" & H29,comparison!$A$2:$A$19,1,FALSE),"") | N29: =IFERROR(VLOOKUP($E29 & "|" & I29,comparison!$A$2:$A$19,1,FALSE),"") | O29: =IFERROR(VLOOKUP($E29 & "|" & J29,comparison!$A$2:$A$19,1,FALSE),"") | Q29: =IF(LEN(K29)>0,1,0) -> 0 | R29: =IF(LEN(L29)>0,1,0) -> 0 | S29: =IF(LEN(M29)>0,1,0) -> 0 | T29: =IF(LEN(N29)>0,1,0) -> 0 | U29: =IF(LEN(O29)>0,1,0) -> 0
A30: Changed | B30: ACTIVE | C30: SST only check | E30: A834_00 | I30: CON_10000 | K30: =IFERROR(VLOOKUP($E30 & "|" & F30,comparison!$A$2:$A$19,1,FALSE),"") | L30: =IFERROR(VLOOKUP($E30 & "|" & G30,comparison!$A$2:$A$19,1,FALSE),"") | M30: =IFERROR(VLOOKUP($E30 & "|" & H30,comparison!$A$2:$A$19,1,FALSE),"") | N30: =IFERROR(VLOOKUP($E30 & "|" & I30,comparison!$A$2:$A$19,1,FALSE),"") | O30: =IFERROR(VLOOKUP($E30 & "|" & J30,comparison!$A$2:$A$19,1,FALSE),"") | Q30: =IF(LEN(K30)>0,1,0) -> 0 | R30: =IF(LEN(L30)>0,1,0) -> 0 | S30: =IF(LEN(M30)>0,1,0) -> 0 | T30: =IF(LEN(N30)>0,1,0) -> 0 | U30: =IF(LEN(O30)>0,1,0) -> 0
A31: Changed | B31: ACTIVE | C31: Debt Securities - Amortized cost | E31: AE003_09 | K31: =IFERROR(VLOOKUP($E31 & "|" & F31,comparison!$A$2:$A$19,1,FALSE),"") | L31: =IFERROR(VLOOKUP($E31 & "|" & G31,comparison!$A$2:$A$19,1,FALSE),"") | M31: =IFERROR(VLOOKUP($E31 & "|" & H31,comparison!$A$2:$A$19,1,FALSE),"") | N31: =IFERROR(VLOOKUP($E31 & "|" & I31,comparison!$A$2:$A$19,1,FALSE),"") | O31: =IFERROR(VLOOKUP($E31 & "|" & J31,comparison!$A$2:$A$19,1,FALSE),"") | Q31: =IF(LEN(K31)>0,1,0) -> 0 | R31: =IF(LEN(L31)>0,1,0) -> 0 | S31: =IF(LEN(M31)>0,1,0) -> 0 | T31: =IF(LEN(N31)>0,1,0) -> 0 | U31: =IF(LEN(O31)>0,1,0) -> 0
A32: Changed | B32: ACTIVE | C32: Debt Securities - Amortized cost | E32: AE006_09 | K32: =IFERROR(VLOOKUP($E32 & "|" & F32,comparison!$A$2:$A$19,1,FALSE),"") | L32: =IFERROR(VLOOKUP($E32 & "|" & G32,comparison!$A$2:$A$19,1,FALSE),"") | M32: =IFERROR(VLOOKUP($E32 & "|" & H32,comparison!$A$2:$A$19,1,FALSE),"") | N32: =IFERROR(VLOOKUP($E32 & "|" & I32,comparison!$A$2:$A$19,1,FALSE),"") | O32: =IFERROR(VLOOKUP($E32 & "|" & J32,comparison!$A$2:$A$19,1,FALSE),"") | Q32: =IF(LEN(K32)>0,1,0) -> 0 | R32: =IF(LEN(L32)>0,1,0) -> 0 | S32: =IF(LEN(M32)>0,1,0) -> 0 | T32: =IF(LEN(N32)>0,1,0) -> 0 | U32: =IF(LEN(O32)>0,1,0) -> 0
A33: Changed | B33: ACTIVE | C33: Debt Securities - FVOCI | E33: AE010_09 | K33: =IFERROR(VLOOKUP($E33 & "|" & F33,comparison!$A$2:$A$19,1,FALSE),"") | L33: =IFERROR(VLOOKUP($E33 & "|" & G33,comparison!$A$2:$A$19,1,FALSE),"") | M33: =IFERROR(VLOOKUP($E33 & "|" & H33,comparison!$A$2:$A$19,1,FALSE),"") | N33: =IFERROR(VLOOKUP($E33 & "|" & I33,comparison!$A$2:$A$19,1,FALSE),"") | O33: =IFERROR(VLOOKUP($E33 & "|" & J33,comparison!$A$2:$A$19,1,FALSE),"") | Q33: =IF(LEN(K33)>0,1,0) -> 0 | R33: =IF(LEN(L33)>0,1,0) -> 0 | S33: =IF(LEN(M33)>0,1,0) -> 0 | T33: =IF(LEN(N33)>0,1,0) -> 0 | U33: =IF(LEN(O33)>0,1,0) -> 0
A34: Changed | B34: ACTIVE | C34: Loans and Receivables | E34: AE018_09 | K34: =IFERROR(VLOOKUP($E34 & "|" & F34,comparison!$A$2:$A$19,1,FALSE),"") | L34: =IFERROR(VLOOKUP($E34 & "|" & G34,comparison!$A$2:$A$19,1,FALSE),"") | M34: =IFERROR(VLOOKUP($E34 & "|" & H34,comparison!$A$2:$A$19,1,FALSE),"") | N34: =IFERROR(VLOOKUP($E34 & "|" & I34,comparison!$A$2:$A$19,1,FALSE),"") | O34: =IFERROR(VLOOKUP($E34 & "|" & J34,comparison!$A$2:$A$19,1,FALSE),"") | Q34: =IF(LEN(K34)>0,1,0) -> 0 | R34: =IF(LEN(L34)>0,1,0) -> 0 | S34: =IF(LEN(M34)>0,1,0) -> 0 | T34: =IF(LEN(N34)>0,1,0) -> 0 | U34: =IF(LEN(O34)>0,1,0) -> 0
A35: Changed | B35: ACTIVE | C35: Loans and Receivables | E35: AE021_09 | K35: =IFERROR(VLOOKUP($E35 & "|" & F35,comparison!$A$2:$A$19,1,FALSE),"") | L35: =IFERROR(VLOOKUP($E35 & "|" & G35,comparison!$A$2:$A$19,1,FALSE),"") | M35: =IFERROR(VLOOKUP($E35 & "|" & H35,comparison!$A$2:$A$19,1,FALSE),"") | N35: =IFERROR(VLOOKUP($E35 & "|" & I35,comparison!$A$2:$A$19,1,FALSE),"") | O35: =IFERROR(VLOOKUP($E35 & "|" & J35,comparison!$A$2:$A$19,1,FALSE),"") | Q35: =IF(LEN(K35)>0,1,0) -> 0 | R35: =IF(LEN(L35)>0,1,0) -> 0 | S35: =IF(LEN(M35)>0,1,0) -> 0 | T35: =IF(LEN(N35)>0,1,0) -> 0 | U35: =IF(LEN(O35)>0,1,0) -> 0
A36: Changed | B36: ACTIVE | C36: Equity Securities - Alternative Investments | E36: AE027_00 | K36: =IFERROR(VLOOKUP($E36 & "|" & F36,comparison!$A$2:$A$19,1,FALSE),"") | L36: =IFERROR(VLOOKUP($E36 & "|" & G36,comparison!$A$2:$A$19,1,FALSE),"") | M36: =IFERROR(VLOOKUP($E36 & "|" & H36,comparison!$A$2:$A$19,1,FALSE),"") | N36: =IFERROR(VLOOKUP($E36 & "|" & I36,comparison!$A$2:$A$19,1,FALSE),"") | O36: =IFERROR(VLOOKUP($E36 & "|" & J36,comparison!$A$2:$A$19,1,FALSE),"") | Q36: =IF(LEN(K36)>0,1,0) -> 0 | R36: =IF(LEN(L36)>0,1,0) -> 0 | S36: =IF(LEN(M36)>0,1,0) -> 0 | T36: =IF(LEN(N36)>0,1,0) -> 0 | U36: =IF(LEN(O36)>0,1,0) -> 0
A37: Changed | B37: ACTIVE | C37: Loans and Receivables | E37: AE027_09 | K37: =IFERROR(VLOOKUP($E37 & "|" & F37,comparison!$A$2:$A$19,1,FALSE),"") | L37: =IFERROR(VLOOKUP($E37 & "|" & G37,comparison!$A$2:$A$19,1,FALSE),"") | M37: =IFERROR(VLOOKUP($E37 & "|" & H37,comparison!$A$2:$A$19,1,FALSE),"") | N37: =IFERROR(VLOOKUP($E37 & "|" & I37,comparison!$A$2:$A$19,1,FALSE),"") | O37: =IFERROR(VLOOKUP($E37 & "|" & J37,comparison!$A$2:$A$19,1,FALSE),"") | Q37: =IF(LEN(K37)>0,1,0) -> 0 | R37: =IF(LEN(L37)>0,1,0) -> 0 | S37: =IF(LEN(M37)>0,1,0) -> 0 | T37: =IF(LEN(N37)>0,1,0) -> 0 | U37: =IF(LEN(O37)>0,1,0) -> 0
A38: Changed | B38: ACTIVE | C38: Loans and Receivables | E38: AE029_09 | K38: =IFERROR(VLOOKUP($E38 & "|" & F38,comparison!$A$2:$A$19,1,FALSE),"") | L38: =IFERROR(VLOOKUP($E38 & "|" & G38,comparison!$A$2:$A$19,1,FALSE),"") | M38: =IFERROR(VLOOKUP($E38 & "|" & H38,comparison!$A$2:$A$19,1,FALSE),"") | N38: =IFERROR(VLOOKUP($E38 & "|" & I38,comparison!$A$2:$A$19,1,FALSE),"") | O38: =IFERROR(VLOOKUP($E38 & "|" & J38,comparison!$A$2:$A$19,1,FALSE),"") | Q38: =IF(LEN(K38)>0,1,0) -> 0 | R38: =IF(LEN(L38)>0,1,0) -> 0 | S38: =IF(LEN(M38)>0,1,0) -> 0 | T38: =IF(LEN(N38)>0,1,0) -> 0 | U38: =IF(LEN(O38)>0,1,0) -> 0
B39: ACTIVE | C39: ZIE only | E39: AE100_70 | K39: =IFERROR(VLOOKUP($E39 & "|" & F39,comparison!$A$2:$A$19,1,FALSE),"") | L39: =IFERROR(VLOOKUP($E39 & "|" & G39,comparison!$A$2:$A$19,1,FALSE),"") | M39: =IFERROR(VLOOKUP($E39 & "|" & H39,comparison!$A$2:$A$19,1,FALSE),"") | N39: =IFERROR(VLOOKUP($E39 & "|" & I39,comparison!$A$2:$A$19,1,FALSE),"") | O39: =IFERROR(VLOOKUP($E39 & "|" & J39,comparison!$A$2:$A$19,1,FALSE),"") | Q39: =IF(LEN(K39)>0,1,0) -> 0 | R39: =IF(LEN(L39)>0,1,0) -> 0 | S39: =IF(LEN(M39)>0,1,0) -> 0 | T39: =IF(LEN(N39)>0,1,0) -> 0 | U39: =IF(LEN(O39)>0,1,0) -> 0
B40: ACTIVE | C40: ZIE only | E40: AE101_70 | K40: =IFERROR(VLOOKUP($E40 & "|" & F40,comparison!$A$2:$A$19,1,FALSE),"") | L40: =IFERROR(VLOOKUP($E40 & "|" & G40,comparison!$A$2:$A$19,1,FALSE),"") | M40: =IFERROR(VLOOKUP($E40 & "|" & H40,comparison!$A$2:$A$19,1,FALSE),"") | N40: =IFERROR(VLOOKUP($E40 & "|" & I40,comparison!$A$2:$A$19,1,FALSE),"") | O40: =IFERROR(VLOOKUP($E40 & "|" & J40,comparison!$A$2:$A$19,1,FALSE),"") | Q40: =IF(LEN(K40)>0,1,0) -> 0 | R40: =IF(LEN(L40)>0,1,0) -> 0 | S40: =IF(LEN(M40)>0,1,0) -> 0 | T40: =IF(LEN(N40)>0,1,0) -> 0 | U40: =IF(LEN(O40)>0,1,0) -> 0
B41: ACTIVE | C41: ZIE only | E41: AE102_70 | K41: =IFERROR(VLOOKUP($E41 & "|" & F41,comparison!$A$2:$A$19,1,FALSE),"") | L41: =IFERROR(VLOOKUP($E41 & "|" & G41,comparison!$A$2:$A$19,1,FALSE),"") | M41: =IFERROR(VLOOKUP($E41 & "|" & H41,comparison!$A$2:$A$19,1,FALSE),"") | N41: =IFERROR(VLOOKUP($E41 & "|" & I41,comparison!$A$2:$A$19,1,FALSE),"") | O41: =IFERROR(VLOOKUP($E41 & "|" & J41,comparison!$A$2:$A$19,1,FALSE),"") | Q41: =IF(LEN(K41)>0,1,0) -> 0 | R41: =IF(LEN(L41)>0,1,0) -> 0 | S41: =IF(LEN(M41)>0,1,0) -> 0 | T41: =IF(LEN(N41)>0,1,0) -> 0 | U41: =IF(LEN(O41)>0,1,0) -> 0
B42: ACTIVE | C42: ZIE only | E42: AE105_70 | K42: =IFERROR(VLOOKUP($E42 & "|" & F42,comparison!$A$2:$A$19,1,FALSE),"") | L42: =IFERROR(VLOOKUP($E42 & "|" & G42,comparison!$A$2:$A$19,1,FALSE),"") | M42: =IFERROR(VLOOKUP($E42 & "|" & H42,comparison!$A$2:$A$19,1,FALSE),"") | N42: =IFERROR(VLOOKUP($E42 & "|" & I42,comparison!$A$2:$A$19,1,FALSE),"") | O42: =IFERROR(VLOOKUP($E42 & "|" & J42,comparison!$A$2:$A$19,1,FALSE),"") | Q42: =IF(LEN(K42)>0,1,0) -> 0 | R42: =IF(LEN(L42)>0,1,0) -> 0 | S42: =IF(LEN(M42)>0,1,0) -> 0 | T42: =IF(LEN(N42)>0,1,0) -> 0 | U42: =IF(LEN(O42)>0,1,0) -> 0
B43: ACTIVE | C43: ZIE only | E43: AE106_70 | K43: =IFERROR(VLOOKUP($E43 & "|" & F43,comparison!$A$2:$A$19,1,FALSE),"") | L43: =IFERROR(VLOOKUP($E43 & "|" & G43,comparison!$A$2:$A$19,1,FALSE),"") | M43: =IFERROR(VLOOKUP($E43 & "|" & H43,comparison!$A$2:$A$19,1,FALSE),"") | N43: =IFERROR(VLOOKUP($E43 & "|" & I43,comparison!$A$2:$A$19,1,FALSE),"") | O43: =IFERROR(VLOOKUP($E43 & "|" & J43,comparison!$A$2:$A$19,1,FALSE),"") | Q43: =IF(LEN(K43)>0,1,0) -> 0 | R43: =IF(LEN(L43)>0,1,0) -> 0 | S43: =IF(LEN(M43)>0,1,0) -> 0 | T43: =IF(LEN(N43)>0,1,0) -> 0 | U43: =IF(LEN(O43)>0,1,0) -> 0
B44: ACTIVE | C44: ZIE only | E44: AE107_70 | K44: =IFERROR(VLOOKUP($E44 & "|" & F44,comparison!$A$2:$A$19,1,FALSE),"") | L44: =IFERROR(VLOOKUP($E44 & "|" & G44,comparison!$A$2:$A$19,1,FALSE),"") | M44: =IFERROR(VLOOKUP($E44 & "|" & H44,comparison!$A$2:$A$19,1,FALSE),"") | N44: =IFERROR(VLOOKUP($E44 & "|" & I44,comparison!$A$2:$A$19,1,FALSE),"") | O44: =IFERROR(VLOOKUP($E44 & "|" & J44,comparison!$A$2:$A$19,1,FALSE),"") | Q44: =IF(LEN(K44)>0,1,0) -> 0 | R44: =IF(LEN(L44)>0,1,0) -> 0 | S44: =IF(LEN(M44)>0,1,0) -> 0 | T44: =IF(LEN(N44)>0,1,0) -> 0 | U44: =IF(LEN(O44)>0,1,0) -> 0
B45: ACTIVE | C45: ZIE only | E45: AE110_70 | K45: =IFERROR(VLOOKUP($E45 & "|" & F45,comparison!$A$2:$A$19,1,FALSE),"") | L45: =IFERROR(VLOOKUP($E45 & "|" & G45,comparison!$A$2:$A$19,1,FALSE),"") | M45: =IFERROR(VLOOKUP($E45 & "|" & H45,comparison!$A$2:$A$19,1,FALSE),"") | N45: =IFERROR(VLOOKUP($E45 & "|" & I45,comparison!$A$2:$A$19,1,FALSE),"") | O45: =IFERROR(VLOOKUP($E45 & "|" & J45,comparison!$A$2:$A$19,1,FALSE),"") | Q45: =IF(LEN(K45)>0,1,0) -> 0 | R45: =IF(LEN(L45)>0,1,0) -> 0 | S45: =IF(LEN(M45)>0,1,0) -> 0 | T45: =IF(LEN(N45)>0,1,0) -> 0 | U45: =IF(LEN(O45)>0,1,0) -> 0
B46: ACTIVE | C46: ZIE only | E46: AE111_70 | K46: =IFERROR(VLOOKUP($E46 & "|" & F46,comparison!$A$2:$A$19,1,FALSE),"") | L46: =IFERROR(VLOOKUP($E46 & "|" & G46,comparison!$A$2:$A$19,1,FALSE),"") | M46: =IFERROR(VLOOKUP($E46 & "|" & H46,comparison!$A$2:$A$19,1,FALSE),"") | N46: =IFERROR(VLOOKUP($E46 & "|" & I46,comparison!$A$2:$A$19,1,FALSE),"") | O46: =IFERROR(VLOOKUP($E46 & "|" & J46,comparison!$A$2:$A$19,1,FALSE),"") | Q46: =IF(LEN(K46)>0,1,0) -> 0 | R46: =IF(LEN(L46)>0,1,0) -> 0 | S46: =IF(LEN(M46)>0,1,0) -> 0 | T46: =IF(LEN(N46)>0,1,0) -> 0 | U46: =IF(LEN(O46)>0,1,0) -> 0
B47: ACTIVE | C47: ZIE only | E47: AE112_70 | K47: =IFERROR(VLOOKUP($E47 & "|" & F47,comparison!$A$2:$A$19,1,FALSE),"") | L47: =IFERROR(VLOOKUP($E47 & "|" & G47,comparison!$A$2:$A$19,1,FALSE),"") | M47: =IFERROR(VLOOKUP($E47 & "|" & H47,comparison!$A$2:$A$19,1,FALSE),"") | N47: =IFERROR(VLOOKUP($E47 & "|" & I47,comparison!$A$2:$A$19,1,FALSE),"") | O47: =IFERROR(VLOOKUP($E47 & "|" & J47,comparison!$A$2:$A$19,1,FALSE),"") | Q47: =IF(LEN(K47)>0,1,0) -> 0 | R47: =IF(LEN(L47)>0,1,0) -> 0 | S47: =IF(LEN(M47)>0,1,0) -> 0 | T47: =IF(LEN(N47)>0,1,0) -> 0 | U47: =IF(LEN(O47)>0,1,0) -> 0
B48: ACTIVE | C48: ZIE only | E48: AE113_70 | K48: =IFERROR(VLOOKUP($E48 & "|" & F48,comparison!$A$2:$A$19,1,FALSE),"") | L48: =IFERROR(VLOOKUP($E48 & "|" & G48,comparison!$A$2:$A$19,1,FALSE),"") | M48: =IFERROR(VLOOKUP($E48 & "|" & H48,comparison!$A$2:$A$19,1,FALSE),"") | N48: =IFERROR(VLOOKUP($E48 & "|" & I48,comparison!$A$2:$A$19,1,FALSE),"") | O48: =IFERROR(VLOOKUP($E48 & "|" & J48,comparison!$A$2:$A$19,1,FALSE),"") | Q48: =IF(LEN(K48)>0,1,0) -> 0 | R48: =IF(LEN(L48)>0,1,0) -> 0 | S48: =IF(LEN(M48)>0,1,0) -> 0 | T48: =IF(LEN(N48)>0,1,0) -> 0 | U48: =IF(LEN(O48)>0,1,0) -> 0
B49: ACTIVE | C49: ZIE only | E49: AE114_70 | K49: =IFERROR(VLOOKUP($E49 & "|" & F49,comparison!$A$2:$A$19,1,FALSE),"") | L49: =IFERROR(VLOOKUP($E49 & "|" & G49,comparison!$A$2:$A$19,1,FALSE),"") | M49: =IFERROR(VLOOKUP($E49 & "|" & H49,comparison!$A$2:$A$19,1,FALSE),"") | N49: =IFERROR(VLOOKUP($E49 & "|" & I49,comparison!$A$2:$A$19,1,FALSE),"") | O49: =IFERROR(VLOOKUP($E49 & "|" & J49,comparison!$A$2:$A$19,1,FALSE),"") | Q49: =IF(LEN(K49)>0,1,0) -> 0 | R49: =IF(LEN(L49)>0,1,0) -> 0 | S49: =IF(LEN(M49)>0,1,0) -> 0 | T49: =IF(LEN(N49)>0,1,0) -> 0 | U49: =IF(LEN(O49)>0,1,0) -> 0
B50: ACTIVE | C50: ZIE only | E50: AE115_70 | K50: =IFERROR(VLOOKUP($E50 & "|" & F50,comparison!$A$2:$A$19,1,FALSE),"") | L50: =IFERROR(VLOOKUP($E50 & "|" & G50,comparison!$A$2:$A$19,1,FALSE),"") | M50: =IFERROR(VLOOKUP($E50 & "|" & H50,comparison!$A$2:$A$19,1,FALSE),"") | N50: =IFERROR(VLOOKUP($E50 & "|" & I50,comparison!$A$2:$A$19,1,FALSE),"") | O50: =IFERROR(VLOOKUP($E50 & "|" & J50,comparison!$A$2:$A$19,1,FALSE),"") | Q50: =IF(LEN(K50)>0,1,0) -> 0 | R50: =IF(LEN(L50)>0,1,0) -> 0 | S50: =IF(LEN(M50)>0,1,0) -> 0 | T50: =IF(LEN(N50)>0,1,0) -> 0 | U50: =IF(LEN(O50)>0,1,0) -> 0
A51: New xcheck or association | B51: ACTIVE | C51: ZIE only | E51: AE200_70 | K51: =IFERROR(VLOOKUP($E51 & "|" & F51,comparison!$A$2:$A$19,1,FALSE),"") | L51: =IFERROR(VLOOKUP($E51 & "|" & G51,comparison!$A$2:$A$19,1,FALSE),"") | M51: =IFERROR(VLOOKUP($E51 & "|" & H51,comparison!$A$2:$A$19,1,FALSE),"") | N51: =IFERROR(VLOOKUP($E51 & "|" & I51,comparison!$A$2:$A$19,1,FALSE),"") | O51: =IFERROR(VLOOKUP($E51 & "|" & J51,comparison!$A$2:$A$19,1,FALSE),"") | Q51: =IF(LEN(K51)>0,1,0) -> 0 | R51: =IF(LEN(L51)>0,1,0) -> 0 | S51: =IF(LEN(M51)>0,1,0) -> 0 | T51: =IF(LEN(N51)>0,1,0) -> 0 | U51: =IF(LEN(O51)>0,1,0) -> 0
A52: New xcheck or association | B52: ACTIVE | C52: ZIE only | E52: AE201_70 | K52: =IFERROR(VLOOKUP($E52 & "|" & F52,comparison!$A$2:$A$19,1,FALSE),"") | L52: =IFERROR(VLOOKUP($E52 & "|" & G52,comparison!$A$2:$A$19,1,FALSE),"") | M52: =IFERROR(VLOOKUP($E52 & "|" & H52,comparison!$A$2:$A$19,1,FALSE),"") | N52: =IFERROR(VLOOKUP($E52 & "|" & I52,comparison!$A$2:$A$19,1,FALSE),"") | O52: =IFERROR(VLOOKUP($E52 & "|" & J52,comparison!$A$2:$A$19,1,FALSE),"") | Q52: =IF(LEN(K52)>0,1,0) -> 0 | R52: =IF(LEN(L52)>0,1,0) -> 0 | S52: =IF(LEN(M52)>0,1,0) -> 0 | T52: =IF(LEN(N52)>0,1,0) -> 0 | U52: =IF(LEN(O52)>0,1,0) -> 0
A53: New xcheck or association | B53: ACTIVE | C53: ZIE only | E53: AE202_70 | K53: =IFERROR(VLOOKUP($E53 & "|" & F53,comparison!$A$2:$A$19,1,FALSE),"") | L53: =IFERROR(VLOOKUP($E53 & "|" & G53,comparison!$A$2:$A$19,1,FALSE),"") | M53: =IFERROR(VLOOKUP($E53 & "|" & H53,comparison!$A$2:$A$19,1,FALSE),"") | N53: =IFERROR(VLOOKUP($E53 & "|" & I53,comparison!$A$2:$A$19,1,FALSE),"") | O53: =IFERROR(VLOOKUP($E53 & "|" & J53,comparison!$A$2:$A$19,1,FALSE),"") | Q53: =IF(LEN(K53)>0,1,0) -> 0 | R53: =IF(LEN(L53)>0,1,0) -> 0 | S53: =IF(LEN(M53)>0,1,0) -> 0 | T53: =IF(LEN(N53)>0,1,0) -> 0 | U53: =IF(LEN(O53)>0,1,0) -> 0
A54: New xcheck or association | B54: ACTIVE | C54: ZIE only | E54: AE208_70 | K54: =IFERROR(VLOOKUP($E54 & "|" & F54,comparison!$A$2:$A$19,1,FALSE),"") | L54: =IFERROR(VLOOKUP($E54 & "|" & G54,comparison!$A$2:$A$19,1,FALSE),"") | M54: =IFERROR(VLOOKUP($E54 & "|" & H54,comparison!$A$2:$A$19,1,FALSE),"") | N54: =IFERROR(VLOOKUP($E54 & "|" & I54,comparison!$A$2:$A$19,1,FALSE),"") | O54: =IFERROR(VLOOKUP($E54 & "|" & J54,comparison!$A$2:$A$19,1,FALSE),"") | Q54: =IF(LEN(K54)>0,1,0) -> 0 | R54: =IF(LEN(L54)>0,1,0) -> 0 | S54: =IF(LEN(M54)>0,1,0) -> 0 | T54: =IF(LEN(N54)>0,1,0) -> 0 | U54: =IF(LEN(O54)>0,1,0) -> 0
A55: New xcheck or association | B55: ACTIVE | C55: ZIE only | E55: AE210_70 | K55: =IFERROR(VLOOKUP($E55 & "|" & F55,comparison!$A$2:$A$19,1,FALSE),"") | L55: =IFERROR(VLOOKUP($E55 & "|" & G55,comparison!$A$2:$A$19,1,FALSE),"") | M55: =IFERROR(VLOOKUP($E55 & "|" & H55,comparison!$A$2:$A$19,1,FALSE),"") | N55: =IFERROR(VLOOKUP($E55 & "|" & I55,comparison!$A$2:$A$19,1,FALSE),"") | O55: =IFERROR(VLOOKUP($E55 & "|" & J55,comparison!$A$2:$A$19,1,FALSE),"") | Q55: =IF(LEN(K55)>0,1,0) -> 0 | R55: =IF(LEN(L55)>0,1,0) -> 0 | S55: =IF(LEN(M55)>0,1,0) -> 0 | T55: =IF(LEN(N55)>0,1,0) -> 0 | U55: =IF(LEN(O55)>0,1,0) -> 0
A56: New xcheck or association | B56: ACTIVE | C56: ZIE only | E56: AE212_70 | K56: =IFERROR(VLOOKUP($E56 & "|" & F56,comparison!$A$2:$A$19,1,FALSE),"") | L56: =IFERROR(VLOOKUP($E56 & "|" & G56,comparison!$A$2:$A$19,1,FALSE),"") | M56: =IFERROR(VLOOKUP($E56 & "|" & H56,comparison!$A$2:$A$19,1,FALSE),"") | N56: =IFERROR(VLOOKUP($E56 & "|" & I56,comparison!$A$2:$A$19,1,FALSE),"") | O56: =IFERROR(VLOOKUP($E56 & "|" & J56,comparison!$A$2:$A$19,1,FALSE),"") | Q56: =IF(LEN(K56)>0,1,0) -> 0 | R56: =IF(LEN(L56)>0,1,0) -> 0 | S56: =IF(LEN(M56)>0,1,0) -> 0 | T56: =IF(LEN(N56)>0,1,0) -> 0 | U56: =IF(LEN(O56)>0,1,0) -> 0
A57: New xcheck or association | B57: ACTIVE | C57: ZIE only | E57: AE214_70 | K57: =IFERROR(VLOOKUP($E57 & "|" & F57,comparison!$A$2:$A$19,1,FALSE),"") | L57: =IFERROR(VLOOKUP($E57 & "|" & G57,comparison!$A$2:$A$19,1,FALSE),"") | M57: =IFERROR(VLOOKUP($E57 & "|" & H57,comparison!$A$2:$A$19,1,FALSE),"") | N57: =IFERROR(VLOOKUP($E57 & "|" & I57,comparison!$A$2:$A$19,1,FALSE),"") | O57: =IFERROR(VLOOKUP($E57 & "|" & J57,comparison!$A$2:$A$19,1,FALSE),"") | Q57: =IF(LEN(K57)>0,1,0) -> 0 | R57: =IF(LEN(L57)>0,1,0) -> 0 | S57: =IF(LEN(M57)>0,1,0) -> 0 | T57: =IF(LEN(N57)>0,1,0) -> 0 | U57: =IF(LEN(O57)>0,1,0) -> 0
A58: Changed | B58: ACTIVE | C58: SST only check | E58: AL106_80 | K58: =IFERROR(VLOOKUP($E58 & "|" & F58,comparison!$A$2:$A$19,1,FALSE),"") | L58: =IFERROR(VLOOKUP($E58 & "|" & G58,comparison!$A$2:$A$19,1,FALSE),"") | M58: =IFERROR(VLOOKUP($E58 & "|" & H58,comparison!$A$2:$A$19,1,FALSE),"") | N58: =IFERROR(VLOOKUP($E58 & "|" & I58,comparison!$A$2:$A$19,1,FALSE),"") | O58: =IFERROR(VLOOKUP($E58 & "|" & J58,comparison!$A$2:$A$19,1,FALSE),"") | Q58: =IF(LEN(K58)>0,1,0) -> 0 | R58: =IF(LEN(L58)>0,1,0) -> 0 | S58: =IF(LEN(M58)>0,1,0) -> 0 | T58: =IF(LEN(N58)>0,1,0) -> 0 | U58: =IF(LEN(O58)>0,1,0) -> 0
A59: Changed | B59: ACTIVE | C59: Taxes | E59: AL135_00 | K59: =IFERROR(VLOOKUP($E59 & "|" & F59,comparison!$A$2:$A$19,1,FALSE),"") | L59: =IFERROR(VLOOKUP($E59 & "|" & G59,comparison!$A$2:$A$19,1,FALSE),"") | M59: =IFERROR(VLOOKUP($E59 & "|" & H59,comparison!$A$2:$A$19,1,FALSE),"") | N59: =IFERROR(VLOOKUP($E59 & "|" & I59,comparison!$A$2:$A$19,1,FALSE),"") | O59: =IFERROR(VLOOKUP($E59 & "|" & J59,comparison!$A$2:$A$19,1,FALSE),"") | Q59: =IF(LEN(K59)>0,1,0) -> 0 | R59: =IF(LEN(L59)>0,1,0) -> 0 | S59: =IF(LEN(M59)>0,1,0) -> 0 | T59: =IF(LEN(N59)>0,1,0) -> 0 | U59: =IF(LEN(O59)>0,1,0) -> 0
A60: Changed | B60: ACTIVE | C60: Taxes | E60: AL135_01 | K60: =IFERROR(VLOOKUP($E60 & "|" & F60,comparison!$A$2:$A$19,1,FALSE),"") | L60: =IFERROR(VLOOKUP($E60 & "|" & G60,comparison!$A$2:$A$19,1,FALSE),"") | M60: =IFERROR(VLOOKUP($E60 & "|" & H60,comparison!$A$2:$A$19,1,FALSE),"") | N60: =IFERROR(VLOOKUP($E60 & "|" & I60,comparison!$A$2:$A$19,1,FALSE),"") | O60: =IFERROR(VLOOKUP($E60 & "|" & J60,comparison!$A$2:$A$19,1,FALSE),"") | Q60: =IF(LEN(K60)>0,1,0) -> 0 | R60: =IF(LEN(L60)>0,1,0) -> 0 | S60: =IF(LEN(M60)>0,1,0) -> 0 | T60: =IF(LEN(N60)>0,1,0) -> 0 | U60: =IF(LEN(O60)>0,1,0) -> 0
A61: New xcheck or association | B61: ACTIVE | C61: Stammhaus / SLST | E61: AL602_60 | K61: =IFERROR(VLOOKUP($E61 & "|" & F61,comparison!$A$2:$A$19,1,FALSE),"") | L61: =IFERROR(VLOOKUP($E61 & "|" & G61,comparison!$A$2:$A$19,1,FALSE),"") | M61: =IFERROR(VLOOKUP($E61 & "|" & H61,comparison!$A$2:$A$19,1,FALSE),"") | N61: =IFERROR(VLOOKUP($E61 & "|" & I61,comparison!$A$2:$A$19,1,FALSE),"") | O61: =IFERROR(VLOOKUP($E61 & "|" & J61,comparison!$A$2:$A$19,1,FALSE),"") | Q61: =IF(LEN(K61)>0,1,0) -> 0 | R61: =IF(LEN(L61)>0,1,0) -> 0 | S61: =IF(LEN(M61)>0,1,0) -> 0 | T61: =IF(LEN(N61)>0,1,0) -> 0 | U61: =IF(LEN(O61)>0,1,0) -> 0
A62: Changed | B62: ACTIVE | C62: Shareholders' Equity | E62: AR001_00 | K62: =IFERROR(VLOOKUP($E62 & "|" & F62,comparison!$A$2:$A$19,1,FALSE),"") | L62: =IFERROR(VLOOKUP($E62 & "|" & G62,comparison!$A$2:$A$19,1,FALSE),"") | M62: =IFERROR(VLOOKUP($E62 & "|" & H62,comparison!$A$2:$A$19,1,FALSE),"") | N62: =IFERROR(VLOOKUP($E62 & "|" & I62,comparison!$A$2:$A$19,1,FALSE),"") | O62: =IFERROR(VLOOKUP($E62 & "|" & J62,comparison!$A$2:$A$19,1,FALSE),"") | Q62: =IF(LEN(K62)>0,1,0) -> 0 | R62: =IF(LEN(L62)>0,1,0) -> 0 | S62: =IF(LEN(M62)>0,1,0) -> 0 | T62: =IF(LEN(N62)>0,1,0) -> 0 | U62: =IF(LEN(O62)>0,1,0) -> 0
... A76: New xcheck or association | B76: ACTIVE | C76: Shareholders' Equity | E76: AR148_00 | K76: =IFERROR(VLOOKUP($E76 & "|" & F76,comparison!$A$2:$A$19,1,FALSE),"") | L76: =IFERROR(VLOOKUP($E76 & "|" & G76,comparison!$A$2:$A$19,1,FALSE),"") | M76: =IFERROR(VLOOKUP($E76 & "|" & H76,comparison!$A$2:$A$19,1,FALSE),"") | N76: =IFERROR(VLOOKUP($E76 & "|" & I76,comparison!$A$2:$A$19,1,FALSE),"") | O76: =IFERROR(VLOOKUP($E76 & "|" & J76,comparison!$A$2:$A$19,1,FALSE),"") | Q76: =IF(LEN(K76)>0,1,0) -> 0 | R76: =IF(LEN(L76)>0,1,0) -> 0 | S76: =IF(LEN(M76)>0,1,0) -> 0 | T76: =IF(LEN(N76)>0,1,0) -> 0 | U76: =IF(LEN(O76)>0,1,0) -> 0
B77: ACTIVE | C77: Shareholders' Equity | E77: AR148_00 | K77: =IFERROR(VLOOKUP($E77 & "|" & F77,comparison!$A$2:$A$19,1,FALSE),"") | L77: =IFERROR(VLOOKUP($E77 & "|" & G77,comparison!$A$2:$A$19,1,FALSE),"") | M77: =IFERROR(VLOOKUP($E77 & "|" & H77,comparison!$A$2:$A$19,1,FALSE),"") | N77: =IFERROR(VLOOKUP($E77 & "|" & I77,comparison!$A$2:$A$19,1,FALSE),"") | O77: =IFERROR(VLOOKUP($E77 & "|" & J77,comparison!$A$2:$A$19,1,FALSE),"") | Q77: =IF(LEN(K77)>0,1,0) -> 0 | R77: =IF(LEN(L77)>0,1,0) -> 0 | S77: =IF(LEN(M77)>0,1,0) -> 0 | T77: =IF(LEN(N77)>0,1,0) -> 0 | U77: =IF(LEN(O77)>0,1,0) -> 0
A78: New xcheck or association | B78: ACTIVE | C78: ZIE only | E78: AR205_70 | K78: =IFERROR(VLOOKUP($E78 & "|" & F78,comparison!$A$2:$A$19,1,FALSE),"") | L78: =IFERROR(VLOOKUP($E78 & "|" & G78,comparison!$A$2:$A$19,1,FALSE),"") | M78: =IFERROR(VLOOKUP($E78 & "|" & H78,comparison!$A$2:$A$19,1,FALSE),"") | N78: =IFERROR(VLOOKUP($E78 & "|" & I78,comparison!$A$2:$A$19,1,FALSE),"") | O78: =IFERROR(VLOOKUP($E78 & "|" & J78,comparison!$A$2:$A$19,1,FALSE),"") | Q78: =IF(LEN(K78)>0,1,0) -> 0 | R78: =IF(LEN(L78)>0,1,0) -> 0 | S78: =IF(LEN(M78)>0,1,0) -> 0 | T78: =IF(LEN(N78)>0,1,0) -> 0 | U78: =IF(LEN(O78)>0,1,0) -> 0
A79: New xcheck or association | B79: ACTIVE | C79: ZIE only | E79: AR206_70 | K79: =IFERROR(VLOOKUP($E79 & "|" & F79,comparison!$A$2:$A$19,1,FALSE),"") | L79: =IFERROR(VLOOKUP($E79 & "|" & G79,comparison!$A$2:$A$19,1,FALSE),"") | M79: =IFERROR(VLOOKUP($E79 & "|" & H79,comparison!$A$2:$A$19,1,FALSE),"") | N79: =IFERROR(VLOOKUP($E79 & "|" & I79,comparison!$A$2:$A$19,1,FALSE),"") | O79: =IFERROR(VLOOKUP($E79 & "|" & J79,comparison!$A$2:$A$19,1,FALSE),"") | Q79: =IF(LEN(K79)>0,1,0) -> 0 | R79: =IF(LEN(L79)>0,1,0) -> 0 | S79: =IF(LEN(M79)>0,1,0) -> 0 | T79: =IF(LEN(N79)>0,1,0) -> 0 | U79: =IF(LEN(O79)>0,1,0) -> 0
A80: New xcheck or association | B80: ACTIVE | C80: ZIE only | E80: AR207_70 | K80: =IFERROR(VLOOKUP($E80 & "|" & F80,comparison!$A$2:$A$19,1,FALSE),"") | L80: =IFERROR(VLOOKUP($E80 & "|" & G80,comparison!$A$2:$A$19,1,FALSE),"") | M80: =IFERROR(VLOOKUP($E80 & "|" & H80,comparison!$A$2:$A$19,1,FALSE),"") | N80: =IFERROR(VLOOKUP($E80 & "|" & I80,comparison!$A$2:$A$19,1,FALSE),"") | O80: =IFERROR(VLOOKUP($E80 & "|" & J80,comparison!$A$2:$A$19,1,FALSE),"") | Q80: =IF(LEN(K80)>0,1,0) -> 0 | R80: =IF(LEN(L80)>0,1,0) -> 0 | S80: =IF(LEN(M80)>0,1,0) -> 0 | T80: =IF(LEN(N80)>0,1,0) -> 0 | U80: =IF(LEN(O80)>0,1,0) -> 0
A81: New xcheck or association | B81: ACTIVE | C81: ZIE only | E81: AR209_70 | K81: =IFERROR(VLOOKUP($E81 & "|" & F81,comparison!$A$2:$A$19,1,FALSE),"") | L81: =IFERROR(VLOOKUP($E81 & "|" & G81,comparison!$A$2:$A$19,1,FALSE),"") | M81: =IFERROR(VLOOKUP($E81 & "|" & H81,comparison!$A$2:$A$19,1,FALSE),"") | N81: =IFERROR(VLOOKUP($E81 & "|" & I81,comparison!$A$2:$A$19,1,FALSE),"") | O81: =IFERROR(VLOOKUP($E81 & "|" & J81,comparison!$A$2:$A$19,1,FALSE),"") | Q81: =IF(LEN(K81)>0,1,0) -> 0 | R81: =IF(LEN(L81)>0,1,0) -> 0 | S81: =IF(LEN(M81)>0,1,0) -> 0 | T81: =IF(LEN(N81)>0,1,0) -> 0 | U81: =IF(LEN(O81)>0,1,0) -> 0
A82: New xcheck or association | B82: ACTIVE | C82: ZIE only | E82: AR211_70 | K82: =IFERROR(VLOOKUP($E82 & "|" & F82,comparison!$A$2:$A$19,1,FALSE),"") | L82: =IFERROR(VLOOKUP($E82 & "|" & G82,comparison!$A$2:$A$19,1,FALSE),"") | M82: =IFERROR(VLOOKUP($E82 & "|" & H82,comparison!$A$2:$A$19,1,FALSE),"") | N82: =IFERROR(VLOOKUP($E82 & "|" & I82,comparison!$A$2:$A$19,1,FALSE),"") | O82: =IFERROR(VLOOKUP($E82 & "|" & J82,comparison!$A$2:$A$19,1,FALSE),"") | Q82: =IF(LEN(K82)>0,1,0) -> 0 | R82: =IF(LEN(L82)>0,1,0) -> 0 | S82: =IF(LEN(M82)>0,1,0) -> 0 | T82: =IF(LEN(N82)>0,1,0) -> 0 | U82: =IF(LEN(O82)>0,1,0) -> 0
A83: New xcheck or association | B83: ACTIVE | C83: ZIE only | E83: AR213_70 | K83: =IFERROR(VLOOKUP($E83 & "|" & F83,comparison!$A$2:$A$19,1,FALSE),"") | L83: =IFERROR(VLOOKUP($E83 & "|" & G83,comparison!$A$2:$A$19,1,FALSE),"") | M83: =IFERROR(VLOOKUP($E83 & "|" & H83,comparison!$A$2:$A$19,1,FALSE),"") | N83: =IFERROR(VLOOKUP($E83 & "|" & I83,comparison!$A$2:$A$19,1,FALSE),"") | O83: =IFERROR(VLOOKUP($E83 & "|" & J83,comparison!$A$2:$A$19,1,FALSE),"") | Q83: =IF(LEN(K83)>0,1,0) -> 0 | R83: =IF(LEN(L83)>0,1,0) -> 0 | S83: =IF(LEN(M83)>0,1,0) -> 0 | T83: =IF(LEN(N83)>0,1,0) -> 0 | U83: =IF(LEN(O83)>0,1,0) -> 0
A84: New xcheck or association | B84: ACTIVE | C84: ZIE only | E84: AR215_70 | K84: =IFERROR(VLOOKUP($E84 & "|" & F84,comparison!$A$2:$A$19,1,FALSE),"") | L84: =IFERROR(VLOOKUP($E84 & "|" & G84,comparison!$A$2:$A$19,1,FALSE),"") | M84: =IFERROR(VLOOKUP($E84 & "|" & H84,comparison!$A$2:$A$19,1,FALSE),"") | N84: =IFERROR(VLOOKUP($E84 & "|" & I84,comparison!$A$2:$A$19,1,FALSE),"") | O84: =IFERROR(VLOOKUP($E84 & "|" & J84,comparison!$A$2:$A$19,1,FALSE),"") | Q84: =IF(LEN(K84)>0,1,0) -> 0 | R84: =IF(LEN(L84)>0,1,0) -> 0 | S84: =IF(LEN(M84)>0,1,0) -> 0 | T84: =IF(LEN(N84)>0,1,0) -> 0 | U84: =IF(LEN(O84)>0,1,0) -> 0
A85: Changed | B85: ACTIVE | C85: IFRS 17 - BBA LRC CSM | E85: AS004_17 | G85: CON_Q3_Q4 | K85: =IFERROR(VLOOKUP($E85 & "|" & F85,comparison!$A$2:$A$19,1,FALSE),"") | L85: =IFERROR(VLOOKUP($E85 & "|" & G85,comparison!$A$2:$A$19,1,FALSE),"") -> AS004_17|CON_Q3_Q4 | M85: =IFERROR(VLOOKUP($E85 & "|" & H85,comparison!$A$2:$A$19,1,FALSE),"") | N85: =IFERROR(VLOOKUP($E85 & "|" & I85,comparison!$A$2:$A$19,1,FALSE),"") | O85: =IFERROR(VLOOKUP($E85 & "|" & J85,comparison!$A$2:$A$19,1,FALSE),"") | Q85: =IF(LEN(K85)>0,1,0) -> 0 | R85: =IF(LEN(L85)>0,1,0) -> 1 | S85: =IF(LEN(M85)>0,1,0) -> 0 | T85: =IF(LEN(N85)>0,1,0) -> 0 | U85: =IF(LEN(O85)>0,1,0) -> 0
A86: Changed | B86: ACTIVE | C86: Taxes | E86: AS057_00 | K86: =IFERROR(VLOOKUP($E86 & "|" & F86,comparison!$A$2:$A$19,1,FALSE),"") | L86: =IFERROR(VLOOKUP($E86 & "|" & G86,comparison!$A$2:$A$19,1,FALSE),"") | M86: =IFERROR(VLOOKUP($E86 & "|" & H86,comparison!$A$2:$A$19,1,FALSE),"") | N86: =IFERROR(VLOOKUP($E86 & "|" & I86,comparison!$A$2:$A$19,1,FALSE),"") | O86: =IFERROR(VLOOKUP($E86 & "|" & J86,comparison!$A$2:$A$19,1,FALSE),"") | Q86: =IF(LEN(K86)>0,1,0) -> 0 | R86: =IF(LEN(L86)>0,1,0) -> 0 | S86: =IF(LEN(M86)>0,1,0) -> 0 | T86: =IF(LEN(N86)>0,1,0) -> 0 | U86: =IF(LEN(O86)>0,1,0) -> 0
A87: Changed | B87: ACTIVE | C87: Taxes | E87: AS064_00 | K87: =IFERROR(VLOOKUP($E87 & "|" & F87,comparison!$A$2:$A$19,1,FALSE),"") | L87: =IFERROR(VLOOKUP($E87 & "|" & G87,comparison!$A$2:$A$19,1,FALSE),"") | M87: =IFERROR(VLOOKUP($E87 & "|" & H87,comparison!$A$2:$A$19,1,FALSE),"") | N87: =IFERROR(VLOOKUP($E87 & "|" & I87,comparison!$A$2:$A$19,1,FALSE),"") | O87: =IFERROR(VLOOKUP($E87 & "|" & J87,comparison!$A$2:$A$19,1,FALSE),"") | Q87: =IF(LEN(K87)>0,1,0) -> 0 | R87: =IF(LEN(L87)>0,1,0) -> 0 | S87: =IF(LEN(M87)>0,1,0) -> 0 | T87: =IF(LEN(N87)>0,1,0) -> 0 | U87: =IF(LEN(O87)>0,1,0) -> 0
A88: Changed | B88: ACTIVE | C88: IFRS 13 - level 1,2,3 | E88: AS130_00 | G88: CON_Q2_Q4 | K88: =IFERROR(VLOOKUP($E88 & "|" & F88,comparison!$A$2:$A$19,1,FALSE),"") | L88: =IFERROR(VLOOKUP($E88 & "|" & G88,comparison!$A$2:$A$19,1,FALSE),"") | M88: =IFERROR(VLOOKUP($E88 & "|" & H88,comparison!$A$2:$A$19,1,FALSE),"") | N88: =IFERROR(VLOOKUP($E88 & "|" & I88,comparison!$A$2:$A$19,1,FALSE),"") | O88: =IFERROR(VLOOKUP($E88 & "|" & J88,comparison!$A$2:$A$19,1,FALSE),"") | Q88: =IF(LEN(K88)>0,1,0) -> 0 | R88: =IF(LEN(L88)>0,1,0) -> 0 | S88: =IF(LEN(M88)>0,1,0) -> 0 | T88: =IF(LEN(N88)>0,1,0) -> 0 | U88: =IF(LEN(O88)>0,1,0) -> 0
A89: Changed | B89: ACTIVE | C89: IFRS 13 - level 1,2,3 | E89: AS132_00 | G89: CON_Q2_Q4 | K89: =IFERROR(VLOOKUP($E89 & "|" & F89,comparison!$A$2:$A$19,1,FALSE),"") | L89: =IFERROR(VLOOKUP($E89 & "|" & G89,comparison!$A$2:$A$19,1,FALSE),"") | M89: =IFERROR(VLOOKUP($E89 & "|" & H89,comparison!$A$2:$A$19,1,FALSE),"") | N89: =IFERROR(VLOOKUP($E89 & "|" & I89,comparison!$A$2:$A$19,1,FALSE),"") | O89: =IFERROR(VLOOKUP($E89 & "|" & J89,comparison!$A$2:$A$19,1,FALSE),"") | Q89: =IF(LEN(K89)>0,1,0) -> 0 | R89: =IF(LEN(L89)>0,1,0) -> 0 | S89: =IF(LEN(M89)>0,1,0) -> 0 | T89: =IF(LEN(N89)>0,1,0) -> 0 | U89: =IF(LEN(O89)>0,1,0) -> 0
A90: Changed | B90: ACTIVE | C90: IFRS 13 - level 1,2,3 | E90: AS133_00 | G90: CON_Q4 | K90: =IFERROR(VLOOKUP($E90 & "|" & F90,comparison!$A$2:$A$19,1,FALSE),"") | L90: =IFERROR(VLOOKUP($E90 & "|" & G90,comparison!$A$2:$A$19,1,FALSE),"") -> AS133_00|CON_Q4 | M90: =IFERROR(VLOOKUP($E90 & "|" & H90,comparison!$A$2:$A$19,1,FALSE),"") | N90: =IFERROR(VLOOKUP($E90 & "|" & I90,comparison!$A$2:$A$19,1,FALSE),"") | O90: =IFERROR(VLOOKUP($E90 & "|" & J90,comparison!$A$2:$A$19,1,FALSE),"") | Q90: =IF(LEN(K90)>0,1,0) -> 0 | R90: =IF(LEN(L90)>0,1,0) -> 1 | S90: =IF(LEN(M90)>0,1,0) -> 0 | T90: =IF(LEN(N90)>0,1,0) -> 0 | U90: =IF(LEN(O90)>0,1,0) -> 0
A91: Changed | B91: ACTIVE | C91: IFRS 13 - level 1,2,3 | E91: AS134_00 | G91: CON_Q2_Q4 | K91: =IFERROR(VLOOKUP($E91 & "|" & F91,comparison!$A$2:$A$19,1,FALSE),"") | L91: =IFERROR(VLOOKUP($E91 & "|" & G91,comparison!$A$2:$A$19,1,FALSE),"") | M91: =IFERROR(VLOOKUP($E91 & "|" & H91,comparison!$A$2:$A$19,1,FALSE),"") | N91: =IFERROR(VLOOKUP($E91 & "|" & I91,comparison!$A$2:$A$19,1,FALSE),"") | O91: =IFERROR(VLOOKUP($E91 & "|" & J91,comparison!$A$2:$A$19,1,FALSE),"") | Q91: =IF(LEN(K91)>0,1,0) -> 0 | R91: =IF(LEN(L91)>0,1,0) -> 0 | S91: =IF(LEN(M91)>0,1,0) -> 0 | T91: =IF(LEN(N91)>0,1,0) -> 0 | U91: =IF(LEN(O91)>0,1,0) -> 0
A92: Changed | B92: ACTIVE | C92: IFRS 13 - level 1,2,3 | E92: AS135_00 | G92: CON_Q2_Q4 | K92: =IFERROR(VLOOKUP($E92 & "|" & F92,comparison!$A$2:$A$19,1,FALSE),"") | L92: =IFERROR(VLOOKUP($E92 & "|" & G92,comparison!$A$2:$A$19,1,FALSE),"") | M92: =IFERROR(VLOOKUP($E92 & "|" & H92,comparison!$A$2:$A$19,1,FALSE),"") | N92: =IFERROR(VLOOKUP($E92 & "|" & I92,comparison!$A$2:$A$19,1,FALSE),"") | O92: =IFERROR(VLOOKUP($E92 & "|" & J92,comparison!$A$2:$A$19,1,FALSE),"") | Q92: =IF(LEN(K92)>0,1,0) -> 0 | R92: =IF(LEN(L92)>0,1,0) -> 0 | S92: =IF(LEN(M92)>0,1,0) -> 0 | T92: =IF(LEN(N92)>0,1,0) -> 0 | U92: =IF(LEN(O92)>0,1,0) -> 0
A93: Changed | B93: ACTIVE | C93: IFRS 13 - level 1,2,3 | E93: AS136_00 | G93: CON_Q2_Q4 | K93: =IFERROR(VLOOKUP($E93 & "|" & F93,comparison!$A$2:$A$19,1,FALSE),"") | L93: =IFERROR(VLOOKUP($E93 & "|" & G93,comparison!$A$2:$A$19,1,FALSE),"") | M93: =IFERROR(VLOOKUP($E93 & "|" & H93,comparison!$A$2:$A$19,1,FALSE),"") | N93: =IFERROR(VLOOKUP($E93 & "|" & I93,comparison!$A$2:$A$19,1,FALSE),"") | O93: =IFERROR(VLOOKUP($E93 & "|" & J93,comparison!$A$2:$A$19,1,FALSE),"") | Q93: =IF(LEN(K93)>0,1,0) -> 0 | R93: =IF(LEN(L93)>0,1,0) -> 0 | S93: =IF(LEN(M93)>0,1,0) -> 0 | T93: =IF(LEN(N93)>0,1,0) -> 0 | U93: =IF(LEN(O93)>0,1,0) -> 0
A94: Changed | B94: ACTIVE | C94: IFRS 13 - level 1,2,3 | E94: AS137_00 | G94: CON_Q4 | K94: =IFERROR(VLOOKUP($E94 & "|" & F94,comparison!$A$2:$A$19,1,FALSE),"") | L94: =IFERROR(VLOOKUP($E94 & "|" & G94,comparison!$A$2:$A$19,1,FALSE),"") -> AS137_00|CON_Q4 | M94: =IFERROR(VLOOKUP($E94 & "|" & H94,comparison!$A$2:$A$19,1,FALSE),"") | N94: =IFERROR(VLOOKUP($E94 & "|" & I94,comparison!$A$2:$A$19,1,FALSE),"") | O94: =IFERROR(VLOOKUP($E94 & "|" & J94,comparison!$A$2:$A$19,1,FALSE),"") | Q94: =IF(LEN(K94)>0,1,0) -> 0 | R94: =IF(LEN(L94)>0,1,0) -> 1 | S94: =IF(LEN(M94)>0,1,0) -> 0 | T94: =IF(LEN(N94)>0,1,0) -> 0 | U94: =IF(LEN(O94)>0,1,0) -> 0
A95: Changed | B95: ACTIVE | C95: IFRS 13 - level 1,2,3 | E95: AS138_00 | G95: CON_Q2_Q4 | K95: =IFERROR(VLOOKUP($E95 & "|" & F95,comparison!$A$2:$A$19,1,FALSE),"") | L95: =IFERROR(VLOOKUP($E95 & "|" & G95,comparison!$A$2:$A$19,1,FALSE),"") | M95: =IFERROR(VLOOKUP($E95 & "|" & H95,comparison!$A$2:$A$19,1,FALSE),"") | N95: =IFERROR(VLOOKUP($E95 & "|" & I95,comparison!$A$2:$A$19,1,FALSE),"") | O95: =IFERROR(VLOOKUP($E95 & "|" & J95,comparison!$A$2:$A$19,1,FALSE),"") | Q95: =IF(LEN(K95)>0,1,0) -> 0 | R95: =IF(LEN(L95)>0,1,0) -> 0 | S95: =IF(LEN(M95)>0,1,0) -> 0 | T95: =IF(LEN(N95)>0,1,0) -> 0 | U95: =IF(LEN(O95)>0,1,0) -> 0
A96: Changed | B96: ACTIVE | C96: IFRS 13 - level 1,2,3 | E96: AS139_00 | G96: CON_Q4 | K96: =IFERROR(VLOOKUP($E96 & "|" & F96,comparison!$A$2:$A$19,1,FALSE),"") | L96: =IFERROR(VLOOKUP($E96 & "|" & G96,comparison!$A$2:$A$19,1,FALSE),"") -> AS139_00|CON_Q4 | M96: =IFERROR(VLOOKUP($E96 & "|" & H96,comparison!$A$2:$A$19,1,FALSE),"") | N96: =IFERROR(VLOOKUP($E96 & "|" & I96,comparison!$A$2:$A$19,1,FALSE),"") | O96: =IFERROR(VLOOKUP($E96 & "|" & J96,comparison!$A$2:$A$19,1,FALSE),"") | Q96: =IF(LEN(K96)>0,1,0) -> 0 | R96: =IF(LEN(L96)>0,1,0) -> 1 | S96: =IF(LEN(M96)>0,1,0) -> 0 | T96: =IF(LEN(N96)>0,1,0) -> 0 | U96: =IF(LEN(O96)>0,1,0) -> 0
A97: Changed | B97: ACTIVE | C97: IFRS 13 - level 1,2,3 | E97: AS142_00 | G97: CON_Q4 | K97: =IFERROR(VLOOKUP($E97 & "|" & F97,comparison!$A$2:$A$19,1,FALSE),"") | L97: =IFERROR(VLOOKUP($E97 & "|" & G97,comparison!$A$2:$A$19,1,FALSE),"") -> AS142_00|CON_Q4 | M97: =IFERROR(VLOOKUP($E97 & "|" & H97,comparison!$A$2:$A$19,1,FALSE),"") | N97: =IFERROR(VLOOKUP($E97 & "|" & I97,comparison!$A$2:$A$19,1,FALSE),"") | O97: =IFERROR(VLOOKUP($E97 & "|" & J97,comparison!$A$2:$A$19,1,FALSE),"") | Q97: =IF(LEN(K97)>0,1,0) -> 0 | R97: =IF(LEN(L97)>0,1,0) -> 1 | S97: =IF(LEN(M97)>0,1,0) -> 0 | T97: =IF(LEN(N97)>0,1,0) -> 0 | U97: =IF(LEN(O97)>0,1,0) -> 0
A98: Changed | B98: ACTIVE | C98: IFRS 13 - level 1,2,3 | E98: AS167_00 | G98: CON_Q2_Q4 | K98: =IFERROR(VLOOKUP($E98 & "|" & F98,comparison!$A$2:$A$19,1,FALSE),"") | L98: =IFERROR(VLOOKUP($E98 & "|" & G98,comparison!$A$2:$A$19,1,FALSE),"") | M98: =IFERROR(VLOOKUP($E98 & "|" & H98,comparison!$A$2:$A$19,1,FALSE),"") | N98: =IFERROR(VLOOKUP($E98 & "|" & I98,comparison!$A$2:$A$19,1,FALSE),"") | O98: =IFERROR(VLOOKUP($E98 & "|" & J98,comparison!$A$2:$A$19,1,FALSE),"") | Q98: =IF(LEN(K98)>0,1,0) -> 0 | R98: =IF(LEN(L98)>0,1,0) -> 0 | S98: =IF(LEN(M98)>0,1,0) -> 0 | T98: =IF(LEN(N98)>0,1,0) -> 0 | U98: =IF(LEN(O98)>0,1,0) -> 0
A99: Changed | B99: ACTIVE | C99: IFRS 13 - level 1,2,3 | E99: AS168_00 | G99: CON_Q4 | K99: =IFERROR(VLOOKUP($E99 & "|" & F99,comparison!$A$2:$A$19,1,FALSE),"") | L99: =IFERROR(VLOOKUP($E99 & "|" & G99,comparison!$A$2:$A$19,1,FALSE),"") -> AS168_00|CON_Q4 | M99: =IFERROR(VLOOKUP($E99 & "|" & H99,comparison!$A$2:$A$19,1,FALSE),"") | N99: =IFERROR(VLOOKUP($E99 & "|" & I99,comparison!$A$2:$A$19,1,FALSE),"") | O99: =IFERROR(VLOOKUP($E99 & "|" & J99,comparison!$A$2:$A$19,1,FALSE),"") | Q99: =IF(LEN(K99)>0,1,0) -> 0 | R99: =IF(LEN(L99)>0,1,0) -> 1 | S99: =IF(LEN(M99)>0,1,0) -> 0 | T99: =IF(LEN(N99)>0,1,0) -> 0 | U99: =IF(LEN(O99)>0,1,0) -> 0
A100: Changed | B100: ACTIVE | C100: Taxes | E100: AS195_00 | K100: =IFERROR(VLOOKUP($E100 & "|" & F100,comparison!$A$2:$A$19,1,FALSE),"") | L100: =IFERROR(VLOOKUP($E100 & "|" & G100,comparison!$A$2:$A$19,1,FALSE),"") | M100: =IFERROR(VLOOKUP($E100 & "|" & H100,comparison!$A$2:$A$19,1,FALSE),"") | N100: =IFERROR(VLOOKUP($E100 & "|" & I100,comparison!$A$2:$A$19,1,FALSE),"") | O100: =IFERROR(VLOOKUP($E100 & "|" & J100,comparison!$A$2:$A$19,1,FALSE),"") | Q100: =IF(LEN(K100)>0,1,0) -> 0 | R100: =IF(LEN(L100)>0,1,0) -> 0 | S100: =IF(LEN(M100)>0,1,0) -> 0 | T100: =IF(LEN(N100)>0,1,0) -> 0 | U100: =IF(LEN(O100)>0,1,0) -> 0
A101: Changed | B101: ACTIVE | C101: SST only check | E101: AS802_00 | K101: =IFERROR(VLOOKUP($E101 & "|" & F101,comparison!$A$2:$A$19,1,FALSE),"") | L101: =IFERROR(VLOOKUP($E101 & "|" & G101,comparison!$A$2:$A$19,1,FALSE),"") | M101: =IFERROR(VLOOKUP($E101 & "|" & H101,comparison!$A$2:$A$19,1,FALSE),"") | N101: =IFERROR(VLOOKUP($E101 & "|" & I101,comparison!$A$2:$A$19,1,FALSE),"") | O101: =IFERROR(VLOOKUP($E101 & "|" & J101,comparison!$A$2:$A$19,1,FALSE),"") | Q101: =IF(LEN(K101)>0,1,0) -> 0 | R101: =IF(LEN(L101)>0,1,0) -> 0 | S101: =IF(LEN(M101)>0,1,0) -> 0 | T101: =IF(LEN(N101)>0,1,0) -> 0 | U101: =IF(LEN(O101)>0,1,0) -> 0
A102: Changed | B102: ACTIVE | C102: SST only check | E102: AS803_00 | K102: =IFERROR(VLOOKUP($E102 & "|" & F102,comparison!$A$2:$A$19,1,FALSE),"") | L102: =IFERROR(VLOOKUP($E102 & "|" & G102,comparison!$A$2:$A$19,1,FALSE),"") | M102: =IFERROR(VLOOKUP($E102 & "|" & H102,comparison!$A$2:$A$19,1,FALSE),"") | N102: =IFERROR(VLOOKUP($E102 & "|" & I102,comparison!$A$2:$A$19,1,FALSE),"") | O102: =IFERROR(VLOOKUP($E102 & "|" & J102,comparison!$A$2:$A$19,1,FALSE),"") | Q102: =IF(LEN(K102)>0,1,0) -> 0 | R102: =IF(LEN(L102)>0,1,0) -> 0 | S102: =IF(LEN(M102)>0,1,0) -> 0 | T102: =IF(LEN(N102)>0,1,0) -> 0 | U102: =IF(LEN(O102)>0,1,0) -> 0
A103: Changed | B103: ACTIVE | C103: SST only check | E103: AS804_00 | K103: =IFERROR(VLOOKUP($E103 & "|" & F103,comparison!$A$2:$A$19,1,FALSE),"") | L103: =IFERROR(VLOOKUP($E103 & "|" & G103,comparison!$A$2:$A$19,1,FALSE),"") | M103: =IFERROR(VLOOKUP($E103 & "|" & H103,comparison!$A$2:$A$19,1,FALSE),"") | N103: =IFERROR(VLOOKUP($E103 & "|" & I103,comparison!$A$2:$A$19,1,FALSE),"") | O103: =IFERROR(VLOOKUP($E103 & "|" & J103,comparison!$A$2:$A$19,1,FALSE),"") | Q103: =IF(LEN(K103)>0,1,0) -> 0 | R103: =IF(LEN(L103)>0,1,0) -> 0 | S103: =IF(LEN(M103)>0,1,0) -> 0 | T103: =IF(LEN(N103)>0,1,0) -> 0 | U103: =IF(LEN(O103)>0,1,0) -> 0
A104: Changed | B104: ACTIVE | C104: SST only check | E104: AS809_00 | K104: =IFERROR(VLOOKUP($E104 & "|" & F104,comparison!$A$2:$A$19,1,FALSE),"") | L104: =IFERROR(VLOOKUP($E104 & "|" & G104,comparison!$A$2:$A$19,1,FALSE),"") | M104: =IFERROR(VLOOKUP($E104 & "|" & H104,comparison!$A$2:$A$19,1,FALSE),"") | N104: =IFERROR(VLOOKUP($E104 & "|" & I104,comparison!$A$2:$A$19,1,FALSE),"") | O104: =IFERROR(VLOOKUP($E104 & "|" & J104,comparison!$A$2:$A$19,1,FALSE),"") | Q104: =IF(LEN(K104)>0,1,0) -> 0 | R104: =IF(LEN(L104)>0,1,0) -> 0 | S104: =IF(LEN(M104)>0,1,0) -> 0 | T104: =IF(LEN(N104)>0,1,0) -> 0 | U104: =IF(LEN(O104)>0,1,0) -> 0
A105: Changed | B105: ACTIVE | C105: SST only check | E105: AS810_00 | K105: =IFERROR(VLOOKUP($E105 & "|" & F105,comparison!$A$2:$A$19,1,FALSE),"") | L105: =IFERROR(VLOOKUP($E105 & "|" & G105,comparison!$A$2:$A$19,1,FALSE),"") | M105: =IFERROR(VLOOKUP($E105 & "|" & H105,comparison!$A$2:$A$19,1,FALSE),"") | N105: =IFERROR(VLOOKUP($E105 & "|" & I105,comparison!$A$2:$A$19,1,FALSE),"") | O105: =IFERROR(VLOOKUP($E105 & "|" & J105,comparison!$A$2:$A$19,1,FALSE),"") | Q105: =IF(LEN(K105)>0,1,0) -> 0 | R105: =IF(LEN(L105)>0,1,0) -> 0 | S105: =IF(LEN(M105)>0,1,0) -> 0 | T105: =IF(LEN(N105)>0,1,0) -> 0 | U105: =IF(LEN(O105)>0,1,0) -> 0
A106: Changed | B106: ACTIVE | C106: SST only check | E106: AS811_00 | K106: =IFERROR(VLOOKUP($E106 & "|" & F106,comparison!$A$2:$A$19,1,FALSE),"") | L106: =IFERROR(VLOOKUP($E106 & "|" & G106,comparison!$A$2:$A$19,1,FALSE),"") | M106: =IFERROR(VLOOKUP($E106 & "|" & H106,comparison!$A$2:$A$19,1,FALSE),"") | N106: =IFERROR(VLOOKUP($E106 & "|" & I106,comparison!$A$2:$A$19,1,FALSE),"") | O106: =IFERROR(VLOOKUP($E106 & "|" & J106,comparison!$A$2:$A$19,1,FALSE),"") | Q106: =IF(LEN(K106)>0,1,0) -> 0 | R106: =IF(LEN(L106)>0,1,0) -> 0 | S106: =IF(LEN(M106)>0,1,0) -> 0 | T106: =IF(LEN(N106)>0,1,0) -> 0 | U106: =IF(LEN(O106)>0,1,0) -> 0
A107: Changed | B107: ACTIVE | C107: Other Expenses | E107: E026_00 | K107: =IFERROR(VLOOKUP($E107 & "|" & F107,comparison!$A$2:$A$19,1,FALSE),"") | L107: =IFERROR(VLOOKUP($E107 & "|" & G107,comparison!$A$2:$A$19,1,FALSE),"") | M107: =IFERROR(VLOOKUP($E107 & "|" & H107,comparison!$A$2:$A$19,1,FALSE),"") | N107: =IFERROR(VLOOKUP($E107 & "|" & I107,comparison!$A$2:$A$19,1,FALSE),"") | O107: =IFERROR(VLOOKUP($E107 & "|" & J107,comparison!$A$2:$A$19,1,FALSE),"") | Q107: =IF(LEN(K107)>0,1,0) -> 0 | R107: =IF(LEN(L107)>0,1,0) -> 0 | S107: =IF(LEN(M107)>0,1,0) -> 0 | T107: =IF(LEN(N107)>0,1,0) -> 0 | U107: =IF(LEN(O107)>0,1,0) -> 0
A108: Changed | B108: ACTIVE | C108: Other Expenses | E108: E039_17 | K108: =IFERROR(VLOOKUP($E108 & "|" & F108,comparison!$A$2:$A$19,1,FALSE),"") | L108: =IFERROR(VLOOKUP($E108 & "|" & G108,comparison!$A$2:$A$19,1,FALSE),"") | M108: =IFERROR(VLOOKUP($E108 & "|" & H108,comparison!$A$2:$A$19,1,FALSE),"") | N108: =IFERROR(VLOOKUP($E108 & "|" & I108,comparison!$A$2:$A$19,1,FALSE),"") | O108: =IFERROR(VLOOKUP($E108 & "|" & J108,comparison!$A$2:$A$19,1,FALSE),"") | Q108: =IF(LEN(K108)>0,1,0) -> 0 | R108: =IF(LEN(L108)>0,1,0) -> 0 | S108: =IF(LEN(M108)>0,1,0) -> 0 | T108: =IF(LEN(N108)>0,1,0) -> 0 | U108: =IF(LEN(O108)>0,1,0) -> 0
A109: Changed | B109: ACTIVE | C109: Other Expenses | E109: E040_00 | K109: =IFERROR(VLOOKUP($E109 & "|" & F109,comparison!$A$2:$A$19,1,FALSE),"") | L109: =IFERROR(VLOOKUP($E109 & "|" & G109,comparison!$A$2:$A$19,1,FALSE),"") | M109: =IFERROR(VLOOKUP($E109 & "|" & H109,comparison!$A$2:$A$19,1,FALSE),"") | N109: =IFERROR(VLOOKUP($E109 & "|" & I109,comparison!$A$2:$A$19,1,FALSE),"") | O109: =IFERROR(VLOOKUP($E109 & "|" & J109,comparison!$A$2:$A$19,1,FALSE),"") | Q109: =IF(LEN(K109)>0,1,0) -> 0 | R109: =IF(LEN(L109)>0,1,0) -> 0 | S109: =IF(LEN(M109)>0,1,0) -> 0 | T109: =IF(LEN(N109)>0,1,0) -> 0 | U109: =IF(LEN(O109)>0,1,0) -> 0
A110: Changed | B110: ACTIVE | C110: Other Expenses | E110: E051_00 | K110: =IFERROR(VLOOKUP($E110 & "|" & F110,comparison!$A$2:$A$19,1,FALSE),"") | L110: =IFERROR(VLOOKUP($E110 & "|" & G110,comparison!$A$2:$A$19,1,FALSE),"") | M110: =IFERROR(VLOOKUP($E110 & "|" & H110,comparison!$A$2:$A$19,1,FALSE),"") | N110: =IFERROR(VLOOKUP($E110 & "|" & I110,comparison!$A$2:$A$19,1,FALSE),"") | O110: =IFERROR(VLOOKUP($E110 & "|" & J110,comparison!$A$2:$A$19,1,FALSE),"") | Q110: =IF(LEN(K110)>0,1,0) -> 0 | R110: =IF(LEN(L110)>0,1,0) -> 0 | S110: =IF(LEN(M110)>0,1,0) -> 0 | T110: =IF(LEN(N110)>0,1,0) -> 0 | U110: =IF(LEN(O110)>0,1,0) -> 0
A111: Changed | B111: ACTIVE | C111: Other Expenses | E111: E052_00 | K111: =IFERROR(VLOOKUP($E111 & "|" & F111,comparison!$A$2:$A$19,1,FALSE),"") | L111: =IFERROR(VLOOKUP($E111 & "|" & G111,comparison!$A$2:$A$19,1,FALSE),"") | M111: =IFERROR(VLOOKUP($E111 & "|" & H111,comparison!$A$2:$A$19,1,FALSE),"") | N111: =IFERROR(VLOOKUP($E111 & "|" & I111,comparison!$A$2:$A$19,1,FALSE),"") | O111: =IFERROR(VLOOKUP($E111 & "|" & J111,comparison!$A$2:$A$19,1,FALSE),"") | Q111: =IF(LEN(K111)>0,1,0) -> 0 | R111: =IF(LEN(L111)>0,1,0) -> 0 | S111: =IF(LEN(M111)>0,1,0) -> 0 | T111: =IF(LEN(N111)>0,1,0) -> 0 | U111: =IF(LEN(O111)>0,1,0) -> 0
... A134: Changed | B134: ACTIVE | C134: Pensions | E134: LS007_00 | K134: =IFERROR(VLOOKUP($E134 & "|" & F134,comparison!$A$2:$A$19,1,FALSE),"") | L134: =IFERROR(VLOOKUP($E134 & "|" & G134,comparison!$A$2:$A$19,1,FALSE),"") | M134: =IFERROR(VLOOKUP($E134 & "|" & H134,comparison!$A$2:$A$19,1,FALSE),"") | N134: =IFERROR(VLOOKUP($E134 & "|" & I134,comparison!$A$2:$A$19,1,FALSE),"") | O134: =IFERROR(VLOOKUP($E134 & "|" & J134,comparison!$A$2:$A$19,1,FALSE),"") | Q134: =IF(LEN(K134)>0,1,0) -> 0 | R134: =IF(LEN(L134)>0,1,0) -> 0 | S134: =IF(LEN(M134)>0,1,0) -> 0 | T134: =IF(LEN(N134)>0,1,0) -> 0 | U134: =IF(LEN(O134)>0,1,0) -> 0
A135: Changed | B135: ACTIVE | C135: IFRS 17 - BBA LRC CSM | E135: LS013_17 | G135: CON_Q3_Q4 | K135: =IFERROR(VLOOKUP($E135 & "|" & F135,comparison!$A$2:$A$19,1,FALSE),"") | L135: =IFERROR(VLOOKUP($E135 & "|" & G135,comparison!$A$2:$A$19,1,FALSE),"") -> LS013_17|CON_Q3_Q4 | M135: =IFERROR(VLOOKUP($E135 & "|" & H135,comparison!$A$2:$A$19,1,FALSE),"") | N135: =IFERROR(VLOOKUP($E135 & "|" & I135,comparison!$A$2:$A$19,1,FALSE),"") | O135: =IFERROR(VLOOKUP($E135 & "|" & J135,comparison!$A$2:$A$19,1,FALSE),"") | Q135: =IF(LEN(K135)>0,1,0) -> 0 | R135: =IF(LEN(L135)>0,1,0) -> 1 | S135: =IF(LEN(M135)>0,1,0) -> 0 | T135: =IF(LEN(N135)>0,1,0) -> 0 | U135: =IF(LEN(O135)>0,1,0) -> 0
...

Sheet FIP Conditions
A1: Key | B1: MethC | C1: MK | D1: Medium Text MK | E1: Normal X-Check No | F1: X-Check Medium Text | G1: UCFV20G-TRUE_BRANCH | H1: Condition No | I1: Condition Medium Text
A2: =E2 & "|" &H2 -> 3_CACC_020|3_PVLC | B2: 8 | C2: DV100 | D2: Data Entry Validation 100/IFRS | E2: 3_CACC_020 | F2: AC: Counterparty Accounts | H2: 3_PVLC | I2: Amount LC = 0 / Quanity = 0
A3: =E3 & "|" &H3 -> 3_CACC_030|3_PVLC | B3: 8 | C3: DV100 | D3: Data Entry Validation 100/IFRS | E3: 3_CACC_030 | F3: AC: Plan-Accounts | H3: 3_PVLC | I3: Amount LC = 0 / Quanity = 0
A4: =E4 & "|" &H4 -> 3_CACC_050|3_PVLC | B4: 8 | C4: DV100 | D4: Data Entry Validation 100/IFRS | E4: 3_CACC_050 | F4: Account, where only quantities postable | H4: 3_PVLC | I4: Amount LC = 0 / Quanity = 0
A5: =E5 & "|" &H5 -> 3_CACC_130|3_ZTOM_000 | B5: 8 | C5: DV100 | D5: Data Entry Validation 100/IFRS | E5: 3_CACC_130 | F5: IFRS ToM: not relevant accounts | H5: 3_ZTOM_000 | I5: Breakdown Check ToM: relevance
A6: =E6 & "|" &H6 -> 3_CACC_I10|3_ZPRU_000 | B6: 8 | C6: DV100 | D6: Data Entry Validation 100/IFRS | E6: 3_CACC_I10 | F6: IFRS PRU: not relevant Accounts | H6: 3_ZPRU_000 | I6: Breakdown check PRU: relevance
A7: =E7 & "|" &H7 -> 3_CACC_I20|3_ZPSE_000 | B7: 8 | C7: DV100 | D7: Data Entry Validation 100/IFRS | E7: 3_CACC_I20 | F7: IFRS PSE: not relevant accounts | H7: 3_ZPSE_000 | I7: Breakdown check PSE: relevance
A8: =E8 & "|" &H8 -> 3_CACC_I40|3_ZALC_000 | B8: 8 | C8: DV100 | D8: Data Entry Validation 100/IFRS | E8: 3_CACC_I40 | F8: IFRS ALC not relevant Accounts | H8: 3_ZALC_000 | I8: Breakdown Check ALC: relevance
A9: =E9 & "|" &H9 -> 3_CACC_I50|3_ZGRC_000 | B9: 8 | C9: DV100 | D9: Data Entry Validation 100/IFRS | E9: 3_CACC_I50 | F9: IFRS Gross / Ceded not relevant Accounts | H9: 3_ZGRC_000 | I9: Breakdown Check GRC: relevance
A10: =E10 & "|" &H10 -> 3_CACC_I60|3_ZMAT_000 | B10: 8 | C10: DV100 | D10: Data Entry Validation 100/IFRS | E10: 3_CACC_I60 | F10: IFRS MAT not relevant Accounts | H10: 3_ZMAT_000 | I10: Breakdown Check MAT: relevance
A11: =E11 & "|" &H11 -> 3_CACC_I70|3_ZREX_000 | B11: 8 | C11: DV100 | D11: Data Entry Validation 100/IFRS | E11: 3_CACC_I70 | F11: IFRS REX relevant Accounts | H11: 3_ZREX_000 | I11: BD Check REX: relevance
A12: =E12 & "|" &H12 -> 3_CACC_I80|3_ZVLT_000 | B12: 8 | C12: DV100 | D12: Data Entry Validation 100/IFRS | E12: 3_CACC_I80 | F12: IFRS VAL not relevant Accounts | H12: 3_ZVLT_000 | I12: BD Check VAL: relevance
A13: =E13 & "|" &H13 -> 3_CACC_I90|3_ZVAR_000 | B13: 8 | C13: DV100 | D13: Data Entry Validation 100/IFRS | E13: 3_CACC_I90 | F13: IFRS VAR not relevant Accounts | H13: 3_ZVAR_000 | I13: BD Check VAR: relevance
... A16: =E16 & "|" &H16 -> 3_CACY_NA|3_CACC_IB0 | B16: 8 | C16: DV100 | D16: Data Entry Validation 100/IFRS | E16: 3_CACY_NA | F16: AY = not assigned | H16: 3_CACC_IB0 | I16: IFRS ACY not relevant Accounts
A17: =E17 & "|" &H17 -> 3_CACY_RV|3_CACC_IB0 | B17: 8 | C17: DV100 | D17: Data Entry Validation 100/IFRS | E17: 3_CACY_RV | F17: ACY with real value | G17: X | H17: 3_CACC_IB0 | I17: IFRS ACY not relevant Accounts
A18: =E18 & "|" &H18 -> 3_CALC_NA|3_CACC_I40 | B18: 8 | C18: DV100 | D18: Data Entry Validation 100/IFRS | E18: 3_CALC_NA | F18: ALC = not assigned | H18: 3_CACC_I40 | I18: IFRS ALC not relevant Accounts
A19: =E19 & "|" &H19 -> 3_CALC_RV|3_CACC_I40 | B19: 8 | C19: DV100 | D19: Data Entry Validation 100/IFRS | E19: 3_CALC_RV | F19: ALC with real value | G19: X | H19: 3_CACC_I40 | I19: IFRS ALC not relevant Accounts
A20: =E20 & "|" &H20 -> 3_CAMT_000|3_CACC_050 | B20: 8 | C20: DV100 | D20: Data Entry Validation 100/IFRS | E20: 3_CAMT_000 | F20: Amount LC posted? | G20: X | H20: 3_CACC_050 | I20: Account, where only quantities postable
A21: =E21 & "|" &H21 -> 3_CGRC_NA|3_CACC_I50 | B21: 8 | C21: DV100 | D21: Data Entry Validation 100/IFRS | E21: 3_CGRC_NA | F21: GRC = not assigned | H21: 3_CACC_I50 | I21: IFRS Gross / Ceded not relevant Accounts
A22: =E22 & "|" &H22 -> 3_CGRC_RV|3_CACC_I50 | B22: 8 | C22: DV100 | D22: Data Entry Validation 100/IFRS | E22: 3_CGRC_RV | F22: GRC with real value | G22: X | H22: 3_CACC_I50 | I22: IFRS Gross / Ceded not relevant Accounts
A23: =E23 & "|" &H23 -> 3_CISG_010|3_PVLC | B23: 8 | C23: DV100 | D23: Data Entry Validation 100/IFRS | E23: 3_CISG_010 | F23: Investee Segment: only X allowed | H23: 3_PVLC | I23: Amount LC = 0 / Quanity = 0
A24: =E24 & "|" &H24 -> 3_CLOB_NA|3_CACC_IA0 | B24: 8 | C24: DV100 | D24: Data Entry Validation 100/IFRS | E24: 3_CLOB_NA | F24: Line of Business = not assigned | H24: 3_CACC_IA0 | I24: IFRS LOB not relevant Accounts
A25: =E25 & "|" &H25 -> 3_CLOB_RV|3_CACC_IA0 | B25: 8 | C25: DV100 | D25: Data Entry Validation 100/IFRS | E25: 3_CLOB_RV | F25: Line of Business with real value | G25: X | H25: 3_CACC_IA0 | I25: IFRS LOB not relevant Accounts
A26: =E26 & "|" &H26 -> 3_CMAT_NA|3_CACC_I60 | B26: 8 | C26: DV100 | D26: Data Entry Validation 100/IFRS | E26: 3_CMAT_NA | F26: MAT = not assigned | H26: 3_CACC_I60 | I26: IFRS MAT not relevant Accounts
A27: =E27 & "|" &H27 -> 3_CMAT_RV|3_CACC_I60 | B27: 8 | C27: DV100 | D27: Data Entry Validation 100/IFRS | E27: 3_CMAT_RV | F27: MAT with real value | G27: X | H27: 3_CACC_I60 | I27: IFRS MAT not relevant Accounts
A28: =E28 & "|" &H28 -> 3_CPRU_NA|3_CACC_I10 | B28: 8 | C28: DV100 | D28: Data Entry Validation 100/IFRS | E28: 3_CPRU_NA | F28: PRU = not assigned | H28: 3_CACC_I10 | I28: IFRS PRU: not relevant Accounts
A29: =E29 & "|" &H29 -> 3_CPRU_NAY|3_CPRU_RU | B29: 8 | C29: DV100 | D29: Data Entry Validation 100/IFRS | E29: 3_CPRU_NAY | F29: PRU = not assigned, account 29102 | G29: X | H29: 3_CPRU_RU | I29: PRU = RU
A30: =E30 & "|" &H30 -> 3_CPRU_RU|3_CPRU_NA | B30: 8 | C30: DV100 | D30: Data Entry Validation 100/IFRS | E30: 3_CPRU_RU | F30: PRU = RU | H30: 3_CPRU_NA | I30: PRU = not assigned
A31: =E31 & "|" &H31 -> 3_CPRU_RV|3_CACC_I10 | B31: 8 | C31: DV100 | D31: Data Entry Validation 100/IFRS | E31: 3_CPRU_RV | F31: PRU with real value | G31: X | H31: 3_CACC_I10 | I31: IFRS PRU: not relevant Accounts
A32: =E32 & "|" &H32 -> 3_CPSE_NA|3_CACC_I20 | B32: 8 | C32: DV100 | D32: Data Entry Validation 100/IFRS | E32: 3_CPSE_NA | F32: PSE = not assigned | H32: 3_CACC_I20 | I32: IFRS PSE: not relevant accounts
A33: =E33 & "|" &H33 -> 3_CPSE_RV|3_CACC_I20 | B33: 8 | C33: DV100 | D33: Data Entry Validation 100/IFRS | E33: 3_CPSE_RV | F33: PSE with real value | G33: X | H33: 3_CACC_I20 | I33: IFRS PSE: not relevant accounts
A34: =E34 & "|" &H34 -> 3_CQTY_000|3_CACC_050 | B34: 8 | C34: DV100 | D34: Data Entry Validation 100/IFRS | E34: 3_CQTY_000 | F34: Quantity posted? | H34: 3_CACC_050 | I34: Account, where only quantities postable
A35: =E35 & "|" &H35 -> 3_CREX_NA|3_CACC_I70 | B35: 8 | C35: DV100 | D35: Data Entry Validation 100/IFRS | E35: 3_CREX_NA | F35: REX = not assigned | H35: 3_CACC_I70 | I35: IFRS REX relevant Accounts
A36: =E36 & "|" &H36 -> 3_CREX_RV|3_CACC_I70 | B36: 8 | C36: DV100 | D36: Data Entry Validation 100/IFRS | E36: 3_CREX_RV | F36: REX with real value | G36: X | H36: 3_CACC_I70 | I36: IFRS REX relevant Accounts
A37: =E37 & "|" &H37 -> 3_CTOM_NA|3_CACC_130 | B37: 8 | C37: DV100 | D37: Data Entry Validation 100/IFRS | E37: 3_CTOM_NA | F37: TOM = not assigned | H37: 3_CACC_130 | I37: IFRS ToM: not relevant accounts
A38: =E38 & "|" &H38 -> 3_CTOM_RV|3_CACC_130 | B38: 8 | C38: DV100 | D38: Data Entry Validation 100/IFRS | E38: 3_CTOM_RV | F38: TOM with real value | G38: X | H38: 3_CACC_130 | I38: IFRS ToM: not relevant accounts
A39: =E39 & "|" &H39 -> 3_CVAR_NA|3_CACC_I90 | B39: 8 | C39: DV100 | D39: Data Entry Validation 100/IFRS | E39: 3_CVAR_NA | F39: VAR = not assigned | H39: 3_CACC_I90 | I39: IFRS VAR not relevant Accounts
A40: =E40 & "|" &H40 -> 3_CVAR_RV|3_CACC_I90 | B40: 8 | C40: DV100 | D40: Data Entry Validation 100/IFRS | E40: 3_CVAR_RV | F40: VAR with real value | G40: X | H40: 3_CACC_I90 | I40: IFRS VAR not relevant Accounts
A41: =E41 & "|" &H41 -> 3_CVLT_NA|3_CACC_I80 | B41: 8 | C41: DV100 | D41: Data Entry Validation 100/IFRS | E41: 3_CVLT_NA | F41: VAL = not assigned | H41: 3_CACC_I80 | I41: IFRS VAL not relevant Accounts
A42: =E42 & "|" &H42 -> 3_CVLT_RV|3_CACC_I80 | B42: 8 | C42: DV100 | D42: Data Entry Validation 100/IFRS | E42: 3_CVLT_RV | F42: VAL with real value | G42: X | H42: 3_CACC_I80 | I42: IFRS VAL not relevant Accounts
A43: =E43 & "|" &H43 -> 3_ZACA_001|CON_PL00 | B43: 8 | C43: DV100 | D43: Data Entry Validation 100/IFRS | E43: 3_ZACA_001 | F43: BD Check BBA-ACA: ZZZZZ or BLANK | G43: X | H43: CON_PL00 | I43: CON_PL00
A44: =E44 & "|" &H44 -> 3_ZACY_000|CON_PL00 | B44: 8 | C44: DV100 | D44: Data Entry Validation 100/IFRS | E44: 3_ZACY_000 | F44: BD Check Accident Year: relevance | G44: X | H44: CON_PL00 | I44: CON_PL00
A45: =E45 & "|" &H45 -> 3_ZALC_000|CON_PL00 | B45: 8 | C45: DV100 | D45: Data Entry Validation 100/IFRS | E45: 3_ZALC_000 | F45: Breakdown Check ALC: relevance | G45: X | H45: CON_PL00 | I45: CON_PL00
A46: =E46 & "|" &H46 -> 3_ZGRC_000|CON_PL00 | B46: 8 | C46: DV100 | D46: Data Entry Validation 100/IFRS | E46: 3_ZGRC_000 | F46: Breakdown Check GRC: relevance | G46: X | H46: CON_PL00 | I46: CON_PL00
A47: =E47 & "|" &H47 -> 3_ZLOB_000|CON_PL00 | B47: 8 | C47: DV100 | D47: Data Entry Validation 100/IFRS | E47: 3_ZLOB_000 | F47: BD Check LOB: relevance | G47: X | H47: CON_PL00 | I47: CON_PL00
A48: =E48 & "|" &H48 -> 3_ZMAT_000|CON_PL00 | B48: 8 | C48: DV100 | D48: Data Entry Validation 100/IFRS | E48: 3_ZMAT_000 | F48: Breakdown Check MAT: relevance | G48: X | H48: CON_PL00 | I48: CON_PL00
A49: =E49 & "|" &H49 -> 3_ZPRU_000|CON_PL00 | B49: 8 | C49: DV100 | D49: Data Entry Validation 100/IFRS | E49: 3_ZPRU_000 | F49: Breakdown check PRU: relevance | G49: X | H49: CON_PL00 | I49: CON_PL00
A50: =E50 & "|" &H50 -> 3_ZPSE_000|CON_PL00 | B50: 8 | C50: DV100 | D50: Data Entry Validation 100/IFRS | E50: 3_ZPSE_000 | F50: Breakdown check PSE: relevance | G50: X | H50: CON_PL00 | I50: CON_PL00
A51: =E51 & "|" &H51 -> 3_ZREX_000|CON_PL00 | B51: 8 | C51: DV100 | D51: Data Entry Validation 100/IFRS | E51: 3_ZREX_000 | F51: BD Check REX: relevance | G51: X | H51: CON_PL00 | I51: CON_PL00
A52: =E52 & "|" &H52 -> 3_ZTOM_000|CON_PL00 | B52: 8 | C52: DV100 | D52: Data Entry Validation 100/IFRS | E52: 3_ZTOM_000 | F52: Breakdown Check ToM: relevance | G52: X | H52: CON_PL00 | I52: CON_PL00
A53: =E53 & "|" &H53 -> 3_ZVAR_000|CON_PL00 | B53: 8 | C53: DV100 | D53: Data Entry Validation 100/IFRS | E53: 3_ZVAR_000 | F53: BD Check VAR: relevance | G53: X | H53: CON_PL00 | I53: CON_PL00
A54: =E54 & "|" &H54 -> 3_ZVLT_000|CON_PL00 | B54: 8 | C54: DV100 | D54: Data Entry Validation 100/IFRS | E54: 3_ZVLT_000 | F54: BD Check VAL: relevance | G54: X | H54: CON_PL00 | I54: CON_PL00
A55: =E55 & "|" &H55 -> CON_CORECG|3_ZLOB_000 | B55: 8 | C55: DV100 | D55: Data Entry Validation 100/IFRS | E55: CON_CORECG | F55: CON_CORECG | H55: 3_ZLOB_000 | I55: BD Check LOB: relevance
A56: =E56 & "|" &H56 -> CON_LOB|3_CLOB_NA | B56: 8 | C56: DV100 | D56: Data Entry Validation 100/IFRS | E56: CON_LOB | F56: CON_LOB | G56: X | H56: 3_CLOB_NA | I56: Line of Business = not assigned
A57: =E57 & "|" &H57 -> 3_CACA_NA|3_CACC_NC0 | B57: 8 | C57: DV10N | D57: Data Entry Validation 100/IFRSN | E57: 3_CACA_NA | F57: BBA-ACA = not assigned | H57: 3_CACC_NC0 | I57: IFRSN BBA-ACA not relevant Accounts
A58: =E58 & "|" &H58 -> 3_CACA_RV|3_CACC_NC0 | B58: 8 | C58: DV10N | D58: Data Entry Validation 100/IFRSN | E58: 3_CACA_RV | F58: BBA-ACA with real value | G58: X | H58: 3_CACC_NC0 | I58: IFRSN BBA-ACA not relevant Accounts
A59: =E59 & "|" &H59 -> 3_CACC_020|3_PVLC | B59: 8 | C59: DV10N | D59: Data Entry Validation 100/IFRSN | E59: 3_CACC_020 | F59: AC: Counterparty Accounts | H59: 3_PVLC | I59: Amount LC = 0 / Quanity = 0
A60: =E60 & "|" &H60 -> 3_CACC_030|3_PVLC | B60: 8 | C60: DV10N | D60: Data Entry Validation 100/IFRSN | E60: 3_CACC_030 | F60: AC: Plan-Accounts | H60: 3_PVLC | I60: Amount LC = 0 / Quanity = 0
A61: =E61 & "|" &H61 -> 3_CACC_050|3_PVLC | B61: 8 | C61: DV10N | D61: Data Entry Validation 100/IFRSN | E61: 3_CACC_050 | F61: Account, where only quantities postable | H61: 3_PVLC | I61: Amount LC = 0 / Quanity = 0
A62: =E62 & "|" &H62 -> 3_CACC_N10|3_ZPRU_000 | B62: 8 | C62: DV10N | D62: Data Entry Validation 100/IFRSN | E62: 3_CACC_N10 | F62: IFRSN PRU: not relevant Accounts | H62: 3_ZPRU_000 | I62: Breakdown check PRU: relevance
A63: =E63 & "|" &H63 -> 3_CACC_N20|3_ZPSE_000 | B63: 8 | C63: DV10N | D63: Data Entry Validation 100/IFRSN | E63: 3_CACC_N20 | F63: IFRSN PSE: not relevant accounts | H63: 3_ZPSE_000 | I63: Breakdown check PSE: relevance
A64: =E64 & "|" &H64 -> 3_CACC_N30|3_ZTOM_000 | B64: 8 | C64: DV10N | D64: Data Entry Validation 100/IFRSN | E64: 3_CACC_N30 | F64: IFRSN ToM: not relevant accounts | H64: 3_ZTOM_000 | I64: Breakdown Check ToM: relevance
A65: =E65 & "|" &H65 -> 3_CACC_N40|3_ZALC_000 | B65: 8 | C65: DV10N | D65: Data Entry Validation 100/IFRSN | E65: 3_CACC_N40 | F65: IFRSN ALC not relevant Accounts | H65: 3_ZALC_000 | I65: Breakdown Check ALC: relevance
A66: =E66 & "|" &H66 -> 3_CACC_N50|3_ZGRC_000 | B66: 8 | C66: DV10N | D66: Data Entry Validation 100/IFRSN | E66: 3_CACC_N50 | F66: IFRSN Gross / Ceded not relevant Account | H66: 3_ZGRC_000 | I66: Breakdown Check GRC: relevance
A67: =E67 & "|" &H67 -> 3_CACC_N60|3_ZMAT_000 | B67: 8 | C67: DV10N | D67: Data Entry Validation 100/IFRSN | E67: 3_CACC_N60 | F67: IFRSN MAT not relevant Accounts | H67: 3_ZMAT_000 | I67: Breakdown Check MAT: relevance
A68: =E68 & "|" &H68 -> 3_CACC_N70|3_ZREX_000 | B68: 8 | C68: DV10N | D68: Data Entry Validation 100/IFRSN | E68: 3_CACC_N70 | F68: IFRSN REX relevant Accounts | H68: 3_ZREX_000 | I68: BD Check REX: relevance
A69: =E69 & "|" &H69 -> 3_CACC_N80|3_ZVLT_000 | B69: 8 | C69: DV10N | D69: Data Entry Validation 100/IFRSN | E69: 3_CACC_N80 | F69: IFRSN VAL not relevant Accounts | H69: 3_ZVLT_000 | I69: BD Check VAL: relevance
A70: =E70 & "|" &H70 -> 3_CACC_N90|3_ZVAR_000 | B70: 8 | C70: DV10N | D70: Data Entry Validation 100/IFRSN | E70: 3_CACC_N90 | F70: IFRSN VAR not relevant Accounts | H70: 3_ZVAR_000 | I70: BD Check VAR: relevance
... A74: =E74 & "|" &H74 -> 3_CACY_NA|3_CACC_NB0 | B74: 8 | C74: DV10N | D74: Data Entry Validation 100/IFRSN | E74: 3_CACY_NA | F74: AY = not assigned | H74: 3_CACC_NB0 | I74: IFRSN ACY not relevant Accounts
A75: =E75 & "|" &H75 -> 3_CACY_RV|3_CACC_NB0 | B75: 8 | C75: DV10N | D75: Data Entry Validation 100/IFRSN | E75: 3_CACY_RV | F75: ACY with real value | G75: X | H75: 3_CACC_NB0 | I75: IFRSN ACY not relevant Accounts
A76: =E76 & "|" &H76 -> 3_CALC_NA|3_CACC_N40 | B76: 8 | C76: DV10N | D76: Data Entry Validation 100/IFRSN | E76: 3_CALC_NA | F76: ALC = not assigned | H76: 3_CACC_N40 | I76: IFRSN ALC not relevant Accounts
A77: =E77 & "|" &H77 -> 3_CALC_RV|3_CACC_N40 | B77: 8 | C77: DV10N | D77: Data Entry Validation 100/IFRSN | E77: 3_CALC_RV | F77: ALC with real value | G77: X | H77: 3_CACC_N40 | I77: IFRSN ALC not relevant Accounts
A78: =E78 & "|" &H78 -> 3_CAMT_000|3_CACC_050 | B78: 8 | C78: DV10N | D78: Data Entry Validation 100/IFRSN | E78: 3_CAMT_000 | F78: Amount LC posted? | G78: X | H78: 3_CACC_050 | I78: Account, where only quantities postable
A79: =E79 & "|" &H79 -> 3_CGRC_NA|3_CACC_N50 | B79: 8 | C79: DV10N | D79: Data Entry Validation 100/IFRSN | E79: 3_CGRC_NA | F79: GRC = not assigned | H79: 3_CACC_N50 | I79: IFRSN Gross / Ceded not relevant Account
A80: =E80 & "|" &H80 -> 3_CGRC_RV|3_CACC_N50 | B80: 8 | C80: DV10N | D80: Data Entry Validation 100/IFRSN | E80: 3_CGRC_RV | F80: GRC with real value | G80: X | H80: 3_CACC_N50 | I80: IFRSN Gross / Ceded not relevant Account
A81: =E81 & "|" &H81 -> 3_CISG_010|3_PVLC | B81: 8 | C81: DV10N | D81: Data Entry Validation 100/IFRSN | E81: 3_CISG_010 | F81: Investee Segment: only X allowed | H81: 3_PVLC | I81: Amount LC = 0 / Quanity = 0
A82: =E82 & "|" &H82 -> 3_CLOB_NA|3_CACC_NA0 | B82: 8 | C82: DV10N | D82: Data Entry Validation 100/IFRSN | E82: 3_CLOB_NA | F82: Line of Business = not assigned | H82: 3_CACC_NA0 | I82: IFRSN LOB not relevant Accounts
A83: =E83 & "|" &H83 -> 3_CLOB_RV|3_CACC_NA0 | B83: 8 | C83: DV10N | D83: Data Entry Validation 100/IFRSN | E83: 3_CLOB_RV | F83: Line of Business with real value | G83: X | H83: 3_CACC_NA0 | I83: IFRSN LOB not relevant Accounts
A84: =E84 & "|" &H84 -> 3_CMAT_NA|3_CACC_N60 | B84: 8 | C84: DV10N | D84: Data Entry Validation 100/IFRSN | E84: 3_CMAT_NA | F84: MAT = not assigned | H84: 3_CACC_N60 | I84: IFRSN MAT not relevant Accounts
A85: =E85 & "|" &H85 -> 3_CMAT_RV|3_CACC_N60 | B85: 8 | C85: DV10N | D85: Data Entry Validation 100/IFRSN | E85: 3_CMAT_RV | F85: MAT with real value | G85: X | H85: 3_CACC_N60 | I85: IFRSN MAT not relevant Accounts
A86: =E86 & "|" &H86 -> 3_CPRU_NA|3_CACC_N10 | B86: 8 | C86: DV10N | D86: Data Entry Validation 100/IFRSN | E86: 3_CPRU_NA | F86: PRU = not assigned | H86: 3_CACC_N10 | I86: IFRSN PRU: not relevant Accounts
A87: =E87 & "|" &H87 -> 3_CPRU_NAY|3_CPRU_RU | B87: 8 | C87: DV10N | D87: Data Entry Validation 100/IFRSN | E87: 3_CPRU_NAY | F87: PRU = not assigned, account 29102 | G87: X | H87: 3_CPRU_RU | I87: PRU = RU
A88: =E88 & "|" &H88 -> 3_CPRU_RU|3_CPRU_NA | B88: 8 | C88: DV10N | D88: Data Entry Validation 100/IFRSN | E88: 3_CPRU_RU | F88: PRU = RU | H88: 3_CPRU_NA | I88: PRU = not assigned
A89: =E89 & "|" &H89 -> 3_CPRU_RV|3_CACC_N10 | B89: 8 | C89: DV10N | D89: Data Entry Validation 100/IFRSN | E89: 3_CPRU_RV | F89: PRU with real value | G89: X | H89: 3_CACC_N10 | I89: IFRSN PRU: not relevant Accounts
A90: =E90 & "|" &H90 -> 3_CPSE_NA|3_CACC_N20 | B90: 8 | C90: DV10N | D90: Data Entry Validation 100/IFRSN | E90: 3_CPSE_NA | F90: PSE = not assigned | H90: 3_CACC_N20 | I90: IFRSN PSE: not relevant accounts
A91: =E91 & "|" &H91 -> 3_CPSE_RV|3_CACC_N20 | B91: 8 | C91: DV10N | D91: Data Entry Validation 100/IFRSN | E91: 3_CPSE_RV | F91: PSE with real value | G91: X | H91: 3_CACC_N20 | I91: IFRSN PSE: not relevant accounts
A92: =E92 & "|" &H92 -> 3_CQTY_000|3_CACC_050 | B92: 8 | C92: DV10N | D92: Data Entry Validation 100/IFRSN | E92: 3_CQTY_000 | F92: Quantity posted? | H92: 3_CACC_050 | I92: Account, where only quantities postable
A93: =E93 & "|" &H93 -> 3_CREX_NA|3_CACC_N70 | B93: 8 | C93: DV10N | D93: Data Entry Validation 100/IFRSN | E93: 3_CREX_NA | F93: REX = not assigned | H93: 3_CACC_N70 | I93: IFRSN REX relevant Accounts
A94: =E94 & "|" &H94 -> 3_CREX_RV|3_CACC_N70 | B94: 8 | C94: DV10N | D94: Data Entry Validation 100/IFRSN | E94: 3_CREX_RV | F94: REX with real value | G94: X | H94: 3_CACC_N70 | I94: IFRSN REX relevant Accounts
A95: =E95 & "|" &H95 -> 3_CTOM_NA|3_CACC_N30 | B95: 8 | C95: DV10N | D95: Data Entry Validation 100/IFRSN | E95: 3_CTOM_NA | F95: TOM = not assigned | H95: 3_CACC_N30 | I95: IFRSN ToM: not relevant accounts
A96: =E96 & "|" &H96 -> 3_CTOM_RV|3_CACC_N30 | B96: 8 | C96: DV10N | D96: Data Entry Validation 100/IFRSN | E96: 3_CTOM_RV | F96: TOM with real value | G96: X | H96: 3_CACC_N30 | I96: IFRSN ToM: not relevant accounts
A97: =E97 & "|" &H97 -> 3_CVAR_NA|3_CACC_N90 | B97: 8 | C97: DV10N | D97: Data Entry Validation 100/IFRSN | E97: 3_CVAR_NA | F97: VAR = not assigned | H97: 3_CACC_N90 | I97: IFRSN VAR not relevant Accounts
A98: =E98 & "|" &H98 -> 3_CVAR_RV|3_CACC_N90 | B98: 8 | C98: DV10N | D98: Data Entry Validation 100/IFRSN | E98: 3_CVAR_RV | F98: VAR with real value | G98: X | H98: 3_CACC_N90 | I98: IFRSN VAR not relevant Accounts
A99: =E99 & "|" &H99 -> 3_CVLT_NA|3_CACC_N80 | B99: 8 | C99: DV10N | D99: Data Entry Validation 100/IFRSN | E99: 3_CVLT_NA | F99: VAL = not assigned | H99: 3_CACC_N80 | I99: IFRSN VAL not relevant Accounts
A100: =E100 & "|" &H100 -> 3_CVLT_RV|3_CACC_N80 | B100: 8 | C100: DV10N | D100: Data Entry Validation 100/IFRSN | E100: 3_CVLT_RV | F100: VAL with real value | G100: X | H100: 3_CACC_N80 | I100: IFRSN VAL not relevant Accounts
A101: =E101 & "|" &H101 -> 3_ZACA_000|CON_PL00 | B101: 8 | C101: DV10N | D101: Data Entry Validation 100/IFRSN | E101: 3_ZACA_000 | F101: BD Check BBA-ACA: relevance | G101: X | H101: CON_PL00 | I101: CON_PL00
A102: =E102 & "|" &H102 -> 3_ZACY_000|CON_PL00 | B102: 8 | C102: DV10N | D102: Data Entry Validation 100/IFRSN | E102: 3_ZACY_000 | F102: BD Check Accident Year: relevance | G102: X | H102: CON_PL00 | I102: CON_PL00
A103: =E103 & "|" &H103 -> 3_ZALC_000|CON_PL00 | B103: 8 | C103: DV10N | D103: Data Entry Validation 100/IFRSN | E103: 3_ZALC_000 | F103: Breakdown Check ALC: relevance | G103: X | H103: CON_PL00 | I103: CON_PL00
A104: =E104 & "|" &H104 -> 3_ZGRC_000|CON_PL00 | B104: 8 | C104: DV10N | D104: Data Entry Validation 100/IFRSN | E104: 3_ZGRC_000 | F104: Breakdown Check GRC: relevance | G104: X | H104: CON_PL00 | I104: CON_PL00
A105: =E105 & "|" &H105 -> 3_ZLOB_000|CON_PL00 | B105: 8 | C105: DV10N | D105: Data Entry Validation 100/IFRSN | E105: 3_ZLOB_000 | F105: BD Check LOB: relevance | G105: X | H105: CON_PL00 | I105: CON_PL00
...

Sheet Sheet1
A2: Type of change | B2: Status | C2: Category | D2: Sense Check | E2: X-Check No. | F2: Reference X-Check (Condition) | G2: Applicable Quarters | H2: Included RUs | I2: Excluded RUs | J2: Reference X-Check (Limit, %) | L2: Reference X-Check (Condition) | M2: Applicable Quarters | N2: Included RUs | O2: Excluded RUs | P2: Reference X-Check (Limit, %)
A3: Changed | B3: ACTIVE | C3: Real Estate held for Investment | E3: A047_00 | L3: =IF(F3="","",$E3 & "|" & F3) | M3: =IF(G3="","",$E3 & "|" & G3) | N3: =IF(H3="","",$E3 & "|" & H3) | O3: =IF(I3="","",$E3 & "|" & I3) | P3: =IF(J3="","",$E3 & "|" & J3)
A4: Changed | B4: ACTIVE | C4: Real Estate held for Investment | E4: A047_00 | L4: =IF(F4="","",$E4 & "|" & F4) | M4: =IF(G4="","",$E4 & "|" & G4) | N4: =IF(H4="","",$E4 & "|" & H4) | O4: =IF(I4="","",$E4 & "|" & I4) | P4: =IF(J4="","",$E4 & "|" & J4)
A5: Changed | B5: ACTIVE | C5: Real Estate held for Investment | E5: A047_00 | L5: =IF(F5="","",$E5 & "|" & F5) | M5: =IF(G5="","",$E5 & "|" & G5) | N5: =IF(H5="","",$E5 & "|" & H5) | O5: =IF(I5="","",$E5 & "|" & I5) | P5: =IF(J5="","",$E5 & "|" & J5)
A6: Changed | B6: ACTIVE | C6: Equity Securities - Common Stock | D6: yes | E6: A074_00 | L6: =IF(F6="","",$E6 & "|" & F6) | M6: =IF(G6="","",$E6 & "|" & G6) | N6: =IF(H6="","",$E6 & "|" & H6) | O6: =IF(I6="","",$E6 & "|" & I6) | P6: =IF(J6="","",$E6 & "|" & J6)
A7: Changed | B7: ACTIVE | C7: Equity Securities - Common Stock | D7: yes | E7: A074_00 | L7: =IF(F7="","",$E7 & "|" & F7) | M7: =IF(G7="","",$E7 & "|" & G7) | N7: =IF(H7="","",$E7 & "|" & H7) | O7: =IF(I7="","",$E7 & "|" & I7) | P7: =IF(J7="","",$E7 & "|" & J7)
A8: Changed | B8: ACTIVE | C8: Equity Securities - Common Stock | D8: yes | E8: A074_00 | L8: =IF(F8="","",$E8 & "|" & F8) | M8: =IF(G8="","",$E8 & "|" & G8) | N8: =IF(H8="","",$E8 & "|" & H8) | O8: =IF(I8="","",$E8 & "|" & I8) | P8: =IF(J8="","",$E8 & "|" & J8)
A9: Changed | B9: ACTIVE | C9: Equity Securities - Common Stock | D9: yes | E9: A074_00 | L9: =IF(F9="","",$E9 & "|" & F9) | M9: =IF(G9="","",$E9 & "|" & G9) | N9: =IF(H9="","",$E9 & "|" & H9) | O9: =IF(I9="","",$E9 & "|" & I9) | P9: =IF(J9="","",$E9 & "|" & J9)
A10: Changed | B10: ACTIVE | C10: Equity Securities - Common Stock | D10: yes | E10: A074_00 | L10: =IF(F10="","",$E10 & "|" & F10) | M10: =IF(G10="","",$E10 & "|" & G10) | N10: =IF(H10="","",$E10 & "|" & H10) | O10: =IF(I10="","",$E10 & "|" & I10) | P10: =IF(J10="","",$E10 & "|" & J10)
A11: Changed | B11: ACTIVE | C11: Equity Securities - Common Stock | D11: yes | E11: A074_00 | L11: =IF(F11="","",$E11 & "|" & F11) | M11: =IF(G11="","",$E11 & "|" & G11) | N11: =IF(H11="","",$E11 & "|" & H11) | O11: =IF(I11="","",$E11 & "|" & I11) | P11: =IF(J11="","",$E11 & "|" & J11)
A12: Changed | B12: ACTIVE | C12: Equity Securities - Common Stock | D12: yes | E12: A074_00 | L12: =IF(F12="","",$E12 & "|" & F12) | M12: =IF(G12="","",$E12 & "|" & G12) | N12: =IF(H12="","",$E12 & "|" & H12) | O12: =IF(I12="","",$E12 & "|" & I12) | P12: =IF(J12="","",$E12 & "|" & J12)
A13: Changed | B13: ACTIVE | C13: Equity Securities - Common Stock | D13: yes | E13: A074_00 | L13: =IF(F13="","",$E13 & "|" & F13) | M13: =IF(G13="","",$E13 & "|" & G13) | N13: =IF(H13="","",$E13 & "|" & H13) | O13: =IF(I13="","",$E13 & "|" & I13) | P13: =IF(J13="","",$E13 & "|" & J13)
A14: Changed | B14: ACTIVE | C14: Equity Securities - Common Stock | E14: A079_00 | L14: =IF(F14="","",$E14 & "|" & F14) | M14: =IF(G14="","",$E14 & "|" & G14) | N14: =IF(H14="","",$E14 & "|" & H14) | O14: =IF(I14="","",$E14 & "|" & I14) | P14: =IF(J14="","",$E14 & "|" & J14)
A15: Changed | B15: ACTIVE | C15: Equity Securities - Common Stock | E15: A079_00 | L15: =IF(F15="","",$E15 & "|" & F15) | M15: =IF(G15="","",$E15 & "|" & G15) | N15: =IF(H15="","",$E15 & "|" & H15) | O15: =IF(I15="","",$E15 & "|" & I15) | P15: =IF(J15="","",$E15 & "|" & J15)
A16: Changed | B16: ACTIVE | C16: Equity Securities - Common Stock | E16: A079_00 | L16: =IF(F16="","",$E16 & "|" & F16) | M16: =IF(G16="","",$E16 & "|" & G16) | N16: =IF(H16="","",$E16 & "|" & H16) | O16: =IF(I16="","",$E16 & "|" & I16) | P16: =IF(J16="","",$E16 & "|" & J16)
A17: Changed | B17: ACTIVE | C17: Equity Securities - Common Stock | E17: A079_00 | L17: =IF(F17="","",$E17 & "|" & F17) | M17: =IF(G17="","",$E17 & "|" & G17) | N17: =IF(H17="","",$E17 & "|" & H17) | O17: =IF(I17="","",$E17 & "|" & I17) | P17: =IF(J17="","",$E17 & "|" & J17)
A18: Changed | B18: ACTIVE | C18: Equity Securities - Common Stock | E18: A079_00 | L18: =IF(F18="","",$E18 & "|" & F18) | M18: =IF(G18="","",$E18 & "|" & G18) | N18: =IF(H18="","",$E18 & "|" & H18) | O18: =IF(I18="","",$E18 & "|" & I18) | P18: =IF(J18="","",$E18 & "|" & J18)
A19: Changed | B19: ACTIVE | C19: Equity Securities - Common Stock | E19: A079_00 | L19: =IF(F19="","",$E19 & "|" & F19) | M19: =IF(G19="","",$E19 & "|" & G19) | N19: =IF(H19="","",$E19 & "|" & H19) | O19: =IF(I19="","",$E19 & "|" & I19) | P19: =IF(J19="","",$E19 & "|" & J19)
A20: Changed | B20: ACTIVE | C20: Equity Securities - Common Stock | E20: A079_00 | L20: =IF(F20="","",$E20 & "|" & F20) | M20: =IF(G20="","",$E20 & "|" & G20) | N20: =IF(H20="","",$E20 & "|" & H20) | O20: =IF(I20="","",$E20 & "|" & I20) | P20: =IF(J20="","",$E20 & "|" & J20)
A21: Changed | B21: ACTIVE | C21: Equity Securities - Common Stock | E21: A079_00 | L21: =IF(F21="","",$E21 & "|" & F21) | M21: =IF(G21="","",$E21 & "|" & G21) | N21: =IF(H21="","",$E21 & "|" & H21) | O21: =IF(I21="","",$E21 & "|" & I21) | P21: =IF(J21="","",$E21 & "|" & J21)
A22: Changed | B22: ACTIVE | C22: Equity Securities - Common Stock | E22: A079_00 | L22: =IF(F22="","",$E22 & "|" & F22) | M22: =IF(G22="","",$E22 & "|" & G22) | N22: =IF(H22="","",$E22 & "|" & H22) | O22: =IF(I22="","",$E22 & "|" & I22) | P22: =IF(J22="","",$E22 & "|" & J22)
A23: Changed | B23: ACTIVE | C23: Equity Securities - Common Stock | E23: A079_00 | L23: =IF(F23="","",$E23 & "|" & F23) | M23: =IF(G23="","",$E23 & "|" & G23) | N23: =IF(H23="","",$E23 & "|" & H23) | O23: =IF(I23="","",$E23 & "|" & I23) | P23: =IF(J23="","",$E23 & "|" & J23)
A24: Changed | B24: ACTIVE | C24: Equity Securities - Common Stock | E24: A079_00 | L24: =IF(F24="","",$E24 & "|" & F24) | M24: =IF(G24="","",$E24 & "|" & G24) | N24: =IF(H24="","",$E24 & "|" & H24) | O24: =IF(I24="","",$E24 & "|" & I24) | P24: =IF(J24="","",$E24 & "|" & J24)
A25: Changed | B25: ACTIVE | C25: Equity Securities - Common Stock | E25: A079_00 | L25: =IF(F25="","",$E25 & "|" & F25) | M25: =IF(G25="","",$E25 & "|" & G25) | N25: =IF(H25="","",$E25 & "|" & H25) | O25: =IF(I25="","",$E25 & "|" & I25) | P25: =IF(J25="","",$E25 & "|" & J25)
... A89: Changed | B89: ACTIVE | C89: Equity Securities - Common Stock | E89: A081_00 | L89: =IF(F89="","",$E89 & "|" & F89) | M89: =IF(G89="","",$E89 & "|" & G89) | N89: =IF(H89="","",$E89 & "|" & H89) | O89: =IF(I89="","",$E89 & "|" & I89) | P89: =IF(J89="","",$E89 & "|" & J89)
A90: Changed | B90: ACTIVE | C90: Equity Securities - Common Stock | D90: yes | E90: A082_00 | L90: =IF(F90="","",$E90 & "|" & F90) | M90: =IF(G90="","",$E90 & "|" & G90) | N90: =IF(H90="","",$E90 & "|" & H90) | O90: =IF(I90="","",$E90 & "|" & I90) | P90: =IF(J90="","",$E90 & "|" & J90)
A91: Changed | B91: ACTIVE | C91: Equity Securities - Common Stock | D91: yes | E91: A082_00 | L91: =IF(F91="","",$E91 & "|" & F91) | M91: =IF(G91="","",$E91 & "|" & G91) | N91: =IF(H91="","",$E91 & "|" & H91) | O91: =IF(I91="","",$E91 & "|" & I91) | P91: =IF(J91="","",$E91 & "|" & J91)
A92: Changed | B92: ACTIVE | C92: Equity Securities - Common Stock | D92: yes | E92: A082_00 | L92: =IF(F92="","",$E92 & "|" & F92) | M92: =IF(G92="","",$E92 & "|" & G92) | N92: =IF(H92="","",$E92 & "|" & H92) | O92: =IF(I92="","",$E92 & "|" & I92) | P92: =IF(J92="","",$E92 & "|" & J92)
A93: Changed | B93: ACTIVE | C93: Equity Securities - Common Stock | D93: yes | E93: A082_00 | L93: =IF(F93="","",$E93 & "|" & F93) | M93: =IF(G93="","",$E93 & "|" & G93) | N93: =IF(H93="","",$E93 & "|" & H93) | O93: =IF(I93="","",$E93 & "|" & I93) | P93: =IF(J93="","",$E93 & "|" & J93)
A94: Changed | B94: ACTIVE | C94: Equity Securities - Common Stock | D94: yes | E94: A082_00 | L94: =IF(F94="","",$E94 & "|" & F94) | M94: =IF(G94="","",$E94 & "|" & G94) | N94: =IF(H94="","",$E94 & "|" & H94) | O94: =IF(I94="","",$E94 & "|" & I94) | P94: =IF(J94="","",$E94 & "|" & J94)
A95: Changed | B95: ACTIVE | C95: Equity Securities - Common Stock | D95: yes | E95: A082_00 | L95: =IF(F95="","",$E95 & "|" & F95) | M95: =IF(G95="","",$E95 & "|" & G95) | N95: =IF(H95="","",$E95 & "|" & H95) | O95: =IF(I95="","",$E95 & "|" & I95) | P95: =IF(J95="","",$E95 & "|" & J95)
A96: Changed | B96: ACTIVE | C96: Equity Securities - Common Stock | D96: yes | E96: A082_00 | L96: =IF(F96="","",$E96 & "|" & F96) | M96: =IF(G96="","",$E96 & "|" & G96) | N96: =IF(H96="","",$E96 & "|" & H96) | O96: =IF(I96="","",$E96 & "|" & I96) | P96: =IF(J96="","",$E96 & "|" & J96)
A97: Changed | B97: ACTIVE | C97: Equity Securities - Common Stock | D97: yes | E97: A082_00 | L97: =IF(F97="","",$E97 & "|" & F97) | M97: =IF(G97="","",$E97 & "|" & G97) | N97: =IF(H97="","",$E97 & "|" & H97) | O97: =IF(I97="","",$E97 & "|" & I97) | P97: =IF(J97="","",$E97 & "|" & J97)
A98: Changed | B98: ACTIVE | C98: Equity Securities - Common Stock | D98: yes | E98: A082_00 | L98: =IF(F98="","",$E98 & "|" & F98) | M98: =IF(G98="","",$E98 & "|" & G98) | N98: =IF(H98="","",$E98 & "|" & H98) | O98: =IF(I98="","",$E98 & "|" & I98) | P98: =IF(J98="","",$E98 & "|" & J98)
A99: Changed | B99: ACTIVE | C99: Equity Securities - Common Stock | D99: yes | E99: A082_00 | L99: =IF(F99="","",$E99 & "|" & F99) | M99: =IF(G99="","",$E99 & "|" & G99) | N99: =IF(H99="","",$E99 & "|" & H99) | O99: =IF(I99="","",$E99 & "|" & I99) | P99: =IF(J99="","",$E99 & "|" & J99)
A100: Changed | B100: ACTIVE | C100: Equity Securities - Common Stock | D100: yes | E100: A082_00 | L100: =IF(F100="","",$E100 & "|" & F100) | M100: =IF(G100="","",$E100 & "|" & G100) | N100: =IF(H100="","",$E100 & "|" & H100) | O100: =IF(I100="","",$E100 & "|" & I100) | P100: =IF(J100="","",$E100 & "|" & J100)
A101: Changed | B101: ACTIVE | C101: Equity Securities - Common Stock | D101: yes | E101: A082_00 | L101: =IF(F101="","",$E101 & "|" & F101) | M101: =IF(G101="","",$E101 & "|" & G101) | N101: =IF(H101="","",$E101 & "|" & H101) | O101: =IF(I101="","",$E101 & "|" & I101) | P101: =IF(J101="","",$E101 & "|" & J101)
... A127: Changed | B127: ACTIVE | C127: Equity Securities - Common Stock | D127: yes | E127: A082_00 | L127: =IF(F127="","",$E127 & "|" & F127) | M127: =IF(G127="","",$E127 & "|" & G127) | N127: =IF(H127="","",$E127 & "|" & H127) | O127: =IF(I127="","",$E127 & "|" & I127) | P127: =IF(J127="","",$E127 & "|" & J127)
A128: Changed | B128: ACTIVE | C128: Equity Securities - Open-end investment funds | E128: A090_00 | L128: =IF(F128="","",$E128 & "|" & F128) | M128: =IF(G128="","",$E128 & "|" & G128) | N128: =IF(H128="","",$E128 & "|" & H128) | O128: =IF(I128="","",$E128 & "|" & I128) | P128: =IF(J128="","",$E128 & "|" & J128)
A129: Changed | B129: ACTIVE | C129: Equity Securities - Open-end investment funds | E129: A090_00 | L129: =IF(F129="","",$E129 & "|" & F129) | M129: =IF(G129="","",$E129 & "|" & G129) | N129: =IF(H129="","",$E129 & "|" & H129) | O129: =IF(I129="","",$E129 & "|" & I129) | P129: =IF(J129="","",$E129 & "|" & J129)
A130: Changed | B130: ACTIVE | C130: Equity Securities - Open-end investment funds | E130: A090_00 | L130: =IF(F130="","",$E130 & "|" & F130) | M130: =IF(G130="","",$E130 & "|" & G130) | N130: =IF(H130="","",$E130 & "|" & H130) | O130: =IF(I130="","",$E130 & "|" & I130) | P130: =IF(J130="","",$E130 & "|" & J130)
A131: Changed | B131: ACTIVE | C131: Equity Securities - Open-end investment funds | E131: A090_00 | L131: =IF(F131="","",$E131 & "|" & F131) | M131: =IF(G131="","",$E131 & "|" & G131) | N131: =IF(H131="","",$E131 & "|" & H131) | O131: =IF(I131="","",$E131 & "|" & I131) | P131: =IF(J131="","",$E131 & "|" & J131)
A132: Changed | B132: ACTIVE | C132: Equity Securities - Open-end investment funds | E132: A090_00 | L132: =IF(F132="","",$E132 & "|" & F132) | M132: =IF(G132="","",$E132 & "|" & G132) | N132: =IF(H132="","",$E132 & "|" & H132) | O132: =IF(I132="","",$E132 & "|" & I132) | P132: =IF(J132="","",$E132 & "|" & J132)
A133: Changed | B133: ACTIVE | C133: Equity Securities - Open-end investment funds | E133: A090_00 | L133: =IF(F133="","",$E133 & "|" & F133) | M133: =IF(G133="","",$E133 & "|" & G133) | N133: =IF(H133="","",$E133 & "|" & H133) | O133: =IF(I133="","",$E133 & "|" & I133) | P133: =IF(J133="","",$E133 & "|" & J133)
A134: Changed | B134: ACTIVE | C134: Equity Securities - Open-end investment funds | E134: A090_00 | L134: =IF(F134="","",$E134 & "|" & F134) | M134: =IF(G134="","",$E134 & "|" & G134) | N134: =IF(H134="","",$E134 & "|" & H134) | O134: =IF(I134="","",$E134 & "|" & I134) | P134: =IF(J134="","",$E134 & "|" & J134)
A135: Changed | B135: ACTIVE | C135: Equity Securities - Open-end investment funds | E135: A090_00 | L135: =IF(F135="","",$E135 & "|" & F135) | M135: =IF(G135="","",$E135 & "|" & G135) | N135: =IF(H135="","",$E135 & "|" & H135) | O135: =IF(I135="","",$E135 & "|" & I135) | P135: =IF(J135="","",$E135 & "|" & J135)
A136: Changed | B136: ACTIVE | C136: Equity Securities - Open-end investment funds | E136: A090_00 | L136: =IF(F136="","",$E136 & "|" & F136) | M136: =IF(G136="","",$E136 & "|" & G136) | N136: =IF(H136="","",$E136 & "|" & H136) | O136: =IF(I136="","",$E136 & "|" & I136) | P136: =IF(J136="","",$E136 & "|" & J136)
A137: Changed | B137: ACTIVE | C137: Equity Securities - Open-end investment funds | E137: A090_00 | L137: =IF(F137="","",$E137 & "|" & F137) | M137: =IF(G137="","",$E137 & "|" & G137) | N137: =IF(H137="","",$E137 & "|" & H137) | O137: =IF(I137="","",$E137 & "|" & I137) | P137: =IF(J137="","",$E137 & "|" & J137)
A138: Changed | B138: ACTIVE | C138: Equity Securities - Open-end investment funds | E138: A090_00 | L138: =IF(F138="","",$E138 & "|" & F138) | M138: =IF(G138="","",$E138 & "|" & G138) | N138: =IF(H138="","",$E138 & "|" & H138) | O138: =IF(I138="","",$E138 & "|" & I138) | P138: =IF(J138="","",$E138 & "|" & J138)
A139: Changed | B139: ACTIVE | C139: Equity Securities - Open-end investment funds | E139: A090_00 | L139: =IF(F139="","",$E139 & "|" & F139) | M139: =IF(G139="","",$E139 & "|" & G139) | N139: =IF(H139="","",$E139 & "|" & H139) | O139: =IF(I139="","",$E139 & "|" & I139) | P139: =IF(J139="","",$E139 & "|" & J139)
... A151: Changed | B151: ACTIVE | C151: Equity Securities - Open-end investment funds | E151: A091_00 | L151: =IF(F151="","",$E151 & "|" & F151) | M151: =IF(G151="","",$E151 & "|" & G151) | N151: =IF(H151="","",$E151 & "|" & H151) | O151: =IF(I151="","",$E151 & "|" & I151) | P151: =IF(J151="","",$E151 & "|" & J151)
A152: Changed | B152: ACTIVE | C152: Equity Securities - Open-end investment funds | D152: yes | E152: A094_00 | L152: =IF(F152="","",$E152 & "|" & F152) | M152: =IF(G152="","",$E152 & "|" & G152) | N152: =IF(H152="","",$E152 & "|" & H152) | O152: =IF(I152="","",$E152 & "|" & I152) | P152: =IF(J152="","",$E152 & "|" & J152)
A153: Changed | B153: ACTIVE | C153: Equity Securities - Open-end investment funds | D153: yes | E153: A094_00 | L153: =IF(F153="","",$E153 & "|" & F153) | M153: =IF(G153="","",$E153 & "|" & G153) | N153: =IF(H153="","",$E153 & "|" & H153) | O153: =IF(I153="","",$E153 & "|" & I153) | P153: =IF(J153="","",$E153 & "|" & J153)
A154: Changed | B154: ACTIVE | C154: Equity Securities - Open-end investment funds | D154: yes | E154: A094_00 | L154: =IF(F154="","",$E154 & "|" & F154) | M154: =IF(G154="","",$E154 & "|" & G154) | N154: =IF(H154="","",$E154 & "|" & H154) | O154: =IF(I154="","",$E154 & "|" & I154) | P154: =IF(J154="","",$E154 & "|" & J154)
A155: Changed | B155: ACTIVE | C155: Equity Securities - Open-end investment funds | D155: yes | E155: A094_00 | L155: =IF(F155="","",$E155 & "|" & F155) | M155: =IF(G155="","",$E155 & "|" & G155) | N155: =IF(H155="","",$E155 & "|" & H155) | O155: =IF(I155="","",$E155 & "|" & I155) | P155: =IF(J155="","",$E155 & "|" & J155)
A156: Changed | B156: ACTIVE | C156: Equity Securities - Open-end investment funds | D156: yes | E156: A094_00 | L156: =IF(F156="","",$E156 & "|" & F156) | M156: =IF(G156="","",$E156 & "|" & G156) | N156: =IF(H156="","",$E156 & "|" & H156) | O156: =IF(I156="","",$E156 & "|" & I156) | P156: =IF(J156="","",$E156 & "|" & J156)
A157: Changed | B157: ACTIVE | C157: Equity Securities - Open-end investment funds | D157: yes | E157: A094_00 | L157: =IF(F157="","",$E157 & "|" & F157) | M157: =IF(G157="","",$E157 & "|" & G157) | N157: =IF(H157="","",$E157 & "|" & H157) | O157: =IF(I157="","",$E157 & "|" & I157) | P157: =IF(J157="","",$E157 & "|" & J157)
A158: Changed | B158: ACTIVE | C158: Equity Securities - Open-end investment funds | D158: yes | E158: A094_00
A159: Changed | B159: ACTIVE | C159: Equity Securities - Open-end investment funds | D159: yes | E159: A094_00
A160: Changed | B160: ACTIVE | C160: Equity Securities - Open-end investment funds | D160: yes | E160: A094_00
A161: Changed | B161: ACTIVE | C161: Equity Securities - Open-end investment funds | D161: yes | E161: A094_00
A162: Changed | B162: ACTIVE | C162: Equity Securities - Open-end investment funds | D162: yes | E162: A094_00
A163: Changed | B163: ACTIVE | C163: Equity Securities - Open-end investment funds | D163: yes | E163: A094_00
A164: Changed | B164: ACTIVE | C164: Equity Securities - Open-end investment funds | D164: yes | E164: A094_00
A165: Changed | B165: ACTIVE | C165: Equity Securities - Open-end investment funds | D165: yes | E165: A094_00
A166: Changed | B166: ACTIVE | C166: Equity Securities - Open-end investment funds | D166: yes | E166: A094_00
A167: Changed | B167: ACTIVE | C167: Equity Securities - Open-end investment funds | D167: yes | E167: A094_00
A168: Changed | B168: ACTIVE | C168: Equity Securities - Open-end investment funds | D168: yes | E168: A094_00
A169: Changed | B169: ACTIVE | C169: Equity Securities - Open-end investment funds | D169: yes | E169: A094_00
... A179: Changed | B179: ACTIVE | C179: Equity Securities - Open-end investment funds | D179: yes | E179: A094_00
A180: Changed | B180: ACTIVE | C180: Equity Securities - Open-end investment funds | E180: A096_00
A181: Changed | B181: ACTIVE | C181: Equity Securities - Open-end investment funds | E181: A096_00
A182: Changed | B182: ACTIVE | C182: Equity Securities - Open-end investment funds | E182: A096_00
A183: Changed | B183: ACTIVE | C183: Equity Securities - Open-end investment funds | E183: A096_00
A184: Changed | B184: ACTIVE | C184: Equity Securities - Open-end investment funds | E184: A096_00
A185: Changed | B185: ACTIVE | C185: Equity Securities - Open-end investment funds | E185: A096_00
A186: Changed | B186: ACTIVE | C186: Equity Securities - Open-end investment funds | E186: A096_00
A187: Changed | B187: ACTIVE | C187: Equity Securities - Open-end investment funds | E187: A096_00
A188: Changed | B188: ACTIVE | C188: Equity Securities - Open-end investment funds | E188: A096_00
A189: Changed | B189: ACTIVE | C189: Equity Securities - Open-end investment funds | E189: A096_00
A190: Changed | B190: ACTIVE | C190: Equity Securities - Open-end investment funds | E190: A096_00
A191: Changed | B191: ACTIVE | C191: Equity Securities - Open-end investment funds | E191: A096_00
... A241: Changed | B241: ACTIVE | C241: Debt Securities - Amortized cost | E241: A102_00
A242: Changed | B242: ACTIVE | C242: FVPL debts | D242: yes | E242: A114_00
A243: Changed | B243: ACTIVE | C243: FVPL debts | D243: yes | E243: A114_00
A244: Changed | B244: ACTIVE | C244: FVPL debts | D244: yes | E244: A114_00
A245: Changed | B245: ACTIVE | C245: FVPL debts | D245: yes | E245: A114_00
A246: Changed | B246: ACTIVE | C246: FVPL debts | D246: yes | E246: A114_00
A247: Changed | B247: ACTIVE | C247: FVPL debts | D247: yes | E247: A114_00
A248: Changed | B248: ACTIVE | C248: FVPL debts | D248: yes | E248: A114_00
A249: Changed | B249: ACTIVE | C249: FVPL debts | D249: yes | E249: A114_00
A250: Changed | B250: ACTIVE | C250: FVPL debts | D250: yes | E250: A114_00
A251: Changed | B251: ACTIVE | C251: FVPL debts | D251: yes | E251: A114_00
A252: Changed | B252: ACTIVE | C252: FVPL debts | D252: yes | E252: A114_00
A253: Changed | B253: ACTIVE | C253: FVPL debts | D253: yes | E253: A114_00
... A285: Changed | B285: ACTIVE | C285: FVPL debts | D285: yes | E285: A114_00
A286: Changed | B286: ACTIVE | C286: Real Estate held for Investment | E286: A137_00
A287: Changed | B287: ACTIVE | C287: Real Estate held for Investment | E287: A137_00
A288: Changed | B288: ACTIVE | C288: Real Estate held for Investment | E288: A138_00
A289: Changed | B289: ACTIVE | C289: Real Estate held for Investment | E289: A138_00
...

Sheet cross checks all yellow
A2: Type of change | B2: Status | C2: Category | D2: Sense Check | E2: X-Check No. | F2: Reference X-Check (Condition) | G2: Applicable Quarters | H2: Included RUs | I2: Excluded RUs | J2: Reference X-Check (Limit, %) | L2: Reference X-Check (Condition) | M2: Applicable Quarters | N2: Included RUs | O2: Excluded RUs | P2: Reference X-Check (Limit, %)
A3: New xcheck or association | B3: ACTIVE | C3: FINMA statistical information | E3: SR051_00 | G3: CON_Q2_Q4 | L3: =IF(F3="","",$E3 & "|" & F3) | M3: =IF(G3="","",$E3 & "|" & G3) -> SR051_00|CON_Q2_Q4 | N3: =IF(H3="","",$E3 & "|" & H3) | O3: =IF(I3="","",$E3 & "|" & I3) | P3: =IF(J3="","",$E3 & "|" & J3)
A4: New xcheck or association | B4: ACTIVE | C4: FINMA statistical information | D4: yes | E4: SR116_00 | G4: CON_Q2_Q4 | L4: =IF(F4="","",$E4 & "|" & F4) | M4: =IF(G4="","",$E4 & "|" & G4) -> SR116_00|CON_Q2_Q4 | N4: =IF(H4="","",$E4 & "|" & H4) | O4: =IF(I4="","",$E4 & "|" & I4) | P4: =IF(J4="","",$E4 & "|" & J4)
A5: New xcheck or association | B5: ACTIVE | C5: FINMA statistical information | D5: yes | E5: SR117_00 | G5: CON_Q2_Q4 | L5: =IF(F5="","",$E5 & "|" & F5) | M5: =IF(G5="","",$E5 & "|" & G5) -> SR117_00|CON_Q2_Q4 | N5: =IF(H5="","",$E5 & "|" & H5) | O5: =IF(I5="","",$E5 & "|" & I5) | P5: =IF(J5="","",$E5 & "|" & J5)
A6: Changed | B6: ACTIVE | C6: IFRS 17 - BBA LRC CSM | E6: AS004_17 | G6: CON_Q3_Q4 | L6: =IF(F6="","",$E6 & "|" & F6) | M6: =IF(G6="","",$E6 & "|" & G6) -> AS004_17|CON_Q3_Q4 | N6: =IF(H6="","",$E6 & "|" & H6) | O6: =IF(I6="","",$E6 & "|" & I6) | P6: =IF(J6="","",$E6 & "|" & J6)
A7: Changed | B7: ACTIVE | C7: IFRS 13 - level 1,2,3 | E7: AS133_00 | G7: CON_Q4 | L7: =IF(F7="","",$E7 & "|" & F7) | M7: =IF(G7="","",$E7 & "|" & G7) -> AS133_00|CON_Q4 | N7: =IF(H7="","",$E7 & "|" & H7) | O7: =IF(I7="","",$E7 & "|" & I7) | P7: =IF(J7="","",$E7 & "|" & J7)
A8: Changed | B8: ACTIVE | C8: IFRS 13 - level 1,2,3 | E8: AS137_00 | G8: CON_Q4 | L8: =IF(F8="","",$E8 & "|" & F8) | M8: =IF(G8="","",$E8 & "|" & G8) -> AS137_00|CON_Q4 | N8: =IF(H8="","",$E8 & "|" & H8) | O8: =IF(I8="","",$E8 & "|" & I8) | P8: =IF(J8="","",$E8 & "|" & J8)
A9: Changed | B9: ACTIVE | C9: IFRS 13 - level 1,2,3 | E9: AS139_00 | G9: CON_Q4 | L9: =IF(F9="","",$E9 & "|" & F9) | M9: =IF(G9="","",$E9 & "|" & G9) -> AS139_00|CON_Q4 | N9: =IF(H9="","",$E9 & "|" & H9) | O9: =IF(I9="","",$E9 & "|" & I9) | P9: =IF(J9="","",$E9 & "|" & J9)
A10: Changed | B10: ACTIVE | C10: IFRS 13 - level 1,2,3 | E10: AS142_00 | G10: CON_Q4 | L10: =IF(F10="","",$E10 & "|" & F10) | M10: =IF(G10="","",$E10 & "|" & G10) -> AS142_00|CON_Q4 | N10: =IF(H10="","",$E10 & "|" & H10) | O10: =IF(I10="","",$E10 & "|" & I10) | P10: =IF(J10="","",$E10 & "|" & J10)
A11: Changed | B11: ACTIVE | C11: IFRS 13 - level 1,2,3 | E11: AS168_00 | G11: CON_Q4 | L11: =IF(F11="","",$E11 & "|" & F11) | M11: =IF(G11="","",$E11 & "|" & G11) -> AS168_00|CON_Q4 | N11: =IF(H11="","",$E11 & "|" & H11) | O11: =IF(I11="","",$E11 & "|" & I11) | P11: =IF(J11="","",$E11 & "|" & J11)
A12: Changed | B12: ACTIVE | C12: IFRS 17 - BBA LRC CSM | E12: LS013_17 | G12: CON_Q3_Q4 | L12: =IF(F12="","",$E12 & "|" & F12) | M12: =IF(G12="","",$E12 & "|" & G12) -> LS013_17|CON_Q3_Q4 | N12: =IF(H12="","",$E12 & "|" & H12) | O12: =IF(I12="","",$E12 & "|" & I12) | P12: =IF(J12="","",$E12 & "|" & J12)
A13: Changed | B13: ACTIVE | C13: IFRS 13 - level 1,2,3 | E13: LS142_00 | G13: CON_Q4 | L13: =IF(F13="","",$E13 & "|" & F13) | M13: =IF(G13="","",$E13 & "|" & G13) -> LS142_00|CON_Q4 | N13: =IF(H13="","",$E13 & "|" & H13) | O13: =IF(I13="","",$E13 & "|" & I13) | P13: =IF(J13="","",$E13 & "|" & J13)
A14: Changed | B14: ACTIVE | C14: IFRS 13 - level 1,2,3 | E14: S281_00 | G14: CON_Q4 | L14: =IF(F14="","",$E14 & "|" & F14) | M14: =IF(G14="","",$E14 & "|" & G14) -> S281_00|CON_Q4 | N14: =IF(H14="","",$E14 & "|" & H14) | O14: =IF(I14="","",$E14 & "|" & I14) | P14: =IF(J14="","",$E14 & "|" & J14)
A15: Changed | B15: ACTIVE | C15: IFRS 13 - level 1,2,3 | E15: S285_00 | G15: CON_Q4 | L15: =IF(F15="","",$E15 & "|" & F15) | M15: =IF(G15="","",$E15 & "|" & G15) -> S285_00|CON_Q4 | N15: =IF(H15="","",$E15 & "|" & H15) | O15: =IF(I15="","",$E15 & "|" & I15) | P15: =IF(J15="","",$E15 & "|" & J15)
A16: Changed | B16: ACTIVE | C16: IFRS 13 - level 1,2,3 | E16: S287_00 | G16: CON_Q4 | L16: =IF(F16="","",$E16 & "|" & F16) | M16: =IF(G16="","",$E16 & "|" & G16) -> S287_00|CON_Q4 | N16: =IF(H16="","",$E16 & "|" & H16) | O16: =IF(I16="","",$E16 & "|" & I16) | P16: =IF(J16="","",$E16 & "|" & J16)
A17: Changed | B17: ACTIVE | C17: IFRS 13 - level 1,2,3 | E17: S289_00 | G17: CON_Q4 | L17: =IF(F17="","",$E17 & "|" & F17) | M17: =IF(G17="","",$E17 & "|" & G17) -> S289_00|CON_Q4 | N17: =IF(H17="","",$E17 & "|" & H17) | O17: =IF(I17="","",$E17 & "|" & I17) | P17: =IF(J17="","",$E17 & "|" & J17)
... A20: Changed | B20: ACTIVE | C20: IFRS 13 - level 1,2,3 | E20: S463_00 | G20: CON_Q4 | L20: =IF(F20="","",$E20 & "|" & F20) | M20: =IF(G20="","",$E20 & "|" & G20) -> S463_00|CON_Q4 | N20: =IF(H20="","",$E20 & "|" & H20) | O20: =IF(I20="","",$E20 & "|" & I20) | P20: =IF(J20="","",$E20 & "|" & J20)

Sheet comparison
A1: EBX Data | B1: FIP Data | C1: Comparison
A2: SR051_00|CON_Q2_Q4 | B2: =VLOOKUP(A2,'FIP Conditions'!$A:$A,1,FALSE) -> SR051_00|CON_Q2_Q4 | C2: =A2=B2 -> TRUE
A3: SR116_00|CON_Q2_Q4 | B3: =VLOOKUP(A3,'FIP Conditions'!$A:$A,1,FALSE) -> SR116_00|CON_Q2_Q4 | C3: =A3=B3 -> TRUE
A4: SR117_00|CON_Q2_Q4 | B4: =VLOOKUP(A4,'FIP Conditions'!$A:$A,1,FALSE) -> SR117_00|CON_Q2_Q4 | C4: =A4=B4 -> TRUE
A5: AS004_17|CON_Q3_Q4 | B5: =VLOOKUP(A5,'FIP Conditions'!$A:$A,1,FALSE) -> AS004_17|CON_Q3_Q4 | C5: =A5=B5 -> TRUE
A6: AS133_00|CON_Q4 | B6: =VLOOKUP(A6,'FIP Conditions'!$A:$A,1,FALSE) -> AS133_00|CON_Q4 | C6: =A6=B6 -> TRUE
A7: AS137_00|CON_Q4 | B7: =VLOOKUP(A7,'FIP Conditions'!$A:$A,1,FALSE) -> AS137_00|CON_Q4 | C7: =A7=B7 -> TRUE
A8: AS139_00|CON_Q4 | B8: =VLOOKUP(A8,'FIP Conditions'!$A:$A,1,FALSE) -> AS139_00|CON_Q4 | C8: =A8=B8 -> TRUE
A9: AS142_00|CON_Q4 | B9: =VLOOKUP(A9,'FIP Conditions'!$A:$A,1,FALSE) -> AS142_00|CON_Q4 | C9: =A9=B9 -> TRUE
A10: AS168_00|CON_Q4 | B10: =VLOOKUP(A10,'FIP Conditions'!$A:$A,1,FALSE) -> AS168_00|CON_Q4 | C10: =A10=B10 -> TRUE
A11: LS013_17|CON_Q3_Q4 | B11: =VLOOKUP(A11,'FIP Conditions'!$A:$A,1,FALSE) -> LS013_17|CON_Q3_Q4 | C11: =A11=B11 -> TRUE
A12: LS142_00|CON_Q4 | B12: =VLOOKUP(A12,'FIP Conditions'!$A:$A,1,FALSE) -> LS142_00|CON_Q4 | C12: =A12=B12 -> TRUE
A13: S281_00|CON_Q4 | B13: =VLOOKUP(A13,'FIP Conditions'!$A:$A,1,FALSE) -> S281_00|CON_Q4 | C13: =A13=B13 -> TRUE
... A19: S463_00|CON_Q4 | B19: =VLOOKUP(A19,'FIP Conditions'!$A:$A,1,FALSE) -> S463_00|CON_Q4 | C19: =A19=B19 -> TRUE
